Workbook

Sheet Demand Base Matrix
A1: Customer Journey Stage | B1: Stage | C1: Role | D1: Project Start M0 | E1: Project Start M1 | F1: Project Mid | G1: Project End M-1 | H1: Project End M0 | I1: Project End M1 | J1: Project End M1+ | N1: VIBE Tag | O1: Role | P1: Project Start M0 | Q1: Project Start M1 | R1: Project Mid | S1: Project End M-1 | T1: Project End M0 | U1: Project End M1 | V1: Project End M1+
A2: Validate | B2: Discovery and App Go-Live | C2: PM | D2: 10 | E2: 10 | F2: 2 | G2: 0 | H2: 0 | I2: 0 | J2: 0 | K2: LM Bucket | L2: Multiplier | N2: Bond | O2: PM | P2: =SUMIFS(D$2:D$91,$A$2:$A$91,$N2,$C$2:$C$91,$O2) -> 10 | Q2: =SUMIFS(E$2:E$91,$A$2:$A$91,$N2,$C$2:$C$91,$O2) -> 10 | R2: =SUMIFS(F$2:F$91,$A$2:$A$91,$N2,$C$2:$C$91,$O2) -> 10 | S2: =SUMIFS(G$2:G$91,$A$2:$A$91,$N2,$C$2:$C$91,$O2) -> 50 | T2: =SUMIFS(H$2:H$91,$A$2:$A$91,$N2,$C$2:$C$91,$O2) -> 28 | U2: =SUMIFS(I$2:I$91,$A$2:$A$91,$N2,$C$2:$C$91,$O2) -> 8 | V2: =SUMIFS(J$2:J$91,$A$2:$A$91,$N2,$C$2:$C$91,$O2) -> 8 | X2: Final Multiplier Chart | AF2: Orbit A | AG2: Orbit B | AH2: Orbit C&D | AJ2: LMs | AK2: Multiplier | AL2: Dx/Tx | AM2: Multiplier | AN2: Non-Standard Data | AO2: Multiplier | AP2: Non-Standard Metric | AQ2: Multiplier | AR2: IVMS Configuration | AS2: Multiplier
A3: Validate | B3: Imagery Planning, Decisioning & Acquision | C3: PM | D3: 5 | E3: 5 | F3: 5 | G3: 0 | H3: 0 | I3: 0 | J3: 0 | K3: 1000 | L3: 0.75 | N3: Explore | O3: PM | P3: =SUMIFS(D$2:D$91,$A$2:$A$91,$N3,$C$2:$C$91,$O3) -> 15 | Q3: =SUMIFS(E$2:E$91,$A$2:$A$91,$N3,$C$2:$C$91,$O3) -> 30 | R3: =SUMIFS(F$2:F$91,$A$2:$A$91,$N3,$C$2:$C$91,$O3) -> 10 | S3: =SUMIFS(G$2:G$91,$A$2:$A$91,$N3,$C$2:$C$91,$O3) -> 40 | T3: =SUMIFS(H$2:H$91,$A$2:$A$91,$N3,$C$2:$C$91,$O3) -> 40 | U3: =SUMIFS(I$2:I$91,$A$2:$A$91,$N3,$C$2:$C$91,$O3) -> 10 | V3: =SUMIFS(J$2:J$91,$A$2:$A$91,$N3,$C$2:$C$91,$O3) -> 5 | AE3: Validate | AF3: 1.75 | AG3: 1.5 | AH3: 1 | AJ3: 1000 | AK3: 0.75 | AL3: Dx | AM3: 1 | AN3: High | AO3: 1.5 | AP3: High | AQ3: 2 | AR3: High | AS3: 2
A4: Validate | B4: GIS - Correction / Validation | C4: PM | D4: 0 | E4: 0 | F4: 0 | G4: 20 | H4: 0 | I4: 0 | J4: 0 | K4: 5000 | L4: 1 | N4: Integrate | O4: PM | P4: =SUMIFS(D$2:D$91,$A$2:$A$91,$N4,$C$2:$C$91,$O4) -> 10 | Q4: =SUMIFS(E$2:E$91,$A$2:$A$91,$N4,$C$2:$C$91,$O4) -> 20 | R4: =SUMIFS(F$2:F$91,$A$2:$A$91,$N4,$C$2:$C$91,$O4) -> 10 | S4: =SUMIFS(G$2:G$91,$A$2:$A$91,$N4,$C$2:$C$91,$O4) -> 60 | T4: =SUMIFS(H$2:H$91,$A$2:$A$91,$N4,$C$2:$C$91,$O4) -> 28 | U4: =SUMIFS(I$2:I$91,$A$2:$A$91,$N4,$C$2:$C$91,$O4) -> 8 | V4: =SUMIFS(J$2:J$91,$A$2:$A$91,$N4,$C$2:$C$91,$O4) -> 8 | AE4: Integrate | AF4: 1.25 | AG4: 1 | AH4: 0.8 | AJ4: 5000 | AK4: 1 | AL4: Tx | AM4: 1.5 | AN4: Medium | AO4: 1.25 | AP4: Medium | AQ4: 1.5 | AR4: Medium | AS4: 1.5
A5: Validate | B5: Model Run | C5: PM | D5: 0 | E5: 0 | F5: 0 | G5: 20 | H5: 0 | I5: 0 | J5: 0 | K5: 10000 | L5: 1.25 | N5: Validate | O5: PM | P5: =SUMIFS(D$2:D$91,$A$2:$A$91,$N5,$C$2:$C$91,$O5) -> 15 | Q5: =SUMIFS(E$2:E$91,$A$2:$A$91,$N5,$C$2:$C$91,$O5) -> 15 | R5: =SUMIFS(F$2:F$91,$A$2:$A$91,$N5,$C$2:$C$91,$O5) -> 7 | S5: =SUMIFS(G$2:G$91,$A$2:$A$91,$N5,$C$2:$C$91,$O5) -> 40 | T5: =SUMIFS(H$2:H$91,$A$2:$A$91,$N5,$C$2:$C$91,$O5) -> 60 | U5: =SUMIFS(I$2:I$91,$A$2:$A$91,$N5,$C$2:$C$91,$O5) -> 10 | V5: =SUMIFS(J$2:J$91,$A$2:$A$91,$N5,$C$2:$C$91,$O5) -> 4 | Y5: Validate | Z5: A | AA5: 1.75 | AE5: Bond | AF5: 1.225 | AG5: 1.05 | AH5: 0.7 | AJ5: 10000 | AK5: 1.25 | AN5: Low | AO5: 1 | AP5: Low | AQ5: 1 | AR5: Low | AS5: 1
A6: Validate | B6: Analysis | C6: PM | D6: 0 | E6: 0 | F6: 0 | G6: 0 | H6: 40 | I6: 0 | J6: 0 | K6: 25000 | L6: 1.5 | N6: Bond | O6: CSM | P6: =SUMIFS(D$2:D$91,$A$2:$A$91,$N6,$C$2:$C$91,$O6) -> 5 | Q6: =SUMIFS(E$2:E$91,$A$2:$A$91,$N6,$C$2:$C$91,$O6) -> 5 | R6: =SUMIFS(F$2:F$91,$A$2:$A$91,$N6,$C$2:$C$91,$O6) -> 5 | S6: =SUMIFS(G$2:G$91,$A$2:$A$91,$N6,$C$2:$C$91,$O6) -> 10 | T6: =SUMIFS(H$2:H$91,$A$2:$A$91,$N6,$C$2:$C$91,$O6) -> 19 | U6: =SUMIFS(I$2:I$91,$A$2:$A$91,$N6,$C$2:$C$91,$O6) -> 11 | V6: =SUMIFS(J$2:J$91,$A$2:$A$91,$N6,$C$2:$C$91,$O6) -> 1 | Y6: Integrate | Z6: A | AA6: 1.25 | AE6: Explore | AF6: 1.75 | AG6: 1.5 | AH6: 1 | AJ6: 25000 | AK6: 1.5
A7: Validate | B7: Results Presentation and Change Management | C7: PM | D7: 0 | E7: 0 | F7: 0 | G7: 0 | H7: 10 | I7: 0 | J7: 0 | K7: 100000 | L7: 2 | N7: Explore | O7: CSM | P7: =SUMIFS(D$2:D$91,$A$2:$A$91,$N7,$C$2:$C$91,$O7) -> 20 | Q7: =SUMIFS(E$2:E$91,$A$2:$A$91,$N7,$C$2:$C$91,$O7) -> 10 | R7: =SUMIFS(F$2:F$91,$A$2:$A$91,$N7,$C$2:$C$91,$O7) -> 20 | S7: =SUMIFS(G$2:G$91,$A$2:$A$91,$N7,$C$2:$C$91,$O7) -> 5 | T7: =SUMIFS(H$2:H$91,$A$2:$A$91,$N7,$C$2:$C$91,$O7) -> 60 | U7: =SUMIFS(I$2:I$91,$A$2:$A$91,$N7,$C$2:$C$91,$O7) -> 20 | V7: =SUMIFS(J$2:J$91,$A$2:$A$91,$N7,$C$2:$C$91,$O7) -> 10 | Y7: Bond | Z7: A | AA7: 1.225 | AJ7: 100000 | AK7: 2
A8: Validate | B8: Ongoing - Adoption Support | C8: PM | D8: 0 | E8: 0 | F8: 0 | G8: 0 | H8: 10 | I8: 10 | J8: 4 | N8: Integrate | O8: CSM | P8: =SUMIFS(D$2:D$91,$A$2:$A$91,$N8,$C$2:$C$91,$O8) -> 27 | Q8: =SUMIFS(E$2:E$91,$A$2:$A$91,$N8,$C$2:$C$91,$O8) -> 30 | R8: =SUMIFS(F$2:F$91,$A$2:$A$91,$N8,$C$2:$C$91,$O8) -> 36 | S8: =SUMIFS(G$2:G$91,$A$2:$A$91,$N8,$C$2:$C$91,$O8) -> 20 | T8: =SUMIFS(H$2:H$91,$A$2:$A$91,$N8,$C$2:$C$91,$O8) -> 38 | U8: =SUMIFS(I$2:I$91,$A$2:$A$91,$N8,$C$2:$C$91,$O8) -> 24 | V8: =SUMIFS(J$2:J$91,$A$2:$A$91,$N8,$C$2:$C$91,$O8) -> 24 | Y8: Explore | Z8: A | AA8: 1.75
A9: Validate | B9: Sales Handover + Kick off | C9: CSM | D9: 3 | E9: 0 | F9: 0 | G9: 0 | H9: 0 | I9: 0 | J9: 0 | N9: Validate | O9: CSM | P9: =SUMIFS(D$2:D$91,$A$2:$A$91,$N9,$C$2:$C$91,$O9) -> 16 | Q9: =SUMIFS(E$2:E$91,$A$2:$A$91,$N9,$C$2:$C$91,$O9) -> 24 | R9: =SUMIFS(F$2:F$91,$A$2:$A$91,$N9,$C$2:$C$91,$O9) -> 14 | S9: =SUMIFS(G$2:G$91,$A$2:$A$91,$N9,$C$2:$C$91,$O9) -> 15 | T9: =SUMIFS(H$2:H$91,$A$2:$A$91,$N9,$C$2:$C$91,$O9) -> 37 | U9: =SUMIFS(I$2:I$91,$A$2:$A$91,$N9,$C$2:$C$91,$O9) -> 19 | V9: =SUMIFS(J$2:J$91,$A$2:$A$91,$N9,$C$2:$C$91,$O9) -> 0 | Y9: Validate | Z9: B | AA9: 1.5
A10: Validate | B10: Discovery + Imagery | C10: CSM | D10: 8 | E10: 8 | F10: 0 | G10: 0 | H10: 0 | I10: 0 | J10: 0 | N10: Bond | O10: Analyst 1 | P10: =SUMIFS(D$2:D$91,$A$2:$A$91,$N10,$C$2:$C$91,"Analyst") -> 10 | Q10: =SUMIFS(E$2:E$91,$A$2:$A$91,$N10,$C$2:$C$91,"Analyst") -> 12 | R10: =SUMIFS(F$2:F$91,$A$2:$A$91,$N10,$C$2:$C$91,"Analyst") -> 11 | S10: =SUMIFS(G$2:G$91,$A$2:$A$91,$N10,$C$2:$C$91,"Analyst") -> 0 | T10: =SUMIFS(H$2:H$91,$A$2:$A$91,$N10,$C$2:$C$91,"Analyst") -> 89 | U10: =SUMIFS(I$2:I$91,$A$2:$A$91,$N10,$C$2:$C$91,"Analyst") -> 20 | V10: =SUMIFS(J$2:J$91,$A$2:$A$91,$N10,$C$2:$C$91,"Analyst") -> 1 | Y10: Integrate | Z10: B | AA10: 1
A11: Validate | B11: Business Case | C11: CSM | D11: 0 | E11: 1 | F11: 4 | G11: 0 | H11: 0 | I11: 0 | J11: 0 | N11: Explore | O11: Analyst 1 | P11: =SUMIFS(D$2:D$91,$A$2:$A$91,$N11,$C$2:$C$91,"Analyst") -> 0 | Q11: =SUMIFS(E$2:E$91,$A$2:$A$91,$N11,$C$2:$C$91,"Analyst") -> 0 | R11: =SUMIFS(F$2:F$91,$A$2:$A$91,$N11,$C$2:$C$91,"Analyst") -> 0 | S11: =SUMIFS(G$2:G$91,$A$2:$A$91,$N11,$C$2:$C$91,"Analyst") -> 0 | T11: =SUMIFS(H$2:H$91,$A$2:$A$91,$N11,$C$2:$C$91,"Analyst") -> 0 | U11: =SUMIFS(I$2:I$91,$A$2:$A$91,$N11,$C$2:$C$91,"Analyst") -> 0 | V11: =SUMIFS(J$2:J$91,$A$2:$A$91,$N11,$C$2:$C$91,"Analyst") -> 0 | Y11: Bond | Z11: B | AA11: 1.05
A12: Validate | B12: App Go Live + Confirm Requirements | C12: CSM | D12: 0 | E12: 10 | F12: 0 | G12: 0 | H12: 0 | I12: 0 | J12: 0 | L12: PS Work | N12: Integrate | O12: Analyst 1 | P12: =SUMIFS(D$2:D$91,$A$2:$A$91,$N12,$C$2:$C$91,"Analyst") -> 20 | Q12: =SUMIFS(E$2:E$91,$A$2:$A$91,$N12,$C$2:$C$91,"Analyst") -> 22 | R12: =SUMIFS(F$2:F$91,$A$2:$A$91,$N12,$C$2:$C$91,"Analyst") -> 11 | S12: =SUMIFS(G$2:G$91,$A$2:$A$91,$N12,$C$2:$C$91,"Analyst") -> 0 | T12: =SUMIFS(H$2:H$91,$A$2:$A$91,$N12,$C$2:$C$91,"Analyst") -> 89 | U12: =SUMIFS(I$2:I$91,$A$2:$A$91,$N12,$C$2:$C$91,"Analyst") -> 20 | V12: =SUMIFS(J$2:J$91,$A$2:$A$91,$N12,$C$2:$C$91,"Analyst") -> 1 | Y12: Explore | Z12: B | AA12: 1.5
A13: Validate | B13: Analysis | C13: CSM | D13: 0 | E13: 0 | F13: 5 | G13: 10 | H13: 0 | I13: 0 | J13: 0 | L13: Validate as a multiplier | N13: Validate | O13: Analyst 1 | P13: =SUMIFS(D$2:D$91,$A$2:$A$91,$N13,$C$2:$C$91,"Analyst") -> 30 | Q13: =SUMIFS(E$2:E$91,$A$2:$A$91,$N13,$C$2:$C$91,"Analyst") -> 22 | R13: =SUMIFS(F$2:F$91,$A$2:$A$91,$N13,$C$2:$C$91,"Analyst") -> 12 | S13: =SUMIFS(G$2:G$91,$A$2:$A$91,$N13,$C$2:$C$91,"Analyst") -> 0 | T13: =SUMIFS(H$2:H$91,$A$2:$A$91,$N13,$C$2:$C$91,"Analyst") -> 89 | U13: =SUMIFS(I$2:I$91,$A$2:$A$91,$N13,$C$2:$C$91,"Analyst") -> 20 | V13: =SUMIFS(J$2:J$91,$A$2:$A$91,$N13,$C$2:$C$91,"Analyst") -> 1 | Y13: Validate | Z13: C | AA13: 1
A14: Validate | B14: Insights & Recs + FV | C14: CSM | D14: 0 | E14: 0 | F14: 0 | G14: 0 | H14: 32 | I14: 0 | J14: 0 | K14: not sure of bond? | N14: Bond | O14: Analyst 2 | P14: =SUMIFS(D$2:D$91,$A$2:$A$91,$N14,$C$2:$C$91,"Analyst") -> 10 | Q14: =SUMIFS(E$2:E$91,$A$2:$A$91,$N14,$C$2:$C$91,"Analyst") -> 12 | R14: =SUMIFS(F$2:F$91,$A$2:$A$91,$N14,$C$2:$C$91,"Analyst") -> 11 | S14: =SUMIFS(G$2:G$91,$A$2:$A$91,$N14,$C$2:$C$91,"Analyst") -> 0 | T14: =SUMIFS(H$2:H$91,$A$2:$A$91,$N14,$C$2:$C$91,"Analyst") -> 89 | U14: =SUMIFS(I$2:I$91,$A$2:$A$91,$N14,$C$2:$C$91,"Analyst") -> 20 | V14: =SUMIFS(J$2:J$91,$A$2:$A$91,$N14,$C$2:$C$91,"Analyst") -> 1 | Y14: Integrate | Z14: C | AA14: 0.8
A15: Validate | B15: Change Management + Conversion | C15: CSM | D15: 5 | E15: 5 | F15: 5 | G15: 5 | H15: 5 | I15: 19 | J15: 0 | K15: {=SUM(D9:E15,G9:J15)+SUM(F9:F15*6)} -> 195 | L15: =K15*1.75 -> 341.25 | N15: Explore | O15: Analyst 2 | P15: =SUMIFS(D$2:D$91,$A$2:$A$91,$N15,$C$2:$C$91,"Analyst") -> 0 | Q15: =SUMIFS(E$2:E$91,$A$2:$A$91,$N15,$C$2:$C$91,"Analyst") -> 0 | R15: =SUMIFS(F$2:F$91,$A$2:$A$91,$N15,$C$2:$C$91,"Analyst") -> 0 | S15: =SUMIFS(G$2:G$91,$A$2:$A$91,$N15,$C$2:$C$91,"Analyst") -> 0 | T15: =SUMIFS(H$2:H$91,$A$2:$A$91,$N15,$C$2:$C$91,"Analyst") -> 0 | U15: =SUMIFS(I$2:I$91,$A$2:$A$91,$N15,$C$2:$C$91,"Analyst") -> 0 | V15: =SUMIFS(J$2:J$91,$A$2:$A$91,$N15,$C$2:$C$91,"Analyst") -> 0 | Y15: Bond | Z15: C | AA15: 0.7
A16: Validate | B16: Discovery, Original Shapefile Ingestion App Go-Live & Data QC | C16: Analyst | D16: 30 | E16: 10 | F16: 1 | G16: 0 | H16: 0 | I16: 0 | J16: 0 | N16: Integrate | O16: Analyst 2 | P16: =SUMIFS(D$2:D$91,$A$2:$A$91,$N16,$C$2:$C$91,"Analyst") -> 20 | Q16: =SUMIFS(E$2:E$91,$A$2:$A$91,$N16,$C$2:$C$91,"Analyst") -> 22 | R16: =SUMIFS(F$2:F$91,$A$2:$A$91,$N16,$C$2:$C$91,"Analyst") -> 11 | S16: =SUMIFS(G$2:G$91,$A$2:$A$91,$N16,$C$2:$C$91,"Analyst") -> 0 | T16: =SUMIFS(H$2:H$91,$A$2:$A$91,$N16,$C$2:$C$91,"Analyst") -> 89 | U16: =SUMIFS(I$2:I$91,$A$2:$A$91,$N16,$C$2:$C$91,"Analyst") -> 20 | V16: =SUMIFS(J$2:J$91,$A$2:$A$91,$N16,$C$2:$C$91,"Analyst") -> 1 | Y16: Explore | Z16: C | AA16: 1
A17: Validate | B17: Imagery Planning, Decisioning & Acquision | C17: Analyst | D17: 0 | E17: 12 | F17: 1 | G17: 0 | H17: 0 | I17: 0 | J17: 0 | N17: Validate | O17: Analyst 2 | P17: =SUMIFS(D$2:D$91,$A$2:$A$91,$N17,$C$2:$C$91,"Analyst") -> 30 | Q17: =SUMIFS(E$2:E$91,$A$2:$A$91,$N17,$C$2:$C$91,"Analyst") -> 22 | R17: =SUMIFS(F$2:F$91,$A$2:$A$91,$N17,$C$2:$C$91,"Analyst") -> 12 | S17: =SUMIFS(G$2:G$91,$A$2:$A$91,$N17,$C$2:$C$91,"Analyst") -> 0 | T17: =SUMIFS(H$2:H$91,$A$2:$A$91,$N17,$C$2:$C$91,"Analyst") -> 89 | U17: =SUMIFS(I$2:I$91,$A$2:$A$91,$N17,$C$2:$C$91,"Analyst") -> 20 | V17: =SUMIFS(J$2:J$91,$A$2:$A$91,$N17,$C$2:$C$91,"Analyst") -> 1 | Y17: Validate | Z17: D | AA17: 1
A18: Validate | B18: Ingest Corrected / Validated Shapefile & Bbox Creation | C18: Analyst | D18: 0 | E18: 0 | F18: 10 | G18: 0 | H18: 0 | I18: 0 | J18: 0 | N18: Bond | O18: SE | P18: =SUMIFS(D$2:D$91,$A$2:$A$91,$N18,$C$2:$C$91,$O18) -> 24 | Q18: =SUMIFS(E$2:E$91,$A$2:$A$91,$N18,$C$2:$C$91,$O18) -> 23 | R18: =SUMIFS(F$2:F$91,$A$2:$A$91,$N18,$C$2:$C$91,$O18) -> 0 | S18: =SUMIFS(G$2:G$91,$A$2:$A$91,$N18,$C$2:$C$91,$O18) -> 10 | T18: =SUMIFS(H$2:H$91,$A$2:$A$91,$N18,$C$2:$C$91,$O18) -> 25 | U18: =SUMIFS(I$2:I$91,$A$2:$A$91,$N18,$C$2:$C$91,$O18) -> 0 | V18: =SUMIFS(J$2:J$91,$A$2:$A$91,$N18,$C$2:$C$91,$O18) -> 0 | Y18: Integrate | Z18: D | AA18: 0.8
A19: Validate | B19: Model Run | C19: Analyst | D19: 0 | E19: 0 | F19: 0 | G19: 0 | H19: 25 | I19: 0 | J19: 0 | N19: Explore | O19: SE | P19: =SUMIFS(D$2:D$91,$A$2:$A$91,$N19,$C$2:$C$91,$O19) -> 0 | Q19: =SUMIFS(E$2:E$91,$A$2:$A$91,$N19,$C$2:$C$91,$O19) -> 0 | R19: =SUMIFS(F$2:F$91,$A$2:$A$91,$N19,$C$2:$C$91,$O19) -> 0 | S19: =SUMIFS(G$2:G$91,$A$2:$A$91,$N19,$C$2:$C$91,$O19) -> 0 | T19: =SUMIFS(H$2:H$91,$A$2:$A$91,$N19,$C$2:$C$91,$O19) -> 0 | U19: =SUMIFS(I$2:I$91,$A$2:$A$91,$N19,$C$2:$C$91,$O19) -> 0 | V19: =SUMIFS(J$2:J$91,$A$2:$A$91,$N19,$C$2:$C$91,$O19) -> 0 | Y19: Bond | Z19: D | AA19: 0.7
A20: Validate | B20: Analysis | C20: Analyst | D20: 0 | E20: 0 | F20: 0 | G20: 0 | H20: 60 | I20: 0 | J20: 0 | N20: Integrate | O20: SE | P20: =SUMIFS(D$2:D$91,$A$2:$A$91,$N20,$C$2:$C$91,$O20) -> 24 | Q20: =SUMIFS(E$2:E$91,$A$2:$A$91,$N20,$C$2:$C$91,$O20) -> 23 | R20: =SUMIFS(F$2:F$91,$A$2:$A$91,$N20,$C$2:$C$91,$O20) -> 0 | S20: =SUMIFS(G$2:G$91,$A$2:$A$91,$N20,$C$2:$C$91,$O20) -> 10 | T20: =SUMIFS(H$2:H$91,$A$2:$A$91,$N20,$C$2:$C$91,$O20) -> 25 | U20: =SUMIFS(I$2:I$91,$A$2:$A$91,$N20,$C$2:$C$91,$O20) -> 0 | V20: =SUMIFS(J$2:J$91,$A$2:$A$91,$N20,$C$2:$C$91,$O20) -> 0 | Y20: Explore | Z20: D | AA20: 1
A21: Validate | B21: Results Presentation and Change Management | C21: Analyst | D21: 0 | E21: 0 | F21: 0 | G21: 0 | H21: 4 | I21: 0 | J21: 0 | N21: Validate | O21: SE | P21: =SUMIFS(D$2:D$91,$A$2:$A$91,$N21,$C$2:$C$91,$O21) -> 20 | Q21: =SUMIFS(E$2:E$91,$A$2:$A$91,$N21,$C$2:$C$91,$O21) -> 23 | R21: =SUMIFS(F$2:F$91,$A$2:$A$91,$N21,$C$2:$C$91,$O21) -> 8 | S21: =SUMIFS(G$2:G$91,$A$2:$A$91,$N21,$C$2:$C$91,$O21) -> 0 | T21: =SUMIFS(H$2:H$91,$A$2:$A$91,$N21,$C$2:$C$91,$O21) -> 25 | U21: =SUMIFS(I$2:I$91,$A$2:$A$91,$N21,$C$2:$C$91,$O21) -> 0 | V21: =SUMIFS(J$2:J$91,$A$2:$A$91,$N21,$C$2:$C$91,$O21) -> 0
A22: Validate | B22: Ongoing - Adoption Support | C22: Analyst | D22: 0 | E22: 0 | F22: 0 | G22: 0 | H22: 0 | I22: 20 | J22: 1
A23: Validate | B23: Image Acquisition & Ingestion | C23: SE | D23: 20 | E23: 23 | F23: 8 | G23: 0 | H23: 0 | I23: 0 | J23: 0
A24: Validate | B24: Model Run | C24: SE | D24: 0 | E24: 0 | F24: 0 | G24: 0 | H24: 25 | I24: 0 | J24: 0
A25: Validate | B25: Analysis | C25: SE | D25: 0 | E25: 0 | F25: 0 | G25: 0 | H25: 0 | I25: 0 | J25: 0
A26: Validate | B26: Results Presentation and Change Management | C26: SE | D26: 0 | E26: 0 | F26: 0 | G26: 0 | H26: 0 | I26: 0 | J26: 0
A27: Validate | B27: Ongoing - Adoption Support | C27: SE | D27: 0 | E27: 0 | F27: 0 | G27: 0 | H27: 0 | I27: 0 | J27: 0
A28: Integrate | B28: Discovery | C28: PM | D28: 5 | E28: 10 | F28: 0 | G28: 0 | H28: 0 | I28: 0 | J28: 0
A29: Integrate | B29: Imagery Planning, Decisioning & Acquision | C29: PM | D29: 5 | E29: 10 | F29: 5 | G29: 0 | H29: 0 | I29: 0 | J29: 0
A30: Integrate | B30: GIS - Correction / Validation | C30: PM | D30: 0 | E30: 0 | F30: 5 | G30: 15 | H30: 0 | I30: 0 | J30: 0 | K30: initial thought
A31: Integrate | B31: Model Run | C31: PM | D31: 0 | E31: 0 | F31: 0 | G31: 15 | H31: 0 | I31: 0 | J31: 0 | K31: 3 hrs for internal analysis | L31: 20 hrs
A32: Integrate | B32: Analysis | C32: PM | D32: 0 | E32: 0 | F32: 0 | G32: 30 | H32: 10 | I32: 0 | J32: 0
A33: Integrate | B33: Results Presentation and Change Management | C33: PM | D33: 0 | E33: 0 | F33: 0 | G33: 0 | H33: 10 | I33: 0 | J33: 0 | K33: 0.75X of Validate discovery
A34: Integrate | B34: Ongoing - Adoption Support | C34: PM | D34: 0 | E34: 0 | F34: 0 | G34: 0 | H34: 8 | I34: 8 | J34: 8
A35: Integrate | B35: Sales Handover + Kick off | C35: CSM | D35: 0 | E35: 0 | F35: 0 | G35: 0 | H35: 0 | I35: 0 | J35: 0
A36: Integrate | B36: Discovery + Imagery | C36: CSM | D36: 12 | E36: 0 | F36: 0 | G36: 0 | H36: 0 | I36: 0 | J36: 0
A37: Integrate | B37: Business Case | C37: CSM | D37: 0 | E37: 0 | F37: 0 | G37: 0 | H37: 0 | I37: 0 | J37: 0
A38: Integrate | B38: App Go Live + Confirm Requirements | C38: CSM | D38: 0 | E38: 20 | F38: 15 | G38: 0 | H38: 0 | I38: 0 | J38: 0
A39: Integrate | B39: Analysis | C39: CSM | D39: 0 | E39: 0 | F39: 6 | G39: 10 | H39: 0 | I39: 0 | J39: 0
A40: Integrate | B40: Insights & Recs + FV | C40: CSM | D40: 0 | E40: 0 | F40: 0 | G40: 0 | H40: 28 | I40: 0 | J40: 0
A41: Integrate | B41: Change Management + Conversion | C41: CSM | D41: 15 | E41: 10 | F41: 15 | G41: 10 | H41: 10 | I41: 24 | J41: 24
A42: Integrate | B42: Discovery, App Go-Live & Data QC | C42: Analyst | D42: 20 | E42: 10 | F42: 0 | G42: 0 | H42: 0 | I42: 0 | J42: 0
A43: Integrate | B43: Imagery Planning, Decisioning & Acquision | C43: Analyst | D43: 0 | E43: 12 | F43: 1 | G43: 0 | H43: 0 | I43: 0 | J43: 0
A44: Integrate | B44: GIS - Correction / Validation | C44: Analyst | D44: 0 | E44: 0 | F44: 10 | G44: 0 | H44: 0 | I44: 0 | J44: 0
A45: Integrate | B45: Model Run | C45: Analyst | D45: 0 | E45: 0 | F45: 0 | G45: 0 | H45: 25 | I45: 0 | J45: 0
... A57: Bond | B57: GIS - Correction / Validation | C57: PM | D57: 0 | E57: 0 | F57: 5 | G57: 15 | H57: 0 | I57: 0 | J57: 0
A58: Bond | B58: Model Run | C58: PM | D58: 0 | E58: 0 | F58: 0 | G58: 15 | H58: 0 | I58: 0 | J58: 0 | K58: look for nuance around non-us cx
A59: Bond | B59: Analysis | C59: PM | D59: 0 | E59: 0 | F59: 0 | G59: 20 | H59: 10 | I59: 0 | J59: 0 | K59: explore think for it as validate
A60: Bond | B60: Results Presentation and Change Management | C60: PM | D60: 0 | E60: 0 | F60: 0 | G60: 0 | H60: 10 | I60: 0 | J60: 0
A61: Bond | B61: Ongoing - Adoption Support | C61: PM | D61: 0 | E61: 0 | F61: 0 | G61: 0 | H61: 8 | I61: 8 | J61: 8
A62: Bond | B62: Sales Handover + Kick off | C62: CSM | D62: 0 | E62: 0 | F62: 0 | G62: 0 | H62: 0 | I62: 0 | J62: 0
A63: Bond | B63: Discovery + Imagery | C63: CSM | D63: 5 | E63: 0 | F63: 0 | G63: 0 | H63: 0 | I63: 0 | J63: 0
A64: Bond | B64: Business Case | C64: CSM | D64: 0 | E64: 0 | F64: 0 | G64: 0 | H64: 0 | I64: 0 | J64: 0
A65: Bond | B65: App Go Live + Confirm Requirements | C65: CSM | D65: 0 | E65: 5 | F65: 5 | G65: 0 | H65: 0 | I65: 0 | J65: 0
A66: Bond | B66: Analysis | C66: CSM | D66: 0 | E66: 0 | F66: 0 | G66: 10 | H66: 0 | I66: 0 | J66: 0
A67: Bond | B67: Insights & Recs + FV | C67: CSM | D67: 0 | E67: 0 | F67: 0 | G67: 0 | H67: 19 | I67: 0 | J67: 0
A68: Bond | B68: Change Management + Conversion | C68: CSM | D68: 0 | E68: 0 | F68: 0 | G68: 0 | H68: 0 | I68: 11 | J68: 1
A69: Bond | B69: Discovery, App Go-Live & Data QC | C69: Analyst | D69: 10 | E69: 0 | F69: 0 | G69: 0 | H69: 0 | I69: 0 | J69: 0
A70: Bond | B70: Imagery Planning, Decisioning & Acquision | C70: Analyst | D70: 0 | E70: 12 | F70: 1 | G70: 0 | H70: 0 | I70: 0 | J70: 0
A71: Bond | B71: GIS - Correction / Validation | C71: Analyst | D71: 0 | E71: 0 | F71: 10 | G71: 0 | H71: 0 | I71: 0 | J71: 0
... A86: Explore | B86: Process | C86: CSM | D86: 0 | E86: 0 | F86: 20 | G86: 5 | H86: 60 | I86: 0 | J86: 0
A87: Explore | B87: Results Presentation | C87: CSM | D87: 0 | E87: 0 | G87: 0 | H87: 0 | I87: 20 | J87: 10

Sheet Project List
A1: Summary | B1: SF Account Name | C1: CS Type | D1: Assigned Product Consultant.displayName | E1: Assigned Project Manager.displayName | F1: Assigned Business Analyst.displayName | G1: Assigned Business Analyst 2.displayName | H1: Analyst 1 Load% (1 to 100) | I1: Orbit | J1: Dx LMs | K1: Tx LMs | L1: Required Delivery Date (RDD) | M1: Estimated Delivery Date (EDD) | N1: Delivery Year | O1: Created | P1: Product | Q1: Created | R1: Delivery Date | S1: Created Main | T1: Delivery Date Main | U1: Total LMs | V1: Analytics Start Date | W1: LM Multiplier | X1: Delivery Month | Y1: Dx/Tx | Z1: Non-Standard Data | AA1: Non-Standard Metric | AB1: IVMS Configuration | AC1: Dx/Tx Multiplier | AD1: Non-Standard Data Multiplier | AE1: Non-Standard Metric Multiplier | AF1: IVMS Configuration Multiplier | AG1: Project Start M0 | AH1: Project Start M1 | AI1: Project Mid | AJ1: Project End M-1 | AK1: Project End M0 | AL1: Project End M1 | AM1: Project End M1+
A2: [2026 SaaS Y2] Adams-Columbia Electric Coop | B2: Adams-Columbia Electric Cooperative | C2: Bond | D2: Meryl Gibbs | E2: Shashank Sharma | F2: Kshitiz Agrawal | I2: =IFERROR(INDEX('Customer 360'!F:F,MATCH(B2,'Customer 360'!A:A,0)),"-") -> D | J2: 3000 | L2: 46258 | M2: 46258 | N2: 2026 | O2: 46082 | P2: IVMS | Q2: =O2 -> 46082 | R2: =IFERROR(IF(M2<>"",M2,IF(L2<>"",L2,INDEX('CSM RDD'!B:B,MATCH(B2,'CSM RDD'!A:A,0)))),"-") -> 46258 | S2: =IFERROR(EOMONTH(Q2,-1)+1,"") -> 46082 | T2: =IFERROR(EOMONTH(R2,-1)+1,"") -> 46235 | U2: =J2+K2 -> 3000 | V2: =IF(C2<>"Validate",DATE(2026,3,1),O2) -> 46082 | W2: =IF(U2=0,1,IF(U2<='Demand Base Matrix'!$K$3,'Demand Base Matrix'!$L$3,IF(U2<='Demand Base Matrix'!$K$4,'Demand Base Matrix'!$L$4,IF(U2<='Demand Base Matrix'!$K$5,'Demand Base Matrix'!$L$5,IF(U2<='Demand Base Matrix'!$K$6,'Demand Base Matrix'!$L$6,IF(U2<='Demand Base Matrix'!$K$7,'Demand Base Matrix'!$L$7)))))) -> 1 | X2: =DATE(YEAR(R2),MONTH(R2),1) -> 46235 | Y2: =IF(K2>0,"Tx","Dx") -> Dx | Z2: Low | AA2: Low | AB2: Low | AC2: =IFERROR(INDEX('Demand Base Matrix'!AM:AM,MATCH(Y2,'Demand Base Matrix'!AL:AL,0)),1) -> 1 | AD2: =IFERROR(INDEX('Demand Base Matrix'!AO:AO,MATCH(Z2,'Demand Base Matrix'!AN:AN,0)),1) -> 1 | AE2: =IFERROR(INDEX('Demand Base Matrix'!AQ:AQ,MATCH(AA2,'Demand Base Matrix'!AP:AP,0)),1) -> 1 | AF2: =IFERROR(INDEX('Demand Base Matrix'!AS:AS,MATCH(AB2,'Demand Base Matrix'!AR:AR,0)),1) -> 1 | AG2: =IF($C2="Validate",(('Demand Base Matrix'!D$2+'Demand Base Matrix'!D$6)*$AC$2*$AD$2*$AE$2+('Demand Base Matrix'!D$3+'Demand Base Matrix'!D$4)*$W$2*$AD$2+'Demand Base Matrix'!D$5*$W$2*$AD$2*$AE$2+'Demand Base Matrix'!D$7+'Demand Base Matrix'!D$8*$AF$2),IF($C2="Integrate",(('Demand Base Matrix'!D$28+'Demand Base Matrix'!D$32)*$AC$2*$AD$2*$AE$2+('Demand Base Matrix'!D$29+'Demand Base Matrix'!D$30)*$W$2*$AD$2+'Demand Base Matrix'!D$31*$W$2*$AD$2*$AE$2+'Demand Base Matrix'!D$33+'Demand Base Matrix'!D$34*$AF$2),IF($C2="Bond",(('Demand Base Matrix'!D$55+'Demand Base Matrix'!D$59)*$AC$2*$AD$2*$AE$2+('Demand Base Matrix'!D$56+'Demand Base Matrix'!D$57)*$W$2*$AD$2+'Demand Base Matrix'!D$58*$W$2*$AD$2*$AE$2+'Demand Base Matrix'!D$60+'Demand Base Matrix'!D$61*$AF$2),IF($C2="Explore",('Demand Base Matrix'!D$82*$AC$2*$AD$2*$AE$2*$AF$2+'Demand Base Matrix'!D$83*$W$2*$AC$2*$AD$2*$AE$2*$AF$2+'Demand Base Matrix'!D$84))))) -> 10 | AH2: =IF($C2="Validate",(('Demand Base Matrix'!E$2+'Demand Base Matrix'!E$6)*$AC$2*$AD$2*$AE$2+('Demand Base Matrix'!E$3+'Demand Base Matrix'!E$4)*$W$2*$AD$2+'Demand Base Matrix'!E$5*$W$2*$AD$2*$AE$2+'Demand Base Matrix'!E$7+'Demand Base Matrix'!E$8*$AF$2),IF($C2="Integrate",(('Demand Base Matrix'!E$28+'Demand Base Matrix'!E$32)*$AC$2*$AD$2*$AE$2+('Demand Base Matrix'!E$29+'Demand Base Matrix'!E$30)*$W$2*$AD$2+'Demand Base Matrix'!E$31*$W$2*$AD$2*$AE$2+'Demand Base Matrix'!E$33+'Demand Base Matrix'!E$34*$AF$2),IF($C2="Bond",(('Demand Base Matrix'!E$55+'Demand Base Matrix'!E$59)*$AC$2*$AD$2*$AE$2+('Demand Base Matrix'!E$56+'Demand Base Matrix'!E$57)*$W$2*$AD$2+'Demand Base Matrix'!E$58*$W$2*$AD$2*$AE$2+'Demand Base Matrix'!E$60+'Demand Base Matrix'!E$61*$AF$2),IF($C2="Explore",('Demand Base Matrix'!E$82*$AC$2*$AD$2*$AE$2*$AF$2+'Demand Base Matrix'!E$83*$W$2*$AC$2*$AD$2*$AE$2*$AF$2+'Demand Base Matrix'!E$84))))) -> 10 | AI2: =IF($C2="Validate",(('Demand Base Matrix'!F$2+'Demand Base Matrix'!F$6)*$AC$2*$AD$2*$AE$2+('Demand Base Matrix'!F$3+'Demand Base Matrix'!F$4)*$W$2*$AD$2+'Demand Base Matrix'!F$5*$W$2*$AD$2*$AE$2+'Demand Base Matrix'!F$7+'Demand Base Matrix'!F$8*$AF$2),IF($C2="Integrate",(('Demand Base Matrix'!F$28+'Demand Base Matrix'!F$32)*$AC$2*$AD$2*$AE$2+('Demand Base Matrix'!F$29+'Demand Base Matrix'!F$30)*$W$2*$AD$2+'Demand Base Matrix'!F$31*$W$2*$AD$2*$AE$2+'Demand Base Matrix'!F$33+'Demand Base Matrix'!F$34*$AF$2),IF($C2="Bond",(('Demand Base Matrix'!F$55+'Demand Base Matrix'!F$59)*$AC$2*$AD$2*$AE$2+('Demand Base Matrix'!F$56+'Demand Base Matrix'!F$57)*$W$2*$AD$2+'Demand Base Matrix'!F$58*$W$2*$AD$2*$AE$2+'Demand Base Matrix'!F$60+'Demand Base Matrix'!F$61*$AF$2),IF($C2="Explore",('Demand Base Matrix'!F$82*$AC$2*$AD$2*$AE$2*$AF$2+'Demand Base Matrix'!F$83*$W$2*$AC$2*$AD$2*$AE$2*$AF$2+'Demand Base Matrix'!F$84))))) -> 10 | AJ2: =IF($C2="Validate",(('Demand Base Matrix'!G$2+'Demand Base Matrix'!G$6)*$AC$2*$AD$2*$AE$2+('Demand Base Matrix'!G$3+'Demand Base Matrix'!G$4)*$W$2*$AD$2+'Demand Base Matrix'!G$5*$W$2*$AD$2*$AE$2+'Demand Base Matrix'!G$7+'Demand Base Matrix'!G$8*$AF$2),IF($C2="Integrate",(('Demand Base Matrix'!G$28+'Demand Base Matrix'!G$32)*$AC$2*$AD$2*$AE$2+('Demand Base Matrix'!G$29+'Demand Base Matrix'!G$30)*$W$2*$AD$2+'Demand Base Matrix'!G$31*$W$2*$AD$2*$AE$2+'Demand Base Matrix'!G$33+'Demand Base Matrix'!G$34*$AF$2),IF($C2="Bond",(('Demand Base Matrix'!G$55+'Demand Base Matrix'!G$59)*$AC$2*$AD$2*$AE$2+('Demand Base Matrix'!G$56+'Demand Base Matrix'!G$57)*$W$2*$AD$2+'Demand Base Matrix'!G$58*$W$2*$AD$2*$AE$2+'Demand Base Matrix'!G$60+'Demand Base Matrix'!G$61*$AF$2),IF($C2="Explore",('Demand Base Matrix'!G$82*$AC$2*$AD$2*$AE$2*$AF$2+'Demand Base Matrix'!G$83*$W$2*$AC$2*$AD$2*$AE$2*$AF$2+'Demand Base Matrix'!G$84))))) -> 50 | AK2: =IF($C2="Validate",(('Demand Base Matrix'!H$2+'Demand Base Matrix'!H$6)*$AC$2*$AD$2*$AE$2+('Demand Base Matrix'!H$3+'Demand Base Matrix'!H$4)*$W$2*$AD$2+'Demand Base Matrix'!H$5*$W$2*$AD$2*$AE$2+'Demand Base Matrix'!H$7+'Demand Base Matrix'!H$8*$AF$2),IF($C2="Integrate",(('Demand Base Matrix'!H$28+'Demand Base Matrix'!H$32)*$AC$2*$AD$2*$AE$2+('Demand Base Matrix'!H$29+'Demand Base Matrix'!H$30)*$W$2*$AD$2+'Demand Base Matrix'!H$31*$W$2*$AD$2*$AE$2+'Demand Base Matrix'!H$33+'Demand Base Matrix'!H$34*$AF$2),IF($C2="Bond",(('Demand Base Matrix'!H$55+'Demand Base Matrix'!H$59)*$AC$2*$AD$2*$AE$2+('Demand Base Matrix'!H$56+'Demand Base Matrix'!H$57)*$W$2*$AD$2+'Demand Base Matrix'!H$58*$W$2*$AD$2*$AE$2+'Demand Base Matrix'!H$60+'Demand Base Matrix'!H$61*$AF$2),IF($C2="Explore",('Demand Base Matrix'!H$82*$AC$2*$AD$2*$AE$2*$AF$2+'Demand Base Matrix'!H$83*$W$2*$AC$2*$AD$2*$AE$2*$AF$2+'Demand Base Matrix'!H$84))))) -> 28 | AL2: =IF($C2="Validate",(('Demand Base Matrix'!I$2+'Demand Base Matrix'!I$6)*$AC$2*$AD$2*$AE$2+('Demand Base Matrix'!I$3+'Demand Base Matrix'!I$4)*$W$2*$AD$2+'Demand Base Matrix'!I$5*$W$2*$AD$2*$AE$2+'Demand Base Matrix'!I$7+'Demand Base Matrix'!I$8*$AF$2),IF($C2="Integrate",(('Demand Base Matrix'!I$28+'Demand Base Matrix'!I$32)*$AC$2*$AD$2*$AE$2+('Demand Base Matrix'!I$29+'Demand Base Matrix'!I$30)*$W$2*$AD$2+'Demand Base Matrix'!I$31*$W$2*$AD$2*$AE$2+'Demand Base Matrix'!I$33+'Demand Base Matrix'!I$34*$AF$2),IF($C2="Bond",(('Demand Base Matrix'!I$55+'Demand Base Matrix'!I$59)*$AC$2*$AD$2*$AE$2+('Demand Base Matrix'!I$56+'Demand Base Matrix'!I$57)*$W$2*$AD$2+'Demand Base Matrix'!I$58*$W$2*$AD$2*$AE$2+'Demand Base Matrix'!I$60+'Demand Base Matrix'!I$61*$AF$2),IF($C2="Explore",('Demand Base Matrix'!I$82*$AC$2*$AD$2*$AE$2*$AF$2+'Demand Base Matrix'!I$83*$W$2*$AC$2*$AD$2*$AE$2*$AF$2+'Demand Base Matrix'!I$84))))) -> 8 | AM2: =IF($C2="Validate",(('Demand Base Matrix'!J$2+'Demand Base Matrix'!J$6)*$AC$2*$AD$2*$AE$2+('Demand Base Matrix'!J$3+'Demand Base Matrix'!J$4)*$W$2*$AD$2+'Demand Base Matrix'!J$5*$W$2*$AD$2*$AE$2+'Demand Base Matrix'!J$7+'Demand Base Matrix'!J$8*$AF$2),IF($C2="Integrate",(('Demand Base Matrix'!J$28+'Demand Base Matrix'!J$32)*$AC$2*$AD$2*$AE$2+('Demand Base Matrix'!J$29+'Demand Base Matrix'!J$30)*$W$2*$AD$2+'Demand Base Matrix'!J$31*$W$2*$AD$2*$AE$2+'Demand Base Matrix'!J$33+'Demand Base Matrix'!J$34*$AF$2),IF($C2="Bond",(('Demand Base Matrix'!J$55+'Demand Base Matrix'!J$59)*$AC$2*$AD$2*$AE$2+('Demand Base Matrix'!J$56+'Demand Base Matrix'!J$57)*$W$2*$AD$2+'Demand Base Matrix'!J$58*$W$2*$AD$2*$AE$2+'Demand Base Matrix'!J$60+'Demand Base Matrix'!J$61*$AF$2),IF($C2="Explore",('Demand Base Matrix'!J$82*$AC$2*$AD$2*$AE$2*$AF$2+'Demand Base Matrix'!J$83*$W$2*$AC$2*$AD$2*$AE$2*$AF$2+'Demand Base Matrix'!J$84))))) -> 8
A3: [2026 [SaaS Y3] Alabama Power - Dx | B3: Alabama Power Company | C3: Bond | D3: Chiranjiv Kathuria | E3: Mannat Padha | F3: Kshitiz Agrawal | I3: =IFERROR(INDEX('Customer 360'!F:F,MATCH(B3,'Customer 360'!A:A,0)),"-") -> A | J3: 52000 | L3: 46295 | M3: 46295 | N3: 2026 | O3: 46023 | P3: IVMS | Q3: =O3 -> 46023 | R3: =IFERROR(IF(M3<>"",M3,IF(L3<>"",L3,INDEX('CSM RDD'!B:B,MATCH(B3,'CSM RDD'!A:A,0)))),"-") -> 46295 | S3: =IFERROR(EOMONTH(Q3,-1)+1,"") -> 46023 | T3: =IFERROR(EOMONTH(R3,-1)+1,"") -> 46266 | U3: =J3+K3 -> 52000 | V3: =IF(C3<>"Validate",DATE(2026,3,1),O3) -> 46082 | W3: =IF(U3=0,1,IF(U3<='Demand Base Matrix'!$K$3,'Demand Base Matrix'!$L$3,IF(U3<='Demand Base Matrix'!$K$4,'Demand Base Matrix'!$L$4,IF(U3<='Demand Base Matrix'!$K$5,'Demand Base Matrix'!$L$5,IF(U3<='Demand Base Matrix'!$K$6,'Demand Base Matrix'!$L$6,IF(U3<='Demand Base Matrix'!$K$7,'Demand Base Matrix'!$L$7)))))) -> 2 | X3: =DATE(YEAR(R3),MONTH(R3),1) -> 46266 | Y3: =IF(K3>0,"Tx","Dx") -> Dx | Z3: Low | AA3: Low | AB3: Medium | AC3: =IFERROR(INDEX('Demand Base Matrix'!AM:AM,MATCH(Y3,'Demand Base Matrix'!AL:AL,0)),"-") -> 1 | AD3: =IFERROR(INDEX('Demand Base Matrix'!AO:AO,MATCH(Z3,'Demand Base Matrix'!AN:AN,0)),1) -> 1 | AE3: =IFERROR(INDEX('Demand Base Matrix'!AQ:AQ,MATCH(AA3,'Demand Base Matrix'!AP:AP,0)),1) -> 1 | AF3: =IFERROR(INDEX('Demand Base Matrix'!AS:AS,MATCH(AB3,'Demand Base Matrix'!AR:AR,0)),1) -> 1.5 | AG3: =IF($C3="Validate",(('Demand Base Matrix'!D$2+'Demand Base Matrix'!D$6)*$AC$2*$AD$2*$AE$2+('Demand Base Matrix'!D$3+'Demand Base Matrix'!D$4)*$W$2*$AD$2+'Demand Base Matrix'!D$5*$W$2*$AD$2*$AE$2+'Demand Base Matrix'!D$7+'Demand Base Matrix'!D$8*$AF$2),IF($C3="Integrate",(('Demand Base Matrix'!D$28+'Demand Base Matrix'!D$32)*$AC$2*$AD$2*$AE$2+('Demand Base Matrix'!D$29+'Demand Base Matrix'!D$30)*$W$2*$AD$2+'Demand Base Matrix'!D$31*$W$2*$AD$2*$AE$2+'Demand Base Matrix'!D$33+'Demand Base Matrix'!D$34*$AF$2),IF($C3="Bond",(('Demand Base Matrix'!D$55+'Demand Base Matrix'!D$59)*$AC$2*$AD$2*$AE$2+('Demand Base Matrix'!D$56+'Demand Base Matrix'!D$57)*$W$2*$AD$2+'Demand Base Matrix'!D$58*$W$2*$AD$2*$AE$2+'Demand Base Matrix'!D$60+'Demand Base Matrix'!D$61*$AF$2),IF($C3="Explore",('Demand Base Matrix'!D$82*$AC$2*$AD$2*$AE$2*$AF$2+'Demand Base Matrix'!D$83*$W$2*$AC$2*$AD$2*$AE$2*$AF$2+'Demand Base Matrix'!D$84))))) -> 10 | AH3: =IF($C3="Validate",(('Demand Base Matrix'!E$2+'Demand Base Matrix'!E$6)*$AC$2*$AD$2*$AE$2+('Demand Base Matrix'!E$3+'Demand Base Matrix'!E$4)*$W$2*$AD$2+'Demand Base Matrix'!E$5*$W$2*$AD$2*$AE$2+'Demand Base Matrix'!E$7+'Demand Base Matrix'!E$8*$AF$2),IF($C3="Integrate",(('Demand Base Matrix'!E$28+'Demand Base Matrix'!E$32)*$AC$2*$AD$2*$AE$2+('Demand Base Matrix'!E$29+'Demand Base Matrix'!E$30)*$W$2*$AD$2+'Demand Base Matrix'!E$31*$W$2*$AD$2*$AE$2+'Demand Base Matrix'!E$33+'Demand Base Matrix'!E$34*$AF$2),IF($C3="Bond",(('Demand Base Matrix'!E$55+'Demand Base Matrix'!E$59)*$AC$2*$AD$2*$AE$2+('Demand Base Matrix'!E$56+'Demand Base Matrix'!E$57)*$W$2*$AD$2+'Demand Base Matrix'!E$58*$W$2*$AD$2*$AE$2+'Demand Base Matrix'!E$60+'Demand Base Matrix'!E$61*$AF$2),IF($C3="Explore",('Demand Base Matrix'!E$82*$AC$2*$AD$2*$AE$2*$AF$2+'Demand Base Matrix'!E$83*$W$2*$AC$2*$AD$2*$AE$2*$AF$2+'Demand Base Matrix'!E$84))))) -> 10 | AI3: =IF($C3="Validate",(('Demand Base Matrix'!F$2+'Demand Base Matrix'!F$6)*$AC$2*$AD$2*$AE$2+('Demand Base Matrix'!F$3+'Demand Base Matrix'!F$4)*$W$2*$AD$2+'Demand Base Matrix'!F$5*$W$2*$AD$2*$AE$2+'Demand Base Matrix'!F$7+'Demand Base Matrix'!F$8*$AF$2),IF($C3="Integrate",(('Demand Base Matrix'!F$28+'Demand Base Matrix'!F$32)*$AC$2*$AD$2*$AE$2+('Demand Base Matrix'!F$29+'Demand Base Matrix'!F$30)*$W$2*$AD$2+'Demand Base Matrix'!F$31*$W$2*$AD$2*$AE$2+'Demand Base Matrix'!F$33+'Demand Base Matrix'!F$34*$AF$2),IF($C3="Bond",(('Demand Base Matrix'!F$55+'Demand Base Matrix'!F$59)*$AC$2*$AD$2*$AE$2+('Demand Base Matrix'!F$56+'Demand Base Matrix'!F$57)*$W$2*$AD$2+'Demand Base Matrix'!F$58*$W$2*$AD$2*$AE$2+'Demand Base Matrix'!F$60+'Demand Base Matrix'!F$61*$AF$2),IF($C3="Explore",('Demand Base Matrix'!F$82*$AC$2*$AD$2*$AE$2*$AF$2+'Demand Base Matrix'!F$83*$W$2*$AC$2*$AD$2*$AE$2*$AF$2+'Demand Base Matrix'!F$84))))) -> 10 | AJ3: =IF($C3="Validate",(('Demand Base Matrix'!G$2+'Demand Base Matrix'!G$6)*$AC$2*$AD$2*$AE$2+('Demand Base Matrix'!G$3+'Demand Base Matrix'!G$4)*$W$2*$AD$2+'Demand Base Matrix'!G$5*$W$2*$AD$2*$AE$2+'Demand Base Matrix'!G$7+'Demand Base Matrix'!G$8*$AF$2),IF($C3="Integrate",(('Demand Base Matrix'!G$28+'Demand Base Matrix'!G$32)*$AC$2*$AD$2*$AE$2+('Demand Base Matrix'!G$29+'Demand Base Matrix'!G$30)*$W$2*$AD$2+'Demand Base Matrix'!G$31*$W$2*$AD$2*$AE$2+'Demand Base Matrix'!G$33+'Demand Base Matrix'!G$34*$AF$2),IF($C3="Bond",(('Demand Base Matrix'!G$55+'Demand Base Matrix'!G$59)*$AC$2*$AD$2*$AE$2+('Demand Base Matrix'!G$56+'Demand Base Matrix'!G$57)*$W$2*$AD$2+'Demand Base Matrix'!G$58*$W$2*$AD$2*$AE$2+'Demand Base Matrix'!G$60+'Demand Base Matrix'!G$61*$AF$2),IF($C3="Explore",('Demand Base Matrix'!G$82*$AC$2*$AD$2*$AE$2*$AF$2+'Demand Base Matrix'!G$83*$W$2*$AC$2*$AD$2*$AE$2*$AF$2+'Demand Base Matrix'!G$84))))) -> 50 | AK3: =IF($C3="Validate",(('Demand Base Matrix'!H$2+'Demand Base Matrix'!H$6)*$AC$2*$AD$2*$AE$2+('Demand Base Matrix'!H$3+'Demand Base Matrix'!H$4)*$W$2*$AD$2+'Demand Base Matrix'!H$5*$W$2*$AD$2*$AE$2+'Demand Base Matrix'!H$7+'Demand Base Matrix'!H$8*$AF$2),IF($C3="Integrate",(('Demand Base Matrix'!H$28+'Demand Base Matrix'!H$32)*$AC$2*$AD$2*$AE$2+('Demand Base Matrix'!H$29+'Demand Base Matrix'!H$30)*$W$2*$AD$2+'Demand Base Matrix'!H$31*$W$2*$AD$2*$AE$2+'Demand Base Matrix'!H$33+'Demand Base Matrix'!H$34*$AF$2),IF($C3="Bond",(('Demand Base Matrix'!H$55+'Demand Base Matrix'!H$59)*$AC$2*$AD$2*$AE$2+('Demand Base Matrix'!H$56+'Demand Base Matrix'!H$57)*$W$2*$AD$2+'Demand Base Matrix'!H$58*$W$2*$AD$2*$AE$2+'Demand Base Matrix'!H$60+'Demand Base Matrix'!H$61*$AF$2),IF($C3="Explore",('Demand Base Matrix'!H$82*$AC$2*$AD$2*$AE$2*$AF$2+'Demand Base Matrix'!H$83*$W$2*$AC$2*$AD$2*$AE$2*$AF$2+'Demand Base Matrix'!H$84))))) -> 28 | AL3: =IF($C3="Validate",(('Demand Base Matrix'!I$2+'Demand Base Matrix'!I$6)*$AC$2*$AD$2*$AE$2+('Demand Base Matrix'!I$3+'Demand Base Matrix'!I$4)*$W$2*$AD$2+'Demand Base Matrix'!I$5*$W$2*$AD$2*$AE$2+'Demand Base Matrix'!I$7+'Demand Base Matrix'!I$8*$AF$2),IF($C3="Integrate",(('Demand Base Matrix'!I$28+'Demand Base Matrix'!I$32)*$AC$2*$AD$2*$AE$2+('Demand Base Matrix'!I$29+'Demand Base Matrix'!I$30)*$W$2*$AD$2+'Demand Base Matrix'!I$31*$W$2*$AD$2*$AE$2+'Demand Base Matrix'!I$33+'Demand Base Matrix'!I$34*$AF$2),IF($C3="Bond",(('Demand Base Matrix'!I$55+'Demand Base Matrix'!I$59)*$AC$2*$AD$2*$AE$2+('Demand Base Matrix'!I$56+'Demand Base Matrix'!I$57)*$W$2*$AD$2+'Demand Base Matrix'!I$58*$W$2*$AD$2*$AE$2+'Demand Base Matrix'!I$60+'Demand Base Matrix'!I$61*$AF$2),IF($C3="Explore",('Demand Base Matrix'!I$82*$AC$2*$AD$2*$AE$2*$AF$2+'Demand Base Matrix'!I$83*$W$2*$AC$2*$AD$2*$AE$2*$AF$2+'Demand Base Matrix'!I$84))))) -> 8 | AM3: =IF($C3="Validate",(('Demand Base Matrix'!J$2+'Demand Base Matrix'!J$6)*$AC$2*$AD$2*$AE$2+('Demand Base Matrix'!J$3+'Demand Base Matrix'!J$4)*$W$2*$AD$2+'Demand Base Matrix'!J$5*$W$2*$AD$2*$AE$2+'Demand Base Matrix'!J$7+'Demand Base Matrix'!J$8*$AF$2),IF($C3="Integrate",(('Demand Base Matrix'!J$28+'Demand Base Matrix'!J$32)*$AC$2*$AD$2*$AE$2+('Demand Base Matrix'!J$29+'Demand Base Matrix'!J$30)*$W$2*$AD$2+'Demand Base Matrix'!J$31*$W$2*$AD$2*$AE$2+'Demand Base Matrix'!J$33+'Demand Base Matrix'!J$34*$AF$2),IF($C3="Bond",(('Demand Base Matrix'!J$55+'Demand Base Matrix'!J$59)*$AC$2*$AD$2*$AE$2+('Demand Base Matrix'!J$56+'Demand Base Matrix'!J$57)*$W$2*$AD$2+'Demand Base Matrix'!J$58*$W$2*$AD$2*$AE$2+'Demand Base Matrix'!J$60+'Demand Base Matrix'!J$61*$AF$2),IF($C3="Explore",('Demand Base Matrix'!J$82*$AC$2*$AD$2*$AE$2*$AF$2+'Demand Base Matrix'!J$83*$W$2*$AC$2*$AD$2*$AE$2*$AF$2+'Demand Base Matrix'!J$84))))) -> 8
A4: [2026 [SaaS Y3] Alabama Power - SubTx | B4: Alabama Power Company | C4: Bond | D4: Chiranjiv Kathuria | E4: Mannat Padha | F4: Kshitiz Agrawal | I4: =IFERROR(INDEX('Customer 360'!F:F,MATCH(B4,'Customer 360'!A:A,0)),"-") -> A | K4: 3298 | L4: 46295 | M4: 46295 | N4: 2026 | O4: 46023 | P4: IVMS | Q4: =O4 -> 46023 | R4: =IFERROR(IF(M4<>"",M4,IF(L4<>"",L4,INDEX('CSM RDD'!B:B,MATCH(B4,'CSM RDD'!A:A,0)))),"-") -> 46295 | S4: =IFERROR(EOMONTH(Q4,-1)+1,"") -> 46023 | T4: =IFERROR(EOMONTH(R4,-1)+1,"") -> 46266 | U4: =J4+K4 -> 3298 | V4: =IF(C4<>"Validate",DATE(2026,3,1),O4) -> 46082 | W4: =IF(U4=0,1,IF(U4<='Demand Base Matrix'!$K$3,'Demand Base Matrix'!$L$3,IF(U4<='Demand Base Matrix'!$K$4,'Demand Base Matrix'!$L$4,IF(U4<='Demand Base Matrix'!$K$5,'Demand Base Matrix'!$L$5,IF(U4<='Demand Base Matrix'!$K$6,'Demand Base Matrix'!$L$6,IF(U4<='Demand Base Matrix'!$K$7,'Demand Base Matrix'!$L$7)))))) -> 1 | X4: =DATE(YEAR(R4),MONTH(R4),1) -> 46266 | Y4: =IF(K4>0,"Tx","Dx") -> Tx | Z4: Low | AA4: Low | AB4: Medium | AC4: =IFERROR(INDEX('Demand Base Matrix'!AM:AM,MATCH(Y4,'Demand Base Matrix'!AL:AL,0)),"-") -> 1.5 | AD4: =IFERROR(INDEX('Demand Base Matrix'!AO:AO,MATCH(Z4,'Demand Base Matrix'!AN:AN,0)),1) -> 1 | AE4: =IFERROR(INDEX('Demand Base Matrix'!AQ:AQ,MATCH(AA4,'Demand Base Matrix'!AP:AP,0)),1) -> 1 | AF4: =IFERROR(INDEX('Demand Base Matrix'!AS:AS,MATCH(AB4,'Demand Base Matrix'!AR:AR,0)),1) -> 1.5 | AG4: =IF($C4="Validate",(('Demand Base Matrix'!D$2+'Demand Base Matrix'!D$6)*$AC$2*$AD$2*$AE$2+('Demand Base Matrix'!D$3+'Demand Base Matrix'!D$4)*$W$2*$AD$2+'Demand Base Matrix'!D$5*$W$2*$AD$2*$AE$2+'Demand Base Matrix'!D$7+'Demand Base Matrix'!D$8*$AF$2),IF($C4="Integrate",(('Demand Base Matrix'!D$28+'Demand Base Matrix'!D$32)*$AC$2*$AD$2*$AE$2+('Demand Base Matrix'!D$29+'Demand Base Matrix'!D$30)*$W$2*$AD$2+'Demand Base Matrix'!D$31*$W$2*$AD$2*$AE$2+'Demand Base Matrix'!D$33+'Demand Base Matrix'!D$34*$AF$2),IF($C4="Bond",(('Demand Base Matrix'!D$55+'Demand Base Matrix'!D$59)*$AC$2*$AD$2*$AE$2+('Demand Base Matrix'!D$56+'Demand Base Matrix'!D$57)*$W$2*$AD$2+'Demand Base Matrix'!D$58*$W$2*$AD$2*$AE$2+'Demand Base Matrix'!D$60+'Demand Base Matrix'!D$61*$AF$2),IF($C4="Explore",('Demand Base Matrix'!D$82*$AC$2*$AD$2*$AE$2*$AF$2+'Demand Base Matrix'!D$83*$W$2*$AC$2*$AD$2*$AE$2*$AF$2+'Demand Base Matrix'!D$84))))) -> 10 | AH4: =IF($C4="Validate",(('Demand Base Matrix'!E$2+'Demand Base Matrix'!E$6)*$AC$2*$AD$2*$AE$2+('Demand Base Matrix'!E$3+'Demand Base Matrix'!E$4)*$W$2*$AD$2+'Demand Base Matrix'!E$5*$W$2*$AD$2*$AE$2+'Demand Base Matrix'!E$7+'Demand Base Matrix'!E$8*$AF$2),IF($C4="Integrate",(('Demand Base Matrix'!E$28+'Demand Base Matrix'!E$32)*$AC$2*$AD$2*$AE$2+('Demand Base Matrix'!E$29+'Demand Base Matrix'!E$30)*$W$2*$AD$2+'Demand Base Matrix'!E$31*$W$2*$AD$2*$AE$2+'Demand Base Matrix'!E$33+'Demand Base Matrix'!E$34*$AF$2),IF($C4="Bond",(('Demand Base Matrix'!E$55+'Demand Base Matrix'!E$59)*$AC$2*$AD$2*$AE$2+('Demand Base Matrix'!E$56+'Demand Base Matrix'!E$57)*$W$2*$AD$2+'Demand Base Matrix'!E$58*$W$2*$AD$2*$AE$2+'Demand Base Matrix'!E$60+'Demand Base Matrix'!E$61*$AF$2),IF($C4="Explore",('Demand Base Matrix'!E$82*$AC$2*$AD$2*$AE$2*$AF$2+'Demand Base Matrix'!E$83*$W$2*$AC$2*$AD$2*$AE$2*$AF$2+'Demand Base Matrix'!E$84))))) -> 10 | AI4: =IF($C4="Validate",(('Demand Base Matrix'!F$2+'Demand Base Matrix'!F$6)*$AC$2*$AD$2*$AE$2+('Demand Base Matrix'!F$3+'Demand Base Matrix'!F$4)*$W$2*$AD$2+'Demand Base Matrix'!F$5*$W$2*$AD$2*$AE$2+'Demand Base Matrix'!F$7+'Demand Base Matrix'!F$8*$AF$2),IF($C4="Integrate",(('Demand Base Matrix'!F$28+'Demand Base Matrix'!F$32)*$AC$2*$AD$2*$AE$2+('Demand Base Matrix'!F$29+'Demand Base Matrix'!F$30)*$W$2*$AD$2+'Demand Base Matrix'!F$31*$W$2*$AD$2*$AE$2+'Demand Base Matrix'!F$33+'Demand Base Matrix'!F$34*$AF$2),IF($C4="Bond",(('Demand Base Matrix'!F$55+'Demand Base Matrix'!F$59)*$AC$2*$AD$2*$AE$2+('Demand Base Matrix'!F$56+'Demand Base Matrix'!F$57)*$W$2*$AD$2+'Demand Base Matrix'!F$58*$W$2*$AD$2*$AE$2+'Demand Base Matrix'!F$60+'Demand Base Matrix'!F$61*$AF$2),IF($C4="Explore",('Demand Base Matrix'!F$82*$AC$2*$AD$2*$AE$2*$AF$2+'Demand Base Matrix'!F$83*$W$2*$AC$2*$AD$2*$AE$2*$AF$2+'Demand Base Matrix'!F$84))))) -> 10 | AJ4: =IF($C4="Validate",(('Demand Base Matrix'!G$2+'Demand Base Matrix'!G$6)*$AC$2*$AD$2*$AE$2+('Demand Base Matrix'!G$3+'Demand Base Matrix'!G$4)*$W$2*$AD$2+'Demand Base Matrix'!G$5*$W$2*$AD$2*$AE$2+'Demand Base Matrix'!G$7+'Demand Base Matrix'!G$8*$AF$2),IF($C4="Integrate",(('Demand Base Matrix'!G$28+'Demand Base Matrix'!G$32)*$AC$2*$AD$2*$AE$2+('Demand Base Matrix'!G$29+'Demand Base Matrix'!G$30)*$W$2*$AD$2+'Demand Base Matrix'!G$31*$W$2*$AD$2*$AE$2+'Demand Base Matrix'!G$33+'Demand Base Matrix'!G$34*$AF$2),IF($C4="Bond",(('Demand Base Matrix'!G$55+'Demand Base Matrix'!G$59)*$AC$2*$AD$2*$AE$2+('Demand Base Matrix'!G$56+'Demand Base Matrix'!G$57)*$W$2*$AD$2+'Demand Base Matrix'!G$58*$W$2*$AD$2*$AE$2+'Demand Base Matrix'!G$60+'Demand Base Matrix'!G$61*$AF$2),IF($C4="Explore",('Demand Base Matrix'!G$82*$AC$2*$AD$2*$AE$2*$AF$2+'Demand Base Matrix'!G$83*$W$2*$AC$2*$AD$2*$AE$2*$AF$2+'Demand Base Matrix'!G$84))))) -> 50 | AK4: =IF($C4="Validate",(('Demand Base Matrix'!H$2+'Demand Base Matrix'!H$6)*$AC$2*$AD$2*$AE$2+('Demand Base Matrix'!H$3+'Demand Base Matrix'!H$4)*$W$2*$AD$2+'Demand Base Matrix'!H$5*$W$2*$AD$2*$AE$2+'Demand Base Matrix'!H$7+'Demand Base Matrix'!H$8*$AF$2),IF($C4="Integrate",(('Demand Base Matrix'!H$28+'Demand Base Matrix'!H$32)*$AC$2*$AD$2*$AE$2+('Demand Base Matrix'!H$29+'Demand Base Matrix'!H$30)*$W$2*$AD$2+'Demand Base Matrix'!H$31*$W$2*$AD$2*$AE$2+'Demand Base Matrix'!H$33+'Demand Base Matrix'!H$34*$AF$2),IF($C4="Bond",(('Demand Base Matrix'!H$55+'Demand Base Matrix'!H$59)*$AC$2*$AD$2*$AE$2+('Demand Base Matrix'!H$56+'Demand Base Matrix'!H$57)*$W$2*$AD$2+'Demand Base Matrix'!H$58*$W$2*$AD$2*$AE$2+'Demand Base Matrix'!H$60+'Demand Base Matrix'!H$61*$AF$2),IF($C4="Explore",('Demand Base Matrix'!H$82*$AC$2*$AD$2*$AE$2*$AF$2+'Demand Base Matrix'!H$83*$W$2*$AC$2*$AD$2*$AE$2*$AF$2+'Demand Base Matrix'!H$84))))) -> 28 | AL4: =IF($C4="Validate",(('Demand Base Matrix'!I$2+'Demand Base Matrix'!I$6)*$AC$2*$AD$2*$AE$2+('Demand Base Matrix'!I$3+'Demand Base Matrix'!I$4)*$W$2*$AD$2+'Demand Base Matrix'!I$5*$W$2*$AD$2*$AE$2+'Demand Base Matrix'!I$7+'Demand Base Matrix'!I$8*$AF$2),IF($C4="Integrate",(('Demand Base Matrix'!I$28+'Demand Base Matrix'!I$32)*$AC$2*$AD$2*$AE$2+('Demand Base Matrix'!I$29+'Demand Base Matrix'!I$30)*$W$2*$AD$2+'Demand Base Matrix'!I$31*$W$2*$AD$2*$AE$2+'Demand Base Matrix'!I$33+'Demand Base Matrix'!I$34*$AF$2),IF($C4="Bond",(('Demand Base Matrix'!I$55+'Demand Base Matrix'!I$59)*$AC$2*$AD$2*$AE$2+('Demand Base Matrix'!I$56+'Demand Base Matrix'!I$57)*$W$2*$AD$2+'Demand Base Matrix'!I$58*$W$2*$AD$2*$AE$2+'Demand Base Matrix'!I$60+'Demand Base Matrix'!I$61*$AF$2),IF($C4="Explore",('Demand Base Matrix'!I$82*$AC$2*$AD$2*$AE$2*$AF$2+'Demand Base Matrix'!I$83*$W$2*$AC$2*$AD$2*$AE$2*$AF$2+'Demand Base Matrix'!I$84))))) -> 8 | AM4: =IF($C4="Validate",(('Demand Base Matrix'!J$2+'Demand Base Matrix'!J$6)*$AC$2*$AD$2*$AE$2+('Demand Base Matrix'!J$3+'Demand Base Matrix'!J$4)*$W$2*$AD$2+'Demand Base Matrix'!J$5*$W$2*$AD$2*$AE$2+'Demand Base Matrix'!J$7+'Demand Base Matrix'!J$8*$AF$2),IF($C4="Integrate",(('Demand Base Matrix'!J$28+'Demand Base Matrix'!J$32)*$AC$2*$AD$2*$AE$2+('Demand Base Matrix'!J$29+'Demand Base Matrix'!J$30)*$W$2*$AD$2+'Demand Base Matrix'!J$31*$W$2*$AD$2*$AE$2+'Demand Base Matrix'!J$33+'Demand Base Matrix'!J$34*$AF$2),IF($C4="Bond",(('Demand Base Matrix'!J$55+'Demand Base Matrix'!J$59)*$AC$2*$AD$2*$AE$2+('Demand Base Matrix'!J$56+'Demand Base Matrix'!J$57)*$W$2*$AD$2+'Demand Base Matrix'!J$58*$W$2*$AD$2*$AE$2+'Demand Base Matrix'!J$60+'Demand Base Matrix'!J$61*$AF$2),IF($C4="Explore",('Demand Base Matrix'!J$82*$AC$2*$AD$2*$AE$2*$AF$2+'Demand Base Matrix'!J$83*$W$2*$AC$2*$AD$2*$AE$2*$AF$2+'Demand Base Matrix'!J$84))))) -> 8
A5: [2025 SaaS Y1] Arizona Public Service | B5: Arizona Public Service | C5: Validate | D5: Jessica Felde | E5: Mukul Mathur | F5: Piyush Kumar Pandey | I5: =IFERROR(INDEX('Customer 360'!F:F,MATCH(B5,'Customer 360'!A:A,0)),"-") -> A | J5: 68 | K5: 23 | L5: 46216 | M5: 46216 | N5: 2025 | O5: 46082 | P5: IVMS | Q5: =O5 -> 46082 | R5: =IFERROR(IF(M5<>"",M5,IF(L5<>"",L5,INDEX('CSM RDD'!B:B,MATCH(B5,'CSM RDD'!A:A,0)))),"-") -> 46216 | S5: =IFERROR(EOMONTH(Q5,-1)+1,"") -> 46082 | T5: =IFERROR(EOMONTH(R5,-1)+1,"") -> 46204 | U5: =J5+K5 -> 91 | V5: =IF(C5<>"Validate",DATE(2026,3,1),O5) -> 46082 | W5: =IF(U5=0,1,IF(U5<='Demand Base Matrix'!$K$3,'Demand Base Matrix'!$L$3,IF(U5<='Demand Base Matrix'!$K$4,'Demand Base Matrix'!$L$4,IF(U5<='Demand Base Matrix'!$K$5,'Demand Base Matrix'!$L$5,IF(U5<='Demand Base Matrix'!$K$6,'Demand Base Matrix'!$L$6,IF(U5<='Demand Base Matrix'!$K$7,'Demand Base Matrix'!$L$7)))))) -> 0.75 | X5: =DATE(YEAR(R5),MONTH(R5),1) -> 46204 | Y5: =IF(K5>0,"Tx","Dx") -> Tx | Z5: Low | AA5: Low | AB5: Low | AC5: =IFERROR(INDEX('Demand Base Matrix'!AM:AM,MATCH(Y5,'Demand Base Matrix'!AL:AL,0)),"-") -> 1.5 | AD5: =IFERROR(INDEX('Demand Base Matrix'!AO:AO,MATCH(Z5,'Demand Base Matrix'!AN:AN,0)),1) -> 1 | AE5: =IFERROR(INDEX('Demand Base Matrix'!AQ:AQ,MATCH(AA5,'Demand Base Matrix'!AP:AP,0)),1) -> 1 | AF5: =IFERROR(INDEX('Demand Base Matrix'!AS:AS,MATCH(AB5,'Demand Base Matrix'!AR:AR,0)),1) -> 1 | AG5: =IF($C5="Validate",(('Demand Base Matrix'!D$2+'Demand Base Matrix'!D$6)*$AC$2*$AD$2*$AE$2+('Demand Base Matrix'!D$3+'Demand Base Matrix'!D$4)*$W$2*$AD$2+'Demand Base Matrix'!D$5*$W$2*$AD$2*$AE$2+'Demand Base Matrix'!D$7+'Demand Base Matrix'!D$8*$AF$2),IF($C5="Integrate",(('Demand Base Matrix'!D$28+'Demand Base Matrix'!D$32)*$AC$2*$AD$2*$AE$2+('Demand Base Matrix'!D$29+'Demand Base Matrix'!D$30)*$W$2*$AD$2+'Demand Base Matrix'!D$31*$W$2*$AD$2*$AE$2+'Demand Base Matrix'!D$33+'Demand Base Matrix'!D$34*$AF$2),IF($C5="Bond",(('Demand Base Matrix'!D$55+'Demand Base Matrix'!D$59)*$AC$2*$AD$2*$AE$2+('Demand Base Matrix'!D$56+'Demand Base Matrix'!D$57)*$W$2*$AD$2+'Demand Base Matrix'!D$58*$W$2*$AD$2*$AE$2+'Demand Base Matrix'!D$60+'Demand Base Matrix'!D$61*$AF$2),IF($C5="Explore",('Demand Base Matrix'!D$82*$AC$2*$AD$2*$AE$2*$AF$2+'Demand Base Matrix'!D$83*$W$2*$AC$2*$AD$2*$AE$2*$AF$2+'Demand Base Matrix'!D$84))))) -> 15 | AH5: =IF($C5="Validate",(('Demand Base Matrix'!E$2+'Demand Base Matrix'!E$6)*$AC$2*$AD$2*$AE$2+('Demand Base Matrix'!E$3+'Demand Base Matrix'!E$4)*$W$2*$AD$2+'Demand Base Matrix'!E$5*$W$2*$AD$2*$AE$2+'Demand Base Matrix'!E$7+'Demand Base Matrix'!E$8*$AF$2),IF($C5="Integrate",(('Demand Base Matrix'!E$28+'Demand Base Matrix'!E$32)*$AC$2*$AD$2*$AE$2+('Demand Base Matrix'!E$29+'Demand Base Matrix'!E$30)*$W$2*$AD$2+'Demand Base Matrix'!E$31*$W$2*$AD$2*$AE$2+'Demand Base Matrix'!E$33+'Demand Base Matrix'!E$34*$AF$2),IF($C5="Bond",(('Demand Base Matrix'!E$55+'Demand Base Matrix'!E$59)*$AC$2*$AD$2*$AE$2+('Demand Base Matrix'!E$56+'Demand Base Matrix'!E$57)*$W$2*$AD$2+'Demand Base Matrix'!E$58*$W$2*$AD$2*$AE$2+'Demand Base Matrix'!E$60+'Demand Base Matrix'!E$61*$AF$2),IF($C5="Explore",('Demand Base Matrix'!E$82*$AC$2*$AD$2*$AE$2*$AF$2+'Demand Base Matrix'!E$83*$W$2*$AC$2*$AD$2*$AE$2*$AF$2+'Demand Base Matrix'!E$84))))) -> 15 | AI5: =IF($C5="Validate",(('Demand Base Matrix'!F$2+'Demand Base Matrix'!F$6)*$AC$2*$AD$2*$AE$2+('Demand Base Matrix'!F$3+'Demand Base Matrix'!F$4)*$W$2*$AD$2+'Demand Base Matrix'!F$5*$W$2*$AD$2*$AE$2+'Demand Base Matrix'!F$7+'Demand Base Matrix'!F$8*$AF$2),IF($C5="Integrate",(('Demand Base Matrix'!F$28+'Demand Base Matrix'!F$32)*$AC$2*$AD$2*$AE$2+('Demand Base Matrix'!F$29+'Demand Base Matrix'!F$30)*$W$2*$AD$2+'Demand Base Matrix'!F$31*$W$2*$AD$2*$AE$2+'Demand Base Matrix'!F$33+'Demand Base Matrix'!F$34*$AF$2),IF($C5="Bond",(('Demand Base Matrix'!F$55+'Demand Base Matrix'!F$59)*$AC$2*$AD$2*$AE$2+('Demand Base Matrix'!F$56+'Demand Base Matrix'!F$57)*$W$2*$AD$2+'Demand Base Matrix'!F$58*$W$2*$AD$2*$AE$2+'Demand Base Matrix'!F$60+'Demand Base Matrix'!F$61*$AF$2),IF($C5="Explore",('Demand Base Matrix'!F$82*$AC$2*$AD$2*$AE$2*$AF$2+'Demand Base Matrix'!F$83*$W$2*$AC$2*$AD$2*$AE$2*$AF$2+'Demand Base Matrix'!F$84))))) -> 7 | AJ5: =IF($C5="Validate",(('Demand Base Matrix'!G$2+'Demand Base Matrix'!G$6)*$AC$2*$AD$2*$AE$2+('Demand Base Matrix'!G$3+'Demand Base Matrix'!G$4)*$W$2*$AD$2+'Demand Base Matrix'!G$5*$W$2*$AD$2*$AE$2+'Demand Base Matrix'!G$7+'Demand Base Matrix'!G$8*$AF$2),IF($C5="Integrate",(('Demand Base Matrix'!G$28+'Demand Base Matrix'!G$32)*$AC$2*$AD$2*$AE$2+('Demand Base Matrix'!G$29+'Demand Base Matrix'!G$30)*$W$2*$AD$2+'Demand Base Matrix'!G$31*$W$2*$AD$2*$AE$2+'Demand Base Matrix'!G$33+'Demand Base Matrix'!G$34*$AF$2),IF($C5="Bond",(('Demand Base Matrix'!G$55+'Demand Base Matrix'!G$59)*$AC$2*$AD$2*$AE$2+('Demand Base Matrix'!G$56+'Demand Base Matrix'!G$57)*$W$2*$AD$2+'Demand Base Matrix'!G$58*$W$2*$AD$2*$AE$2+'Demand Base Matrix'!G$60+'Demand Base Matrix'!G$61*$AF$2),IF($C5="Explore",('Demand Base Matrix'!G$82*$AC$2*$AD$2*$AE$2*$AF$2+'Demand Base Matrix'!G$83*$W$2*$AC$2*$AD$2*$AE$2*$AF$2+'Demand Base Matrix'!G$84))))) -> 40 | AK5: =IF($C5="Validate",(('Demand Base Matrix'!H$2+'Demand Base Matrix'!H$6)*$AC$2*$AD$2*$AE$2+('Demand Base Matrix'!H$3+'Demand Base Matrix'!H$4)*$W$2*$AD$2+'Demand Base Matrix'!H$5*$W$2*$AD$2*$AE$2+'Demand Base Matrix'!H$7+'Demand Base Matrix'!H$8*$AF$2),IF($C5="Integrate",(('Demand Base Matrix'!H$28+'Demand Base Matrix'!H$32)*$AC$2*$AD$2*$AE$2+('Demand Base Matrix'!H$29+'Demand Base Matrix'!H$30)*$W$2*$AD$2+'Demand Base Matrix'!H$31*$W$2*$AD$2*$AE$2+'Demand Base Matrix'!H$33+'Demand Base Matrix'!H$34*$AF$2),IF($C5="Bond",(('Demand Base Matrix'!H$55+'Demand Base Matrix'!H$59)*$AC$2*$AD$2*$AE$2+('Demand Base Matrix'!H$56+'Demand Base Matrix'!H$57)*$W$2*$AD$2+'Demand Base Matrix'!H$58*$W$2*$AD$2*$AE$2+'Demand Base Matrix'!H$60+'Demand Base Matrix'!H$61*$AF$2),IF($C5="Explore",('Demand Base Matrix'!H$82*$AC$2*$AD$2*$AE$2*$AF$2+'Demand Base Matrix'!H$83*$W$2*$AC$2*$AD$2*$AE$2*$AF$2+'Demand Base Matrix'!H$84))))) -> 60 | AL5: =IF($C5="Validate",(('Demand Base Matrix'!I$2+'Demand Base Matrix'!I$6)*$AC$2*$AD$2*$AE$2+('Demand Base Matrix'!I$3+'Demand Base Matrix'!I$4)*$W$2*$AD$2+'Demand Base Matrix'!I$5*$W$2*$AD$2*$AE$2+'Demand Base Matrix'!I$7+'Demand Base Matrix'!I$8*$AF$2),IF($C5="Integrate",(('Demand Base Matrix'!I$28+'Demand Base Matrix'!I$32)*$AC$2*$AD$2*$AE$2+('Demand Base Matrix'!I$29+'Demand Base Matrix'!I$30)*$W$2*$AD$2+'Demand Base Matrix'!I$31*$W$2*$AD$2*$AE$2+'Demand Base Matrix'!I$33+'Demand Base Matrix'!I$34*$AF$2),IF($C5="Bond",(('Demand Base Matrix'!I$55+'Demand Base Matrix'!I$59)*$AC$2*$AD$2*$AE$2+('Demand Base Matrix'!I$56+'Demand Base Matrix'!I$57)*$W$2*$AD$2+'Demand Base Matrix'!I$58*$W$2*$AD$2*$AE$2+'Demand Base Matrix'!I$60+'Demand Base Matrix'!I$61*$AF$2),IF($C5="Explore",('Demand Base Matrix'!I$82*$AC$2*$AD$2*$AE$2*$AF$2+'Demand Base Matrix'!I$83*$W$2*$AC$2*$AD$2*$AE$2*$AF$2+'Demand Base Matrix'!I$84))))) -> 10 | AM5: =IF($C5="Validate",(('Demand Base Matrix'!J$2+'Demand Base Matrix'!J$6)*$AC$2*$AD$2*$AE$2+('Demand Base Matrix'!J$3+'Demand Base Matrix'!J$4)*$W$2*$AD$2+'Demand Base Matrix'!J$5*$W$2*$AD$2*$AE$2+'Demand Base Matrix'!J$7+'Demand Base Matrix'!J$8*$AF$2),IF($C5="Integrate",(('Demand Base Matrix'!J$28+'Demand Base Matrix'!J$32)*$AC$2*$AD$2*$AE$2+('Demand Base Matrix'!J$29+'Demand Base Matrix'!J$30)*$W$2*$AD$2+'Demand Base Matrix'!J$31*$W$2*$AD$2*$AE$2+'Demand Base Matrix'!J$33+'Demand Base Matrix'!J$34*$AF$2),IF($C5="Bond",(('Demand Base Matrix'!J$55+'Demand Base Matrix'!J$59)*$AC$2*$AD$2*$AE$2+('Demand Base Matrix'!J$56+'Demand Base Matrix'!J$57)*$W$2*$AD$2+'Demand Base Matrix'!J$58*$W$2*$AD$2*$AE$2+'Demand Base Matrix'!J$60+'Demand Base Matrix'!J$61*$AF$2),IF($C5="Explore",('Demand Base Matrix'!J$82*$AC$2*$AD$2*$AE$2*$AF$2+'Demand Base Matrix'!J$83*$W$2*$AC$2*$AD$2*$AE$2*$AF$2+'Demand Base Matrix'!J$84))))) -> 4
A6: [2026 SaaS Y4] Arkansas Valley | B6: Arkansas Valley Electric Cooperative Corporation | C6: Bond | D6: Savannah Peery | E6: Shashank Sharma | F6: Satyam Kumar | I6: =IFERROR(INDEX('Customer 360'!F:F,MATCH(B6,'Customer 360'!A:A,0)),"-") -> C | J6: 6320 | L6: 46239 | M6: 46239 | N6: 2026 | O6: 46023 | P6: IVMS | Q6: =O6 -> 46023 | R6: =IFERROR(IF(M6<>"",M6,IF(L6<>"",L6,INDEX('CSM RDD'!B:B,MATCH(B6,'CSM RDD'!A:A,0)))),"-") -> 46239 | S6: =IFERROR(EOMONTH(Q6,-1)+1,"") -> 46023 | T6: =IFERROR(EOMONTH(R6,-1)+1,"") -> 46235 | U6: =J6+K6 -> 6320 | V6: =IF(C6<>"Validate",DATE(2026,3,1),O6) -> 46082 | W6: =IF(U6=0,1,IF(U6<='Demand Base Matrix'!$K$3,'Demand Base Matrix'!$L$3,IF(U6<='Demand Base Matrix'!$K$4,'Demand Base Matrix'!$L$4,IF(U6<='Demand Base Matrix'!$K$5,'Demand Base Matrix'!$L$5,IF(U6<='Demand Base Matrix'!$K$6,'Demand Base Matrix'!$L$6,IF(U6<='Demand Base Matrix'!$K$7,'Demand Base Matrix'!$L$7)))))) -> 1.25 | X6: =DATE(YEAR(R6),MONTH(R6),1) -> 46235 | Y6: =IF(K6>0,"Tx","Dx") -> Dx | Z6: Low | AA6: Low | AB6: Low | AC6: =IFERROR(INDEX('Demand Base Matrix'!AM:AM,MATCH(Y6,'Demand Base Matrix'!AL:AL,0)),"-") -> 1 | AD6: =IFERROR(INDEX('Demand Base Matrix'!AO:AO,MATCH(Z6,'Demand Base Matrix'!AN:AN,0)),1) -> 1 | AE6: =IFERROR(INDEX('Demand Base Matrix'!AQ:AQ,MATCH(AA6,'Demand Base Matrix'!AP:AP,0)),1) -> 1 | AF6: =IFERROR(INDEX('Demand Base Matrix'!AS:AS,MATCH(AB6,'Demand Base Matrix'!AR:AR,0)),1) -> 1 | AG6: =IF($C6="Validate",(('Demand Base Matrix'!D$2+'Demand Base Matrix'!D$6)*$AC$2*$AD$2*$AE$2+('Demand Base Matrix'!D$3+'Demand Base Matrix'!D$4)*$W$2*$AD$2+'Demand Base Matrix'!D$5*$W$2*$AD$2*$AE$2+'Demand Base Matrix'!D$7+'Demand Base Matrix'!D$8*$AF$2),IF($C6="Integrate",(('Demand Base Matrix'!D$28+'Demand Base Matrix'!D$32)*$AC$2*$AD$2*$AE$2+('Demand Base Matrix'!D$29+'Demand Base Matrix'!D$30)*$W$2*$AD$2+'Demand Base Matrix'!D$31*$W$2*$AD$2*$AE$2+'Demand Base Matrix'!D$33+'Demand Base Matrix'!D$34*$AF$2),IF($C6="Bond",(('Demand Base Matrix'!D$55+'Demand Base Matrix'!D$59)*$AC$2*$AD$2*$AE$2+('Demand Base Matrix'!D$56+'Demand Base Matrix'!D$57)*$W$2*$AD$2+'Demand Base Matrix'!D$58*$W$2*$AD$2*$AE$2+'Demand Base Matrix'!D$60+'Demand Base Matrix'!D$61*$AF$2),IF($C6="Explore",('Demand Base Matrix'!D$82*$AC$2*$AD$2*$AE$2*$AF$2+'Demand Base Matrix'!D$83*$W$2*$AC$2*$AD$2*$AE$2*$AF$2+'Demand Base Matrix'!D$84))))) -> 10 | AH6: =IF($C6="Validate",(('Demand Base Matrix'!E$2+'Demand Base Matrix'!E$6)*$AC$2*$AD$2*$AE$2+('Demand Base Matrix'!E$3+'Demand Base Matrix'!E$4)*$W$2*$AD$2+'Demand Base Matrix'!E$5*$W$2*$AD$2*$AE$2+'Demand Base Matrix'!E$7+'Demand Base Matrix'!E$8*$AF$2),IF($C6="Integrate",(('Demand Base Matrix'!E$28+'Demand Base Matrix'!E$32)*$AC$2*$AD$2*$AE$2+('Demand Base Matrix'!E$29+'Demand Base Matrix'!E$30)*$W$2*$AD$2+'Demand Base Matrix'!E$31*$W$2*$AD$2*$AE$2+'Demand Base Matrix'!E$33+'Demand Base Matrix'!E$34*$AF$2),IF($C6="Bond",(('Demand Base Matrix'!E$55+'Demand Base Matrix'!E$59)*$AC$2*$AD$2*$AE$2+('Demand Base Matrix'!E$56+'Demand Base Matrix'!E$57)*$W$2*$AD$2+'Demand Base Matrix'!E$58*$W$2*$AD$2*$AE$2+'Demand Base Matrix'!E$60+'Demand Base Matrix'!E$61*$AF$2),IF($C6="Explore",('Demand Base Matrix'!E$82*$AC$2*$AD$2*$AE$2*$AF$2+'Demand Base Matrix'!E$83*$W$2*$AC$2*$AD$2*$AE$2*$AF$2+'Demand Base Matrix'!E$84))))) -> 10 | AI6: =IF($C6="Validate",(('Demand Base Matrix'!F$2+'Demand Base Matrix'!F$6)*$AC$2*$AD$2*$AE$2+('Demand Base Matrix'!F$3+'Demand Base Matrix'!F$4)*$W$2*$AD$2+'Demand Base Matrix'!F$5*$W$2*$AD$2*$AE$2+'Demand Base Matrix'!F$7+'Demand Base Matrix'!F$8*$AF$2),IF($C6="Integrate",(('Demand Base Matrix'!F$28+'Demand Base Matrix'!F$32)*$AC$2*$AD$2*$AE$2+('Demand Base Matrix'!F$29+'Demand Base Matrix'!F$30)*$W$2*$AD$2+'Demand Base Matrix'!F$31*$W$2*$AD$2*$AE$2+'Demand Base Matrix'!F$33+'Demand Base Matrix'!F$34*$AF$2),IF($C6="Bond",(('Demand Base Matrix'!F$55+'Demand Base Matrix'!F$59)*$AC$2*$AD$2*$AE$2+('Demand Base Matrix'!F$56+'Demand Base Matrix'!F$57)*$W$2*$AD$2+'Demand Base Matrix'!F$58*$W$2*$AD$2*$AE$2+'Demand Base Matrix'!F$60+'Demand Base Matrix'!F$61*$AF$2),IF($C6="Explore",('Demand Base Matrix'!F$82*$AC$2*$AD$2*$AE$2*$AF$2+'Demand Base Matrix'!F$83*$W$2*$AC$2*$AD$2*$AE$2*$AF$2+'Demand Base Matrix'!F$84))))) -> 10 | AJ6: =IF($C6="Validate",(('Demand Base Matrix'!G$2+'Demand Base Matrix'!G$6)*$AC$2*$AD$2*$AE$2+('Demand Base Matrix'!G$3+'Demand Base Matrix'!G$4)*$W$2*$AD$2+'Demand Base Matrix'!G$5*$W$2*$AD$2*$AE$2+'Demand Base Matrix'!G$7+'Demand Base Matrix'!G$8*$AF$2),IF($C6="Integrate",(('Demand Base Matrix'!G$28+'Demand Base Matrix'!G$32)*$AC$2*$AD$2*$AE$2+('Demand Base Matrix'!G$29+'Demand Base Matrix'!G$30)*$W$2*$AD$2+'Demand Base Matrix'!G$31*$W$2*$AD$2*$AE$2+'Demand Base Matrix'!G$33+'Demand Base Matrix'!G$34*$AF$2),IF($C6="Bond",(('Demand Base Matrix'!G$55+'Demand Base Matrix'!G$59)*$AC$2*$AD$2*$AE$2+('Demand Base Matrix'!G$56+'Demand Base Matrix'!G$57)*$W$2*$AD$2+'Demand Base Matrix'!G$58*$W$2*$AD$2*$AE$2+'Demand Base Matrix'!G$60+'Demand Base Matrix'!G$61*$AF$2),IF($C6="Explore",('Demand Base Matrix'!G$82*$AC$2*$AD$2*$AE$2*$AF$2+'Demand Base Matrix'!G$83*$W$2*$AC$2*$AD$2*$AE$2*$AF$2+'Demand Base Matrix'!G$84))))) -> 50 | AK6: =IF($C6="Validate",(('Demand Base Matrix'!H$2+'Demand Base Matrix'!H$6)*$AC$2*$AD$2*$AE$2+('Demand Base Matrix'!H$3+'Demand Base Matrix'!H$4)*$W$2*$AD$2+'Demand Base Matrix'!H$5*$W$2*$AD$2*$AE$2+'Demand Base Matrix'!H$7+'Demand Base Matrix'!H$8*$AF$2),IF($C6="Integrate",(('Demand Base Matrix'!H$28+'Demand Base Matrix'!H$32)*$AC$2*$AD$2*$AE$2+('Demand Base Matrix'!H$29+'Demand Base Matrix'!H$30)*$W$2*$AD$2+'Demand Base Matrix'!H$31*$W$2*$AD$2*$AE$2+'Demand Base Matrix'!H$33+'Demand Base Matrix'!H$34*$AF$2),IF($C6="Bond",(('Demand Base Matrix'!H$55+'Demand Base Matrix'!H$59)*$AC$2*$AD$2*$AE$2+('Demand Base Matrix'!H$56+'Demand Base Matrix'!H$57)*$W$2*$AD$2+'Demand Base Matrix'!H$58*$W$2*$AD$2*$AE$2+'Demand Base Matrix'!H$60+'Demand Base Matrix'!H$61*$AF$2),IF($C6="Explore",('Demand Base Matrix'!H$82*$AC$2*$AD$2*$AE$2*$AF$2+'Demand Base Matrix'!H$83*$W$2*$AC$2*$AD$2*$AE$2*$AF$2+'Demand Base Matrix'!H$84))))) -> 28 | AL6: =IF($C6="Validate",(('Demand Base Matrix'!I$2+'Demand Base Matrix'!I$6)*$AC$2*$AD$2*$AE$2+('Demand Base Matrix'!I$3+'Demand Base Matrix'!I$4)*$W$2*$AD$2+'Demand Base Matrix'!I$5*$W$2*$AD$2*$AE$2+'Demand Base Matrix'!I$7+'Demand Base Matrix'!I$8*$AF$2),IF($C6="Integrate",(('Demand Base Matrix'!I$28+'Demand Base Matrix'!I$32)*$AC$2*$AD$2*$AE$2+('Demand Base Matrix'!I$29+'Demand Base Matrix'!I$30)*$W$2*$AD$2+'Demand Base Matrix'!I$31*$W$2*$AD$2*$AE$2+'Demand Base Matrix'!I$33+'Demand Base Matrix'!I$34*$AF$2),IF($C6="Bond",(('Demand Base Matrix'!I$55+'Demand Base Matrix'!I$59)*$AC$2*$AD$2*$AE$2+('Demand Base Matrix'!I$56+'Demand Base Matrix'!I$57)*$W$2*$AD$2+'Demand Base Matrix'!I$58*$W$2*$AD$2*$AE$2+'Demand Base Matrix'!I$60+'Demand Base Matrix'!I$61*$AF$2),IF($C6="Explore",('Demand Base Matrix'!I$82*$AC$2*$AD$2*$AE$2*$AF$2+'Demand Base Matrix'!I$83*$W$2*$AC$2*$AD$2*$AE$2*$AF$2+'Demand Base Matrix'!I$84))))) -> 8 | AM6: =IF($C6="Validate",(('Demand Base Matrix'!J$2+'Demand Base Matrix'!J$6)*$AC$2*$AD$2*$AE$2+('Demand Base Matrix'!J$3+'Demand Base Matrix'!J$4)*$W$2*$AD$2+'Demand Base Matrix'!J$5*$W$2*$AD$2*$AE$2+'Demand Base Matrix'!J$7+'Demand Base Matrix'!J$8*$AF$2),IF($C6="Integrate",(('Demand Base Matrix'!J$28+'Demand Base Matrix'!J$32)*$AC$2*$AD$2*$AE$2+('Demand Base Matrix'!J$29+'Demand Base Matrix'!J$30)*$W$2*$AD$2+'Demand Base Matrix'!J$31*$W$2*$AD$2*$AE$2+'Demand Base Matrix'!J$33+'Demand Base Matrix'!J$34*$AF$2),IF($C6="Bond",(('Demand Base Matrix'!J$55+'Demand Base Matrix'!J$59)*$AC$2*$AD$2*$AE$2+('Demand Base Matrix'!J$56+'Demand Base Matrix'!J$57)*$W$2*$AD$2+'Demand Base Matrix'!J$58*$W$2*$AD$2*$AE$2+'Demand Base Matrix'!J$60+'Demand Base Matrix'!J$61*$AF$2),IF($C6="Explore",('Demand Base Matrix'!J$82*$AC$2*$AD$2*$AE$2*$AF$2+'Demand Base Matrix'!J$83*$W$2*$AC$2*$AD$2*$AE$2*$AF$2+'Demand Base Matrix'!J$84))))) -> 8
A7: [2026 SaaS Y6] Avista | B7: Avista Corporation | C7: Integrate | D7: Stefanie Naden | E7: Susheel Srinivas | F7: Vithika Agrawal | I7: =IFERROR(INDEX('Customer 360'!F:F,MATCH(B7,'Customer 360'!A:A,0)),"-") -> C | J7: 7650 | L7: 46300 | M7: 46300 | N7: 2026 | O7: 46023 | P7: IVMS | Q7: =O7 -> 46023 | R7: =IFERROR(IF(M7<>"",M7,IF(L7<>"",L7,INDEX('CSM RDD'!B:B,MATCH(B7,'CSM RDD'!A:A,0)))),"-") -> 46300 | S7: =IFERROR(EOMONTH(Q7,-1)+1,"") -> 46023 | T7: =IFERROR(EOMONTH(R7,-1)+1,"") -> 46296 | U7: =J7+K7 -> 7650 | V7: =IF(C7<>"Validate",DATE(2026,3,1),O7) -> 46082 | W7: =IF(U7=0,1,IF(U7<='Demand Base Matrix'!$K$3,'Demand Base Matrix'!$L$3,IF(U7<='Demand Base Matrix'!$K$4,'Demand Base Matrix'!$L$4,IF(U7<='Demand Base Matrix'!$K$5,'Demand Base Matrix'!$L$5,IF(U7<='Demand Base Matrix'!$K$6,'Demand Base Matrix'!$L$6,IF(U7<='Demand Base Matrix'!$K$7,'Demand Base Matrix'!$L$7)))))) -> 1.25 | X7: =DATE(YEAR(R7),MONTH(R7),1) -> 46296 | Y7: =IF(K7>0,"Tx","Dx") -> Dx | Z7: Low | AA7: Low | AB7: High | AC7: =IFERROR(INDEX('Demand Base Matrix'!AM:AM,MATCH(Y7,'Demand Base Matrix'!AL:AL,0)),"-") -> 1 | AD7: =IFERROR(INDEX('Demand Base Matrix'!AO:AO,MATCH(Z7,'Demand Base Matrix'!AN:AN,0)),1) -> 1 | AE7: =IFERROR(INDEX('Demand Base Matrix'!AQ:AQ,MATCH(AA7,'Demand Base Matrix'!AP:AP,0)),1) -> 1 | AF7: =IFERROR(INDEX('Demand Base Matrix'!AS:AS,MATCH(AB7,'Demand Base Matrix'!AR:AR,0)),1) -> 2 | AG7: =IF($C7="Validate",(('Demand Base Matrix'!D$2+'Demand Base Matrix'!D$6)*$AC$2*$AD$2*$AE$2+('Demand Base Matrix'!D$3+'Demand Base Matrix'!D$4)*$W$2*$AD$2+'Demand Base Matrix'!D$5*$W$2*$AD$2*$AE$2+'Demand Base Matrix'!D$7+'Demand Base Matrix'!D$8*$AF$2),IF($C7="Integrate",(('Demand Base Matrix'!D$28+'Demand Base Matrix'!D$32)*$AC$2*$AD$2*$AE$2+('Demand Base Matrix'!D$29+'Demand Base Matrix'!D$30)*$W$2*$AD$2+'Demand Base Matrix'!D$31*$W$2*$AD$2*$AE$2+'Demand Base Matrix'!D$33+'Demand Base Matrix'!D$34*$AF$2),IF($C7="Bond",(('Demand Base Matrix'!D$55+'Demand Base Matrix'!D$59)*$AC$2*$AD$2*$AE$2+('Demand Base Matrix'!D$56+'Demand Base Matrix'!D$57)*$W$2*$AD$2+'Demand Base Matrix'!D$58*$W$2*$AD$2*$AE$2+'Demand Base Matrix'!D$60+'Demand Base Matrix'!D$61*$AF$2),IF($C7="Explore",('Demand Base Matrix'!D$82*$AC$2*$AD$2*$AE$2*$AF$2+'Demand Base Matrix'!D$83*$W$2*$AC$2*$AD$2*$AE$2*$AF$2+'Demand Base Matrix'!D$84))))) -> 10 | AH7: =IF($C7="Validate",(('Demand Base Matrix'!E$2+'Demand Base Matrix'!E$6)*$AC$2*$AD$2*$AE$2+('Demand Base Matrix'!E$3+'Demand Base Matrix'!E$4)*$W$2*$AD$2+'Demand Base Matrix'!E$5*$W$2*$AD$2*$AE$2+'Demand Base Matrix'!E$7+'Demand Base Matrix'!E$8*$AF$2),IF($C7="Integrate",(('Demand Base Matrix'!E$28+'Demand Base Matrix'!E$32)*$AC$2*$AD$2*$AE$2+('Demand Base Matrix'!E$29+'Demand Base Matrix'!E$30)*$W$2*$AD$2+'Demand Base Matrix'!E$31*$W$2*$AD$2*$AE$2+'Demand Base Matrix'!E$33+'Demand Base Matrix'!E$34*$AF$2),IF($C7="Bond",(('Demand Base Matrix'!E$55+'Demand Base Matrix'!E$59)*$AC$2*$AD$2*$AE$2+('Demand Base Matrix'!E$56+'Demand Base Matrix'!E$57)*$W$2*$AD$2+'Demand Base Matrix'!E$58*$W$2*$AD$2*$AE$2+'Demand Base Matrix'!E$60+'Demand Base Matrix'!E$61*$AF$2),IF($C7="Explore",('Demand Base Matrix'!E$82*$AC$2*$AD$2*$AE$2*$AF$2+'Demand Base Matrix'!E$83*$W$2*$AC$2*$AD$2*$AE$2*$AF$2+'Demand Base Matrix'!E$84))))) -> 20 | AI7: =IF($C7="Validate",(('Demand Base Matrix'!F$2+'Demand Base Matrix'!F$6)*$AC$2*$AD$2*$AE$2+('Demand Base Matrix'!F$3+'Demand Base Matrix'!F$4)*$W$2*$AD$2+'Demand Base Matrix'!F$5*$W$2*$AD$2*$AE$2+'Demand Base Matrix'!F$7+'Demand Base Matrix'!F$8*$AF$2),IF($C7="Integrate",(('Demand Base Matrix'!F$28+'Demand Base Matrix'!F$32)*$AC$2*$AD$2*$AE$2+('Demand Base Matrix'!F$29+'Demand Base Matrix'!F$30)*$W$2*$AD$2+'Demand Base Matrix'!F$31*$W$2*$AD$2*$AE$2+'Demand Base Matrix'!F$33+'Demand Base Matrix'!F$34*$AF$2),IF($C7="Bond",(('Demand Base Matrix'!F$55+'Demand Base Matrix'!F$59)*$AC$2*$AD$2*$AE$2+('Demand Base Matrix'!F$56+'Demand Base Matrix'!F$57)*$W$2*$AD$2+'Demand Base Matrix'!F$58*$W$2*$AD$2*$AE$2+'Demand Base Matrix'!F$60+'Demand Base Matrix'!F$61*$AF$2),IF($C7="Explore",('Demand Base Matrix'!F$82*$AC$2*$AD$2*$AE$2*$AF$2+'Demand Base Matrix'!F$83*$W$2*$AC$2*$AD$2*$AE$2*$AF$2+'Demand Base Matrix'!F$84))))) -> 10 | AJ7: =IF($C7="Validate",(('Demand Base Matrix'!G$2+'Demand Base Matrix'!G$6)*$AC$2*$AD$2*$AE$2+('Demand Base Matrix'!G$3+'Demand Base Matrix'!G$4)*$W$2*$AD$2+'Demand Base Matrix'!G$5*$W$2*$AD$2*$AE$2+'Demand Base Matrix'!G$7+'Demand Base Matrix'!G$8*$AF$2),IF($C7="Integrate",(('Demand Base Matrix'!G$28+'Demand Base Matrix'!G$32)*$AC$2*$AD$2*$AE$2+('Demand Base Matrix'!G$29+'Demand Base Matrix'!G$30)*$W$2*$AD$2+'Demand Base Matrix'!G$31*$W$2*$AD$2*$AE$2+'Demand Base Matrix'!G$33+'Demand Base Matrix'!G$34*$AF$2),IF($C7="Bond",(('Demand Base Matrix'!G$55+'Demand Base Matrix'!G$59)*$AC$2*$AD$2*$AE$2+('Demand Base Matrix'!G$56+'Demand Base Matrix'!G$57)*$W$2*$AD$2+'Demand Base Matrix'!G$58*$W$2*$AD$2*$AE$2+'Demand Base Matrix'!G$60+'Demand Base Matrix'!G$61*$AF$2),IF($C7="Explore",('Demand Base Matrix'!G$82*$AC$2*$AD$2*$AE$2*$AF$2+'Demand Base Matrix'!G$83*$W$2*$AC$2*$AD$2*$AE$2*$AF$2+'Demand Base Matrix'!G$84))))) -> 60 | AK7: =IF($C7="Validate",(('Demand Base Matrix'!H$2+'Demand Base Matrix'!H$6)*$AC$2*$AD$2*$AE$2+('Demand Base Matrix'!H$3+'Demand Base Matrix'!H$4)*$W$2*$AD$2+'Demand Base Matrix'!H$5*$W$2*$AD$2*$AE$2+'Demand Base Matrix'!H$7+'Demand Base Matrix'!H$8*$AF$2),IF($C7="Integrate",(('Demand Base Matrix'!H$28+'Demand Base Matrix'!H$32)*$AC$2*$AD$2*$AE$2+('Demand Base Matrix'!H$29+'Demand Base Matrix'!H$30)*$W$2*$AD$2+'Demand Base Matrix'!H$31*$W$2*$AD$2*$AE$2+'Demand Base Matrix'!H$33+'Demand Base Matrix'!H$34*$AF$2),IF($C7="Bond",(('Demand Base Matrix'!H$55+'Demand Base Matrix'!H$59)*$AC$2*$AD$2*$AE$2+('Demand Base Matrix'!H$56+'Demand Base Matrix'!H$57)*$W$2*$AD$2+'Demand Base Matrix'!H$58*$W$2*$AD$2*$AE$2+'Demand Base Matrix'!H$60+'Demand Base Matrix'!H$61*$AF$2),IF($C7="Explore",('Demand Base Matrix'!H$82*$AC$2*$AD$2*$AE$2*$AF$2+'Demand Base Matrix'!H$83*$W$2*$AC$2*$AD$2*$AE$2*$AF$2+'Demand Base Matrix'!H$84))))) -> 28 | AL7: =IF($C7="Validate",(('Demand Base Matrix'!I$2+'Demand Base Matrix'!I$6)*$AC$2*$AD$2*$AE$2+('Demand Base Matrix'!I$3+'Demand Base Matrix'!I$4)*$W$2*$AD$2+'Demand Base Matrix'!I$5*$W$2*$AD$2*$AE$2+'Demand Base Matrix'!I$7+'Demand Base Matrix'!I$8*$AF$2),IF($C7="Integrate",(('Demand Base Matrix'!I$28+'Demand Base Matrix'!I$32)*$AC$2*$AD$2*$AE$2+('Demand Base Matrix'!I$29+'Demand Base Matrix'!I$30)*$W$2*$AD$2+'Demand Base Matrix'!I$31*$W$2*$AD$2*$AE$2+'Demand Base Matrix'!I$33+'Demand Base Matrix'!I$34*$AF$2),IF($C7="Bond",(('Demand Base Matrix'!I$55+'Demand Base Matrix'!I$59)*$AC$2*$AD$2*$AE$2+('Demand Base Matrix'!I$56+'Demand Base Matrix'!I$57)*$W$2*$AD$2+'Demand Base Matrix'!I$58*$W$2*$AD$2*$AE$2+'Demand Base Matrix'!I$60+'Demand Base Matrix'!I$61*$AF$2),IF($C7="Explore",('Demand Base Matrix'!I$82*$AC$2*$AD$2*$AE$2*$AF$2+'Demand Base Matrix'!I$83*$W$2*$AC$2*$AD$2*$AE$2*$AF$2+'Demand Base Matrix'!I$84))))) -> 8 | AM7: =IF($C7="Validate",(('Demand Base Matrix'!J$2+'Demand Base Matrix'!J$6)*$AC$2*$AD$2*$AE$2+('Demand Base Matrix'!J$3+'Demand Base Matrix'!J$4)*$W$2*$AD$2+'Demand Base Matrix'!J$5*$W$2*$AD$2*$AE$2+'Demand Base Matrix'!J$7+'Demand Base Matrix'!J$8*$AF$2),IF($C7="Integrate",(('Demand Base Matrix'!J$28+'Demand Base Matrix'!J$32)*$AC$2*$AD$2*$AE$2+('Demand Base Matrix'!J$29+'Demand Base Matrix'!J$30)*$W$2*$AD$2+'Demand Base Matrix'!J$31*$W$2*$AD$2*$AE$2+'Demand Base Matrix'!J$33+'Demand Base Matrix'!J$34*$AF$2),IF($C7="Bond",(('Demand Base Matrix'!J$55+'Demand Base Matrix'!J$59)*$AC$2*$AD$2*$AE$2+('Demand Base Matrix'!J$56+'Demand Base Matrix'!J$57)*$W$2*$AD$2+'Demand Base Matrix'!J$58*$W$2*$AD$2*$AE$2+'Demand Base Matrix'!J$60+'Demand Base Matrix'!J$61*$AF$2),IF($C7="Explore",('Demand Base Matrix'!J$82*$AC$2*$AD$2*$AE$2*$AF$2+'Demand Base Matrix'!J$83*$W$2*$AC$2*$AD$2*$AE$2*$AF$2+'Demand Base Matrix'!J$84))))) -> 8
A8: [2026 [SaaS Y4] Bear Valley | B8: Bear Valley Electric Service | C8: Bond | D8: Grant Lee | E8: Mannat Padha | F8: Satyam Kumar | I8: =IFERROR(INDEX('Customer 360'!F:F,MATCH(B8,'Customer 360'!A:A,0)),"-") -> C | J8: 206 | K8: 0 | L8: 46293 | M8: 46293 | N8: 2026 | O8: 46023 | P8: IVMS | Q8: =O8 -> 46023 | R8: =IFERROR(IF(M8<>"",M8,IF(L8<>"",L8,INDEX('CSM RDD'!B:B,MATCH(B8,'CSM RDD'!A:A,0)))),"-") -> 46293 | S8: =IFERROR(EOMONTH(Q8,-1)+1,"") -> 46023 | T8: =IFERROR(EOMONTH(R8,-1)+1,"") -> 46266 | U8: =J8+K8 -> 206 | V8: =IF(C8<>"Validate",DATE(2026,3,1),O8) -> 46082 | W8: =IF(U8=0,1,IF(U8<='Demand Base Matrix'!$K$3,'Demand Base Matrix'!$L$3,IF(U8<='Demand Base Matrix'!$K$4,'Demand Base Matrix'!$L$4,IF(U8<='Demand Base Matrix'!$K$5,'Demand Base Matrix'!$L$5,IF(U8<='Demand Base Matrix'!$K$6,'Demand Base Matrix'!$L$6,IF(U8<='Demand Base Matrix'!$K$7,'Demand Base Matrix'!$L$7)))))) -> 0.75 | X8: =DATE(YEAR(R8),MONTH(R8),1) -> 46266 | Y8: =IF(K8>0,"Tx","Dx") -> Dx | Z8: Medium | AA8: Low | AB8: Low | AC8: =IFERROR(INDEX('Demand Base Matrix'!AM:AM,MATCH(Y8,'Demand Base Matrix'!AL:AL,0)),"-") -> 1 | AD8: =IFERROR(INDEX('Demand Base Matrix'!AO:AO,MATCH(Z8,'Demand Base Matrix'!AN:AN,0)),1) -> 1.25 | AE8: =IFERROR(INDEX('Demand Base Matrix'!AQ:AQ,MATCH(AA8,'Demand Base Matrix'!AP:AP,0)),1) -> 1 | AF8: =IFERROR(INDEX('Demand Base Matrix'!AS:AS,MATCH(AB8,'Demand Base Matrix'!AR:AR,0)),1) -> 1 | AG8: =IF($C8="Validate",(('Demand Base Matrix'!D$2+'Demand Base Matrix'!D$6)*$AC$2*$AD$2*$AE$2+('Demand Base Matrix'!D$3+'Demand Base Matrix'!D$4)*$W$2*$AD$2+'Demand Base Matrix'!D$5*$W$2*$AD$2*$AE$2+'Demand Base Matrix'!D$7+'Demand Base Matrix'!D$8*$AF$2),IF($C8="Integrate",(('Demand Base Matrix'!D$28+'Demand Base Matrix'!D$32)*$AC$2*$AD$2*$AE$2+('Demand Base Matrix'!D$29+'Demand Base Matrix'!D$30)*$W$2*$AD$2+'Demand Base Matrix'!D$31*$W$2*$AD$2*$AE$2+'Demand Base Matrix'!D$33+'Demand Base Matrix'!D$34*$AF$2),IF($C8="Bond",(('Demand Base Matrix'!D$55+'Demand Base Matrix'!D$59)*$AC$2*$AD$2*$AE$2+('Demand Base Matrix'!D$56+'Demand Base Matrix'!D$57)*$W$2*$AD$2+'Demand Base Matrix'!D$58*$W$2*$AD$2*$AE$2+'Demand Base Matrix'!D$60+'Demand Base Matrix'!D$61*$AF$2),IF($C8="Explore",('Demand Base Matrix'!D$82*$AC$2*$AD$2*$AE$2*$AF$2+'Demand Base Matrix'!D$83*$W$2*$AC$2*$AD$2*$AE$2*$AF$2+'Demand Base Matrix'!D$84))))) -> 10 | AH8: =IF($C8="Validate",(('Demand Base Matrix'!E$2+'Demand Base Matrix'!E$6)*$AC$2*$AD$2*$AE$2+('Demand Base Matrix'!E$3+'Demand Base Matrix'!E$4)*$W$2*$AD$2+'Demand Base Matrix'!E$5*$W$2*$AD$2*$AE$2+'Demand Base Matrix'!E$7+'Demand Base Matrix'!E$8*$AF$2),IF($C8="Integrate",(('Demand Base Matrix'!E$28+'Demand Base Matrix'!E$32)*$AC$2*$AD$2*$AE$2+('Demand Base Matrix'!E$29+'Demand Base Matrix'!E$30)*$W$2*$AD$2+'Demand Base Matrix'!E$31*$W$2*$AD$2*$AE$2+'Demand Base Matrix'!E$33+'Demand Base Matrix'!E$34*$AF$2),IF($C8="Bond",(('Demand Base Matrix'!E$55+'Demand Base Matrix'!E$59)*$AC$2*$AD$2*$AE$2+('Demand Base Matrix'!E$56+'Demand Base Matrix'!E$57)*$W$2*$AD$2+'Demand Base Matrix'!E$58*$W$2*$AD$2*$AE$2+'Demand Base Matrix'!E$60+'Demand Base Matrix'!E$61*$AF$2),IF($C8="Explore",('Demand Base Matrix'!E$82*$AC$2*$AD$2*$AE$2*$AF$2+'Demand Base Matrix'!E$83*$W$2*$AC$2*$AD$2*$AE$2*$AF$2+'Demand Base Matrix'!E$84))))) -> 10 | AI8: =IF($C8="Validate",(('Demand Base Matrix'!F$2+'Demand Base Matrix'!F$6)*$AC$2*$AD$2*$AE$2+('Demand Base Matrix'!F$3+'Demand Base Matrix'!F$4)*$W$2*$AD$2+'Demand Base Matrix'!F$5*$W$2*$AD$2*$AE$2+'Demand Base Matrix'!F$7+'Demand Base Matrix'!F$8*$AF$2),IF($C8="Integrate",(('Demand Base Matrix'!F$28+'Demand Base Matrix'!F$32)*$AC$2*$AD$2*$AE$2+('Demand Base Matrix'!F$29+'Demand Base Matrix'!F$30)*$W$2*$AD$2+'Demand Base Matrix'!F$31*$W$2*$AD$2*$AE$2+'Demand Base Matrix'!F$33+'Demand Base Matrix'!F$34*$AF$2),IF($C8="Bond",(('Demand Base Matrix'!F$55+'Demand Base Matrix'!F$59)*$AC$2*$AD$2*$AE$2+('Demand Base Matrix'!F$56+'Demand Base Matrix'!F$57)*$W$2*$AD$2+'Demand Base Matrix'!F$58*$W$2*$AD$2*$AE$2+'Demand Base Matrix'!F$60+'Demand Base Matrix'!F$61*$AF$2),IF($C8="Explore",('Demand Base Matrix'!F$82*$AC$2*$AD$2*$AE$2*$AF$2+'Demand Base Matrix'!F$83*$W$2*$AC$2*$AD$2*$AE$2*$AF$2+'Demand Base Matrix'!F$84))))) -> 10 | AJ8: =IF($C8="Validate",(('Demand Base Matrix'!G$2+'Demand Base Matrix'!G$6)*$AC$2*$AD$2*$AE$2+('Demand Base Matrix'!G$3+'Demand Base Matrix'!G$4)*$W$2*$AD$2+'Demand Base Matrix'!G$5*$W$2*$AD$2*$AE$2+'Demand Base Matrix'!G$7+'Demand Base Matrix'!G$8*$AF$2),IF($C8="Integrate",(('Demand Base Matrix'!G$28+'Demand Base Matrix'!G$32)*$AC$2*$AD$2*$AE$2+('Demand Base Matrix'!G$29+'Demand Base Matrix'!G$30)*$W$2*$AD$2+'Demand Base Matrix'!G$31*$W$2*$AD$2*$AE$2+'Demand Base Matrix'!G$33+'Demand Base Matrix'!G$34*$AF$2),IF($C8="Bond",(('Demand Base Matrix'!G$55+'Demand Base Matrix'!G$59)*$AC$2*$AD$2*$AE$2+('Demand Base Matrix'!G$56+'Demand Base Matrix'!G$57)*$W$2*$AD$2+'Demand Base Matrix'!G$58*$W$2*$AD$2*$AE$2+'Demand Base Matrix'!G$60+'Demand Base Matrix'!G$61*$AF$2),IF($C8="Explore",('Demand Base Matrix'!G$82*$AC$2*$AD$2*$AE$2*$AF$2+'Demand Base Matrix'!G$83*$W$2*$AC$2*$AD$2*$AE$2*$AF$2+'Demand Base Matrix'!G$84))))) -> 50 | AK8: =IF($C8="Validate",(('Demand Base Matrix'!H$2+'Demand Base Matrix'!H$6)*$AC$2*$AD$2*$AE$2+('Demand Base Matrix'!H$3+'Demand Base Matrix'!H$4)*$W$2*$AD$2+'Demand Base Matrix'!H$5*$W$2*$AD$2*$AE$2+'Demand Base Matrix'!H$7+'Demand Base Matrix'!H$8*$AF$2),IF($C8="Integrate",(('Demand Base Matrix'!H$28+'Demand Base Matrix'!H$32)*$AC$2*$AD$2*$AE$2+('Demand Base Matrix'!H$29+'Demand Base Matrix'!H$30)*$W$2*$AD$2+'Demand Base Matrix'!H$31*$W$2*$AD$2*$AE$2+'Demand Base Matrix'!H$33+'Demand Base Matrix'!H$34*$AF$2),IF($C8="Bond",(('Demand Base Matrix'!H$55+'Demand Base Matrix'!H$59)*$AC$2*$AD$2*$AE$2+('Demand Base Matrix'!H$56+'Demand Base Matrix'!H$57)*$W$2*$AD$2+'Demand Base Matrix'!H$58*$W$2*$AD$2*$AE$2+'Demand Base Matrix'!H$60+'Demand Base Matrix'!H$61*$AF$2),IF($C8="Explore",('Demand Base Matrix'!H$82*$AC$2*$AD$2*$AE$2*$AF$2+'Demand Base Matrix'!H$83*$W$2*$AC$2*$AD$2*$AE$2*$AF$2+'Demand Base Matrix'!H$84))))) -> 28 | AL8: =IF($C8="Validate",(('Demand Base Matrix'!I$2+'Demand Base Matrix'!I$6)*$AC$2*$AD$2*$AE$2+('Demand Base Matrix'!I$3+'Demand Base Matrix'!I$4)*$W$2*$AD$2+'Demand Base Matrix'!I$5*$W$2*$AD$2*$AE$2+'Demand Base Matrix'!I$7+'Demand Base Matrix'!I$8*$AF$2),IF($C8="Integrate",(('Demand Base Matrix'!I$28+'Demand Base Matrix'!I$32)*$AC$2*$AD$2*$AE$2+('Demand Base Matrix'!I$29+'Demand Base Matrix'!I$30)*$W$2*$AD$2+'Demand Base Matrix'!I$31*$W$2*$AD$2*$AE$2+'Demand Base Matrix'!I$33+'Demand Base Matrix'!I$34*$AF$2),IF($C8="Bond",(('Demand Base Matrix'!I$55+'Demand Base Matrix'!I$59)*$AC$2*$AD$2*$AE$2+('Demand Base Matrix'!I$56+'Demand Base Matrix'!I$57)*$W$2*$AD$2+'Demand Base Matrix'!I$58*$W$2*$AD$2*$AE$2+'Demand Base Matrix'!I$60+'Demand Base Matrix'!I$61*$AF$2),IF($C8="Explore",('Demand Base Matrix'!I$82*$AC$2*$AD$2*$AE$2*$AF$2+'Demand Base Matrix'!I$83*$W$2*$AC$2*$AD$2*$AE$2*$AF$2+'Demand Base Matrix'!I$84))))) -> 8 | AM8: =IF($C8="Validate",(('Demand Base Matrix'!J$2+'Demand Base Matrix'!J$6)*$AC$2*$AD$2*$AE$2+('Demand Base Matrix'!J$3+'Demand Base Matrix'!J$4)*$W$2*$AD$2+'Demand Base Matrix'!J$5*$W$2*$AD$2*$AE$2+'Demand Base Matrix'!J$7+'Demand Base Matrix'!J$8*$AF$2),IF($C8="Integrate",(('Demand Base Matrix'!J$28+'Demand Base Matrix'!J$32)*$AC$2*$AD$2*$AE$2+('Demand Base Matrix'!J$29+'Demand Base Matrix'!J$30)*$W$2*$AD$2+'Demand Base Matrix'!J$31*$W$2*$AD$2*$AE$2+'Demand Base Matrix'!J$33+'Demand Base Matrix'!J$34*$AF$2),IF($C8="Bond",(('Demand Base Matrix'!J$55+'Demand Base Matrix'!J$59)*$AC$2*$AD$2*$AE$2+('Demand Base Matrix'!J$56+'Demand Base Matrix'!J$57)*$W$2*$AD$2+'Demand Base Matrix'!J$58*$W$2*$AD$2*$AE$2+'Demand Base Matrix'!J$60+'Demand Base Matrix'!J$61*$AF$2),IF($C8="Explore",('Demand Base Matrix'!J$82*$AC$2*$AD$2*$AE$2*$AF$2+'Demand Base Matrix'!J$83*$W$2*$AC$2*$AD$2*$AE$2*$AF$2+'Demand Base Matrix'!J$84))))) -> 8
A9: [2026 SaaS Y1] Beauregard Electric Cooperative | B9: Beauregard Electric Cooperative | C9: Validate | D9: Stefanie Naden | E9: Shashank Sharma | F9: Satyam Kumar | I9: =IFERROR(INDEX('Customer 360'!F:F,MATCH(B9,'Customer 360'!A:A,0)),"-") -> C | J9: 320 | L9: 46157 | M9: 46157 | N9: 2026 | O9: 46082 | P9: IVMS | Q9: =O9 -> 46082 | R9: =IFERROR(IF(M9<>"",M9,IF(L9<>"",L9,INDEX('CSM RDD'!B:B,MATCH(B9,'CSM RDD'!A:A,0)))),"-") -> 46157 | S9: =IFERROR(EOMONTH(Q9,-1)+1,"") -> 46082 | T9: =IFERROR(EOMONTH(R9,-1)+1,"") -> 46143 | U9: =J9+K9 -> 320 | V9: =IF(C9<>"Validate",DATE(2026,3,1),O9) -> 46082 | W9: =IF(U9=0,1,IF(U9<='Demand Base Matrix'!$K$3,'Demand Base Matrix'!$L$3,IF(U9<='Demand Base Matrix'!$K$4,'Demand Base Matrix'!$L$4,IF(U9<='Demand Base Matrix'!$K$5,'Demand Base Matrix'!$L$5,IF(U9<='Demand Base Matrix'!$K$6,'Demand Base Matrix'!$L$6,IF(U9<='Demand Base Matrix'!$K$7,'Demand Base Matrix'!$L$7)))))) -> 0.75 | X9: =DATE(YEAR(R9),MONTH(R9),1) -> 46143 | Y9: =IF(K9>0,"Tx","Dx") -> Dx | Z9: - | AA9: - | AB9: - | AC9: =IFERROR(INDEX('Demand Base Matrix'!AM:AM,MATCH(Y9,'Demand Base Matrix'!AL:AL,0)),"-") -> 1 | AD9: =IFERROR(INDEX('Demand Base Matrix'!AO:AO,MATCH(Z9,'Demand Base Matrix'!AN:AN,0)),1) -> 1 | AE9: =IFERROR(INDEX('Demand Base Matrix'!AQ:AQ,MATCH(AA9,'Demand Base Matrix'!AP:AP,0)),1) -> 1 | AF9: =IFERROR(INDEX('Demand Base Matrix'!AS:AS,MATCH(AB9,'Demand Base Matrix'!AR:AR,0)),1) -> 1 | AG9: =IF($C9="Validate",(('Demand Base Matrix'!D$2+'Demand Base Matrix'!D$6)*$AC$2*$AD$2*$AE$2+('Demand Base Matrix'!D$3+'Demand Base Matrix'!D$4)*$W$2*$AD$2+'Demand Base Matrix'!D$5*$W$2*$AD$2*$AE$2+'Demand Base Matrix'!D$7+'Demand Base Matrix'!D$8*$AF$2),IF($C9="Integrate",(('Demand Base Matrix'!D$28+'Demand Base Matrix'!D$32)*$AC$2*$AD$2*$AE$2+('Demand Base Matrix'!D$29+'Demand Base Matrix'!D$30)*$W$2*$AD$2+'Demand Base Matrix'!D$31*$W$2*$AD$2*$AE$2+'Demand Base Matrix'!D$33+'Demand Base Matrix'!D$34*$AF$2),IF($C9="Bond",(('Demand Base Matrix'!D$55+'Demand Base Matrix'!D$59)*$AC$2*$AD$2*$AE$2+('Demand Base Matrix'!D$56+'Demand Base Matrix'!D$57)*$W$2*$AD$2+'Demand Base Matrix'!D$58*$W$2*$AD$2*$AE$2+'Demand Base Matrix'!D$60+'Demand Base Matrix'!D$61*$AF$2),IF($C9="Explore",('Demand Base Matrix'!D$82*$AC$2*$AD$2*$AE$2*$AF$2+'Demand Base Matrix'!D$83*$W$2*$AC$2*$AD$2*$AE$2*$AF$2+'Demand Base Matrix'!D$84))))) -> 15 | AH9: =IF($C9="Validate",(('Demand Base Matrix'!E$2+'Demand Base Matrix'!E$6)*$AC$2*$AD$2*$AE$2+('Demand Base Matrix'!E$3+'Demand Base Matrix'!E$4)*$W$2*$AD$2+'Demand Base Matrix'!E$5*$W$2*$AD$2*$AE$2+'Demand Base Matrix'!E$7+'Demand Base Matrix'!E$8*$AF$2),IF($C9="Integrate",(('Demand Base Matrix'!E$28+'Demand Base Matrix'!E$32)*$AC$2*$AD$2*$AE$2+('Demand Base Matrix'!E$29+'Demand Base Matrix'!E$30)*$W$2*$AD$2+'Demand Base Matrix'!E$31*$W$2*$AD$2*$AE$2+'Demand Base Matrix'!E$33+'Demand Base Matrix'!E$34*$AF$2),IF($C9="Bond",(('Demand Base Matrix'!E$55+'Demand Base Matrix'!E$59)*$AC$2*$AD$2*$AE$2+('Demand Base Matrix'!E$56+'Demand Base Matrix'!E$57)*$W$2*$AD$2+'Demand Base Matrix'!E$58*$W$2*$AD$2*$AE$2+'Demand Base Matrix'!E$60+'Demand Base Matrix'!E$61*$AF$2),IF($C9="Explore",('Demand Base Matrix'!E$82*$AC$2*$AD$2*$AE$2*$AF$2+'Demand Base Matrix'!E$83*$W$2*$AC$2*$AD$2*$AE$2*$AF$2+'Demand Base Matrix'!E$84))))) -> 15 | AI9: =IF($C9="Validate",(('Demand Base Matrix'!F$2+'Demand Base Matrix'!F$6)*$AC$2*$AD$2*$AE$2+('Demand Base Matrix'!F$3+'Demand Base Matrix'!F$4)*$W$2*$AD$2+'Demand Base Matrix'!F$5*$W$2*$AD$2*$AE$2+'Demand Base Matrix'!F$7+'Demand Base Matrix'!F$8*$AF$2),IF($C9="Integrate",(('Demand Base Matrix'!F$28+'Demand Base Matrix'!F$32)*$AC$2*$AD$2*$AE$2+('Demand Base Matrix'!F$29+'Demand Base Matrix'!F$30)*$W$2*$AD$2+'Demand Base Matrix'!F$31*$W$2*$AD$2*$AE$2+'Demand Base Matrix'!F$33+'Demand Base Matrix'!F$34*$AF$2),IF($C9="Bond",(('Demand Base Matrix'!F$55+'Demand Base Matrix'!F$59)*$AC$2*$AD$2*$AE$2+('Demand Base Matrix'!F$56+'Demand Base Matrix'!F$57)*$W$2*$AD$2+'Demand Base Matrix'!F$58*$W$2*$AD$2*$AE$2+'Demand Base Matrix'!F$60+'Demand Base Matrix'!F$61*$AF$2),IF($C9="Explore",('Demand Base Matrix'!F$82*$AC$2*$AD$2*$AE$2*$AF$2+'Demand Base Matrix'!F$83*$W$2*$AC$2*$AD$2*$AE$2*$AF$2+'Demand Base Matrix'!F$84))))) -> 7 | AJ9: =IF($C9="Validate",(('Demand Base Matrix'!G$2+'Demand Base Matrix'!G$6)*$AC$2*$AD$2*$AE$2+('Demand Base Matrix'!G$3+'Demand Base Matrix'!G$4)*$W$2*$AD$2+'Demand Base Matrix'!G$5*$W$2*$AD$2*$AE$2+'Demand Base Matrix'!G$7+'Demand Base Matrix'!G$8*$AF$2),IF($C9="Integrate",(('Demand Base Matrix'!G$28+'Demand Base Matrix'!G$32)*$AC$2*$AD$2*$AE$2+('Demand Base Matrix'!G$29+'Demand Base Matrix'!G$30)*$W$2*$AD$2+'Demand Base Matrix'!G$31*$W$2*$AD$2*$AE$2+'Demand Base Matrix'!G$33+'Demand Base Matrix'!G$34*$AF$2),IF($C9="Bond",(('Demand Base Matrix'!G$55+'Demand Base Matrix'!G$59)*$AC$2*$AD$2*$AE$2+('Demand Base Matrix'!G$56+'Demand Base Matrix'!G$57)*$W$2*$AD$2+'Demand Base Matrix'!G$58*$W$2*$AD$2*$AE$2+'Demand Base Matrix'!G$60+'Demand Base Matrix'!G$61*$AF$2),IF($C9="Explore",('Demand Base Matrix'!G$82*$AC$2*$AD$2*$AE$2*$AF$2+'Demand Base Matrix'!G$83*$W$2*$AC$2*$AD$2*$AE$2*$AF$2+'Demand Base Matrix'!G$84))))) -> 40 | AK9: =IF($C9="Validate",(('Demand Base Matrix'!H$2+'Demand Base Matrix'!H$6)*$AC$2*$AD$2*$AE$2+('Demand Base Matrix'!H$3+'Demand Base Matrix'!H$4)*$W$2*$AD$2+'Demand Base Matrix'!H$5*$W$2*$AD$2*$AE$2+'Demand Base Matrix'!H$7+'Demand Base Matrix'!H$8*$AF$2),IF($C9="Integrate",(('Demand Base Matrix'!H$28+'Demand Base Matrix'!H$32)*$AC$2*$AD$2*$AE$2+('Demand Base Matrix'!H$29+'Demand Base Matrix'!H$30)*$W$2*$AD$2+'Demand Base Matrix'!H$31*$W$2*$AD$2*$AE$2+'Demand Base Matrix'!H$33+'Demand Base Matrix'!H$34*$AF$2),IF($C9="Bond",(('Demand Base Matrix'!H$55+'Demand Base Matrix'!H$59)*$AC$2*$AD$2*$AE$2+('Demand Base Matrix'!H$56+'Demand Base Matrix'!H$57)*$W$2*$AD$2+'Demand Base Matrix'!H$58*$W$2*$AD$2*$AE$2+'Demand Base Matrix'!H$60+'Demand Base Matrix'!H$61*$AF$2),IF($C9="Explore",('Demand Base Matrix'!H$82*$AC$2*$AD$2*$AE$2*$AF$2+'Demand Base Matrix'!H$83*$W$2*$AC$2*$AD$2*$AE$2*$AF$2+'Demand Base Matrix'!H$84))))) -> 60 | AL9: =IF($C9="Validate",(('Demand Base Matrix'!I$2+'Demand Base Matrix'!I$6)*$AC$2*$AD$2*$AE$2+('Demand Base Matrix'!I$3+'Demand Base Matrix'!I$4)*$W$2*$AD$2+'Demand Base Matrix'!I$5*$W$2*$AD$2*$AE$2+'Demand Base Matrix'!I$7+'Demand Base Matrix'!I$8*$AF$2),IF($C9="Integrate",(('Demand Base Matrix'!I$28+'Demand Base Matrix'!I$32)*$AC$2*$AD$2*$AE$2+('Demand Base Matrix'!I$29+'Demand Base Matrix'!I$30)*$W$2*$AD$2+'Demand Base Matrix'!I$31*$W$2*$AD$2*$AE$2+'Demand Base Matrix'!I$33+'Demand Base Matrix'!I$34*$AF$2),IF($C9="Bond",(('Demand Base Matrix'!I$55+'Demand Base Matrix'!I$59)*$AC$2*$AD$2*$AE$2+('Demand Base Matrix'!I$56+'Demand Base Matrix'!I$57)*$W$2*$AD$2+'Demand Base Matrix'!I$58*$W$2*$AD$2*$AE$2+'Demand Base Matrix'!I$60+'Demand Base Matrix'!I$61*$AF$2),IF($C9="Explore",('Demand Base Matrix'!I$82*$AC$2*$AD$2*$AE$2*$AF$2+'Demand Base Matrix'!I$83*$W$2*$AC$2*$AD$2*$AE$2*$AF$2+'Demand Base Matrix'!I$84))))) -> 10 | AM9: =IF($C9="Validate",(('Demand Base Matrix'!J$2+'Demand Base Matrix'!J$6)*$AC$2*$AD$2*$AE$2+('Demand Base Matrix'!J$3+'Demand Base Matrix'!J$4)*$W$2*$AD$2+'Demand Base Matrix'!J$5*$W$2*$AD$2*$AE$2+'Demand Base Matrix'!J$7+'Demand Base Matrix'!J$8*$AF$2),IF($C9="Integrate",(('Demand Base Matrix'!J$28+'Demand Base Matrix'!J$32)*$AC$2*$AD$2*$AE$2+('Demand Base Matrix'!J$29+'Demand Base Matrix'!J$30)*$W$2*$AD$2+'Demand Base Matrix'!J$31*$W$2*$AD$2*$AE$2+'Demand Base Matrix'!J$33+'Demand Base Matrix'!J$34*$AF$2),IF($C9="Bond",(('Demand Base Matrix'!J$55+'Demand Base Matrix'!J$59)*$AC$2*$AD$2*$AE$2+('Demand Base Matrix'!J$56+'Demand Base Matrix'!J$57)*$W$2*$AD$2+'Demand Base Matrix'!J$58*$W$2*$AD$2*$AE$2+'Demand Base Matrix'!J$60+'Demand Base Matrix'!J$61*$AF$2),IF($C9="Explore",('Demand Base Matrix'!J$82*$AC$2*$AD$2*$AE$2*$AF$2+'Demand Base Matrix'!J$83*$W$2*$AC$2*$AD$2*$AE$2*$AF$2+'Demand Base Matrix'!J$84))))) -> 4
A10: [2026 SaaS Y3] Big River (Tx) | B10: Big Rivers Electric Corporation | C10: Bond | D10: Grant Lee | E10: Mannat Padha | F10: Kshitiz Agrawal | I10: =IFERROR(INDEX('Customer 360'!F:F,MATCH(B10,'Customer 360'!A:A,0)),"-") -> D | J10: 0 | K10: 483 | L10: 46268 | M10: 46268 | N10: 2026 | O10: 46023 | P10: IVMS | Q10: =O10 -> 46023 | R10: =IFERROR(IF(M10<>"",M10,IF(L10<>"",L10,INDEX('CSM RDD'!B:B,MATCH(B10,'CSM RDD'!A:A,0)))),"-") -> 46268 | S10: =IFERROR(EOMONTH(Q10,-1)+1,"") -> 46023 | T10: =IFERROR(EOMONTH(R10,-1)+1,"") -> 46266 | U10: =J10+K10 -> 483 | V10: =IF(C10<>"Validate",DATE(2026,3,1),O10) -> 46082 | W10: =IF(U10=0,1,IF(U10<='Demand Base Matrix'!$K$3,'Demand Base Matrix'!$L$3,IF(U10<='Demand Base Matrix'!$K$4,'Demand Base Matrix'!$L$4,IF(U10<='Demand Base Matrix'!$K$5,'Demand Base Matrix'!$L$5,IF(U10<='Demand Base Matrix'!$K$6,'Demand Base Matrix'!$L$6,IF(U10<='Demand Base Matrix'!$K$7,'Demand Base Matrix'!$L$7)))))) -> 0.75 | X10: =DATE(YEAR(R10),MONTH(R10),1) -> 46266 | Y10: =IF(K10>0,"Tx","Dx") -> Tx | Z10: Low | AA10: Low | AB10: Low | AC10: =IFERROR(INDEX('Demand Base Matrix'!AM:AM,MATCH(Y10,'Demand Base Matrix'!AL:AL,0)),"-") -> 1.5 | AD10: =IFERROR(INDEX('Demand Base Matrix'!AO:AO,MATCH(Z10,'Demand Base Matrix'!AN:AN,0)),1) -> 1 | AE10: =IFERROR(INDEX('Demand Base Matrix'!AQ:AQ,MATCH(AA10,'Demand Base Matrix'!AP:AP,0)),1) -> 1 | AF10: =IFERROR(INDEX('Demand Base Matrix'!AS:AS,MATCH(AB10,'Demand Base Matrix'!AR:AR,0)),1) -> 1 | AG10: =IF($C10="Validate",(('Demand Base Matrix'!D$2+'Demand Base Matrix'!D$6)*$AC$2*$AD$2*$AE$2+('Demand Base Matrix'!D$3+'Demand Base Matrix'!D$4)*$W$2*$AD$2+'Demand Base Matrix'!D$5*$W$2*$AD$2*$AE$2+'Demand Base Matrix'!D$7+'Demand Base Matrix'!D$8*$AF$2),IF($C10="Integrate",(('Demand Base Matrix'!D$28+'Demand Base Matrix'!D$32)*$AC$2*$AD$2*$AE$2+('Demand Base Matrix'!D$29+'Demand Base Matrix'!D$30)*$W$2*$AD$2+'Demand Base Matrix'!D$31*$W$2*$AD$2*$AE$2+'Demand Base Matrix'!D$33+'Demand Base Matrix'!D$34*$AF$2),IF($C10="Bond",(('Demand Base Matrix'!D$55+'Demand Base Matrix'!D$59)*$AC$2*$AD$2*$AE$2+('Demand Base Matrix'!D$56+'Demand Base Matrix'!D$57)*$W$2*$AD$2+'Demand Base Matrix'!D$58*$W$2*$AD$2*$AE$2+'Demand Base Matrix'!D$60+'Demand Base Matrix'!D$61*$AF$2),IF($C10="Explore",('Demand Base Matrix'!D$82*$AC$2*$AD$2*$AE$2*$AF$2+'Demand Base Matrix'!D$83*$W$2*$AC$2*$AD$2*$AE$2*$AF$2+'Demand Base Matrix'!D$84))))) -> 10 | AH10: =IF($C10="Validate",(('Demand Base Matrix'!E$2+'Demand Base Matrix'!E$6)*$AC$2*$AD$2*$AE$2+('Demand Base Matrix'!E$3+'Demand Base Matrix'!E$4)*$W$2*$AD$2+'Demand Base Matrix'!E$5*$W$2*$AD$2*$AE$2+'Demand Base Matrix'!E$7+'Demand Base Matrix'!E$8*$AF$2),IF($C10="Integrate",(('Demand Base Matrix'!E$28+'Demand Base Matrix'!E$32)*$AC$2*$AD$2*$AE$2+('Demand Base Matrix'!E$29+'Demand Base Matrix'!E$30)*$W$2*$AD$2+'Demand Base Matrix'!E$31*$W$2*$AD$2*$AE$2+'Demand Base Matrix'!E$33+'Demand Base Matrix'!E$34*$AF$2),IF($C10="Bond",(('Demand Base Matrix'!E$55+'Demand Base Matrix'!E$59)*$AC$2*$AD$2*$AE$2+('Demand Base Matrix'!E$56+'Demand Base Matrix'!E$57)*$W$2*$AD$2+'Demand Base Matrix'!E$58*$W$2*$AD$2*$AE$2+'Demand Base Matrix'!E$60+'Demand Base Matrix'!E$61*$AF$2),IF($C10="Explore",('Demand Base Matrix'!E$82*$AC$2*$AD$2*$AE$2*$AF$2+'Demand Base Matrix'!E$83*$W$2*$AC$2*$AD$2*$AE$2*$AF$2+'Demand Base Matrix'!E$84))))) -> 10 | AI10: =IF($C10="Validate",(('Demand Base Matrix'!F$2+'Demand Base Matrix'!F$6)*$AC$2*$AD$2*$AE$2+('Demand Base Matrix'!F$3+'Demand Base Matrix'!F$4)*$W$2*$AD$2+'Demand Base Matrix'!F$5*$W$2*$AD$2*$AE$2+'Demand Base Matrix'!F$7+'Demand Base Matrix'!F$8*$AF$2),IF($C10="Integrate",(('Demand Base Matrix'!F$28+'Demand Base Matrix'!F$32)*$AC$2*$AD$2*$AE$2+('Demand Base Matrix'!F$29+'Demand Base Matrix'!F$30)*$W$2*$AD$2+'Demand Base Matrix'!F$31*$W$2*$AD$2*$AE$2+'Demand Base Matrix'!F$33+'Demand Base Matrix'!F$34*$AF$2),IF($C10="Bond",(('Demand Base Matrix'!F$55+'Demand Base Matrix'!F$59)*$AC$2*$AD$2*$AE$2+('Demand Base Matrix'!F$56+'Demand Base Matrix'!F$57)*$W$2*$AD$2+'Demand Base Matrix'!F$58*$W$2*$AD$2*$AE$2+'Demand Base Matrix'!F$60+'Demand Base Matrix'!F$61*$AF$2),IF($C10="Explore",('Demand Base Matrix'!F$82*$AC$2*$AD$2*$AE$2*$AF$2+'Demand Base Matrix'!F$83*$W$2*$AC$2*$AD$2*$AE$2*$AF$2+'Demand Base Matrix'!F$84))))) -> 10 | AJ10: =IF($C10="Validate",(('Demand Base Matrix'!G$2+'Demand Base Matrix'!G$6)*$AC$2*$AD$2*$AE$2+('Demand Base Matrix'!G$3+'Demand Base Matrix'!G$4)*$W$2*$AD$2+'Demand Base Matrix'!G$5*$W$2*$AD$2*$AE$2+'Demand Base Matrix'!G$7+'Demand Base Matrix'!G$8*$AF$2),IF($C10="Integrate",(('Demand Base Matrix'!G$28+'Demand Base Matrix'!G$32)*$AC$2*$AD$2*$AE$2+('Demand Base Matrix'!G$29+'Demand Base Matrix'!G$30)*$W$2*$AD$2+'Demand Base Matrix'!G$31*$W$2*$AD$2*$AE$2+'Demand Base Matrix'!G$33+'Demand Base Matrix'!G$34*$AF$2),IF($C10="Bond",(('Demand Base Matrix'!G$55+'Demand Base Matrix'!G$59)*$AC$2*$AD$2*$AE$2+('Demand Base Matrix'!G$56+'Demand Base Matrix'!G$57)*$W$2*$AD$2+'Demand Base Matrix'!G$58*$W$2*$AD$2*$AE$2+'Demand Base Matrix'!G$60+'Demand Base Matrix'!G$61*$AF$2),IF($C10="Explore",('Demand Base Matrix'!G$82*$AC$2*$AD$2*$AE$2*$AF$2+'Demand Base Matrix'!G$83*$W$2*$AC$2*$AD$2*$AE$2*$AF$2+'Demand Base Matrix'!G$84))))) -> 50 | AK10: =IF($C10="Validate",(('Demand Base Matrix'!H$2+'Demand Base Matrix'!H$6)*$AC$2*$AD$2*$AE$2+('Demand Base Matrix'!H$3+'Demand Base Matrix'!H$4)*$W$2*$AD$2+'Demand Base Matrix'!H$5*$W$2*$AD$2*$AE$2+'Demand Base Matrix'!H$7+'Demand Base Matrix'!H$8*$AF$2),IF($C10="Integrate",(('Demand Base Matrix'!H$28+'Demand Base Matrix'!H$32)*$AC$2*$AD$2*$AE$2+('Demand Base Matrix'!H$29+'Demand Base Matrix'!H$30)*$W$2*$AD$2+'Demand Base Matrix'!H$31*$W$2*$AD$2*$AE$2+'Demand Base Matrix'!H$33+'Demand Base Matrix'!H$34*$AF$2),IF($C10="Bond",(('Demand Base Matrix'!H$55+'Demand Base Matrix'!H$59)*$AC$2*$AD$2*$AE$2+('Demand Base Matrix'!H$56+'Demand Base Matrix'!H$57)*$W$2*$AD$2+'Demand Base Matrix'!H$58*$W$2*$AD$2*$AE$2+'Demand Base Matrix'!H$60+'Demand Base Matrix'!H$61*$AF$2),IF($C10="Explore",('Demand Base Matrix'!H$82*$AC$2*$AD$2*$AE$2*$AF$2+'Demand Base Matrix'!H$83*$W$2*$AC$2*$AD$2*$AE$2*$AF$2+'Demand Base Matrix'!H$84))))) -> 28 | AL10: =IF($C10="Validate",(('Demand Base Matrix'!I$2+'Demand Base Matrix'!I$6)*$AC$2*$AD$2*$AE$2+('Demand Base Matrix'!I$3+'Demand Base Matrix'!I$4)*$W$2*$AD$2+'Demand Base Matrix'!I$5*$W$2*$AD$2*$AE$2+'Demand Base Matrix'!I$7+'Demand Base Matrix'!I$8*$AF$2),IF($C10="Integrate",(('Demand Base Matrix'!I$28+'Demand Base Matrix'!I$32)*$AC$2*$AD$2*$AE$2+('Demand Base Matrix'!I$29+'Demand Base Matrix'!I$30)*$W$2*$AD$2+'Demand Base Matrix'!I$31*$W$2*$AD$2*$AE$2+'Demand Base Matrix'!I$33+'Demand Base Matrix'!I$34*$AF$2),IF($C10="Bond",(('Demand Base Matrix'!I$55+'Demand Base Matrix'!I$59)*$AC$2*$AD$2*$AE$2+('Demand Base Matrix'!I$56+'Demand Base Matrix'!I$57)*$W$2*$AD$2+'Demand Base Matrix'!I$58*$W$2*$AD$2*$AE$2+'Demand Base Matrix'!I$60+'Demand Base Matrix'!I$61*$AF$2),IF($C10="Explore",('Demand Base Matrix'!I$82*$AC$2*$AD$2*$AE$2*$AF$2+'Demand Base Matrix'!I$83*$W$2*$AC$2*$AD$2*$AE$2*$AF$2+'Demand Base Matrix'!I$84))))) -> 8 | AM10: =IF($C10="Validate",(('Demand Base Matrix'!J$2+'Demand Base Matrix'!J$6)*$AC$2*$AD$2*$AE$2+('Demand Base Matrix'!J$3+'Demand Base Matrix'!J$4)*$W$2*$AD$2+'Demand Base Matrix'!J$5*$W$2*$AD$2*$AE$2+'Demand Base Matrix'!J$7+'Demand Base Matrix'!J$8*$AF$2),IF($C10="Integrate",(('Demand Base Matrix'!J$28+'Demand Base Matrix'!J$32)*$AC$2*$AD$2*$AE$2+('Demand Base Matrix'!J$29+'Demand Base Matrix'!J$30)*$W$2*$AD$2+'Demand Base Matrix'!J$31*$W$2*$AD$2*$AE$2+'Demand Base Matrix'!J$33+'Demand Base Matrix'!J$34*$AF$2),IF($C10="Bond",(('Demand Base Matrix'!J$55+'Demand Base Matrix'!J$59)*$AC$2*$AD$2*$AE$2+('Demand Base Matrix'!J$56+'Demand Base Matrix'!J$57)*$W$2*$AD$2+'Demand Base Matrix'!J$58*$W$2*$AD$2*$AE$2+'Demand Base Matrix'!J$60+'Demand Base Matrix'!J$61*$AF$2),IF($C10="Explore",('Demand Base Matrix'!J$82*$AC$2*$AD$2*$AE$2*$AF$2+'Demand Base Matrix'!J$83*$W$2*$AC$2*$AD$2*$AE$2*$AF$2+'Demand Base Matrix'!J$84))))) -> 8
A11: [2026 SaaS Y5] Black River Electric Cooperative | B11: Black River Electric Cooperative | C11: Bond | D11: Savannah Peery | E11: Shravani Eleswarapu | F11: Divyansh Diwan | I11: =IFERROR(INDEX('Customer 360'!F:F,MATCH(B11,'Customer 360'!A:A,0)),"-") -> C | J11: 2400 | L11: 46265 | M11: 46265 | N11: 2026 | O11: 46023 | P11: IVMS | Q11: =O11 -> 46023 | R11: =IFERROR(IF(M11<>"",M11,IF(L11<>"",L11,INDEX('CSM RDD'!B:B,MATCH(B11,'CSM RDD'!A:A,0)))),"-") -> 46265 | S11: =IFERROR(EOMONTH(Q11,-1)+1,"") -> 46023 | T11: =IFERROR(EOMONTH(R11,-1)+1,"") -> 46235 | U11: =J11+K11 -> 2400 | V11: =IF(C11<>"Validate",DATE(2026,3,1),O11) -> 46082 | W11: =IF(U11=0,1,IF(U11<='Demand Base Matrix'!$K$3,'Demand Base Matrix'!$L$3,IF(U11<='Demand Base Matrix'!$K$4,'Demand Base Matrix'!$L$4,IF(U11<='Demand Base Matrix'!$K$5,'Demand Base Matrix'!$L$5,IF(U11<='Demand Base Matrix'!$K$6,'Demand Base Matrix'!$L$6,IF(U11<='Demand Base Matrix'!$K$7,'Demand Base Matrix'!$L$7)))))) -> 1 | X11: =DATE(YEAR(R11),MONTH(R11),1) -> 46235 | Y11: =IF(K11>0,"Tx","Dx") -> Dx | Z11: Low | AA11: Low | AB11: Low | AC11: =IFERROR(INDEX('Demand Base Matrix'!AM:AM,MATCH(Y11,'Demand Base Matrix'!AL:AL,0)),"-") -> 1 | AD11: =IFERROR(INDEX('Demand Base Matrix'!AO:AO,MATCH(Z11,'Demand Base Matrix'!AN:AN,0)),1) -> 1 | AE11: =IFERROR(INDEX('Demand Base Matrix'!AQ:AQ,MATCH(AA11,'Demand Base Matrix'!AP:AP,0)),1) -> 1 | AF11: =IFERROR(INDEX('Demand Base Matrix'!AS:AS,MATCH(AB11,'Demand Base Matrix'!AR:AR,0)),1) -> 1 | AG11: =IF($C11="Validate",(('Demand Base Matrix'!D$2+'Demand Base Matrix'!D$6)*$AC$2*$AD$2*$AE$2+('Demand Base Matrix'!D$3+'Demand Base Matrix'!D$4)*$W$2*$AD$2+'Demand Base Matrix'!D$5*$W$2*$AD$2*$AE$2+'Demand Base Matrix'!D$7+'Demand Base Matrix'!D$8*$AF$2),IF($C11="Integrate",(('Demand Base Matrix'!D$28+'Demand Base Matrix'!D$32)*$AC$2*$AD$2*$AE$2+('Demand Base Matrix'!D$29+'Demand Base Matrix'!D$30)*$W$2*$AD$2+'Demand Base Matrix'!D$31*$W$2*$AD$2*$AE$2+'Demand Base Matrix'!D$33+'Demand Base Matrix'!D$34*$AF$2),IF($C11="Bond",(('Demand Base Matrix'!D$55+'Demand Base Matrix'!D$59)*$AC$2*$AD$2*$AE$2+('Demand Base Matrix'!D$56+'Demand Base Matrix'!D$57)*$W$2*$AD$2+'Demand Base Matrix'!D$58*$W$2*$AD$2*$AE$2+'Demand Base Matrix'!D$60+'Demand Base Matrix'!D$61*$AF$2),IF($C11="Explore",('Demand Base Matrix'!D$82*$AC$2*$AD$2*$AE$2*$AF$2+'Demand Base Matrix'!D$83*$W$2*$AC$2*$AD$2*$AE$2*$AF$2+'Demand Base Matrix'!D$84))))) -> 10 | AH11: =IF($C11="Validate",(('Demand Base Matrix'!E$2+'Demand Base Matrix'!E$6)*$AC$2*$AD$2*$AE$2+('Demand Base Matrix'!E$3+'Demand Base Matrix'!E$4)*$W$2*$AD$2+'Demand Base Matrix'!E$5*$W$2*$AD$2*$AE$2+'Demand Base Matrix'!E$7+'Demand Base Matrix'!E$8*$AF$2),IF($C11="Integrate",(('Demand Base Matrix'!E$28+'Demand Base Matrix'!E$32)*$AC$2*$AD$2*$AE$2+('Demand Base Matrix'!E$29+'Demand Base Matrix'!E$30)*$W$2*$AD$2+'Demand Base Matrix'!E$31*$W$2*$AD$2*$AE$2+'Demand Base Matrix'!E$33+'Demand Base Matrix'!E$34*$AF$2),IF($C11="Bond",(('Demand Base Matrix'!E$55+'Demand Base Matrix'!E$59)*$AC$2*$AD$2*$AE$2+('Demand Base Matrix'!E$56+'Demand Base Matrix'!E$57)*$W$2*$AD$2+'Demand Base Matrix'!E$58*$W$2*$AD$2*$AE$2+'Demand Base Matrix'!E$60+'Demand Base Matrix'!E$61*$AF$2),IF($C11="Explore",('Demand Base Matrix'!E$82*$AC$2*$AD$2*$AE$2*$AF$2+'Demand Base Matrix'!E$83*$W$2*$AC$2*$AD$2*$AE$2*$AF$2+'Demand Base Matrix'!E$84))))) -> 10 | AI11: =IF($C11="Validate",(('Demand Base Matrix'!F$2+'Demand Base Matrix'!F$6)*$AC$2*$AD$2*$AE$2+('Demand Base Matrix'!F$3+'Demand Base Matrix'!F$4)*$W$2*$AD$2+'Demand Base Matrix'!F$5*$W$2*$AD$2*$AE$2+'Demand Base Matrix'!F$7+'Demand Base Matrix'!F$8*$AF$2),IF($C11="Integrate",(('Demand Base Matrix'!F$28+'Demand Base Matrix'!F$32)*$AC$2*$AD$2*$AE$2+('Demand Base Matrix'!F$29+'Demand Base Matrix'!F$30)*$W$2*$AD$2+'Demand Base Matrix'!F$31*$W$2*$AD$2*$AE$2+'Demand Base Matrix'!F$33+'Demand Base Matrix'!F$34*$AF$2),IF($C11="Bond",(('Demand Base Matrix'!F$55+'Demand Base Matrix'!F$59)*$AC$2*$AD$2*$AE$2+('Demand Base Matrix'!F$56+'Demand Base Matrix'!F$57)*$W$2*$AD$2+'Demand Base Matrix'!F$58*$W$2*$AD$2*$AE$2+'Demand Base Matrix'!F$60+'Demand Base Matrix'!F$61*$AF$2),IF($C11="Explore",('Demand Base Matrix'!F$82*$AC$2*$AD$2*$AE$2*$AF$2+'Demand Base Matrix'!F$83*$W$2*$AC$2*$AD$2*$AE$2*$AF$2+'Demand Base Matrix'!F$84))))) -> 10 | AJ11: =IF($C11="Validate",(('Demand Base Matrix'!G$2+'Demand Base Matrix'!G$6)*$AC$2*$AD$2*$AE$2+('Demand Base Matrix'!G$3+'Demand Base Matrix'!G$4)*$W$2*$AD$2+'Demand Base Matrix'!G$5*$W$2*$AD$2*$AE$2+'Demand Base Matrix'!G$7+'Demand Base Matrix'!G$8*$AF$2),IF($C11="Integrate",(('Demand Base Matrix'!G$28+'Demand Base Matrix'!G$32)*$AC$2*$AD$2*$AE$2+('Demand Base Matrix'!G$29+'Demand Base Matrix'!G$30)*$W$2*$AD$2+'Demand Base Matrix'!G$31*$W$2*$AD$2*$AE$2+'Demand Base Matrix'!G$33+'Demand Base Matrix'!G$34*$AF$2),IF($C11="Bond",(('Demand Base Matrix'!G$55+'Demand Base Matrix'!G$59)*$AC$2*$AD$2*$AE$2+('Demand Base Matrix'!G$56+'Demand Base Matrix'!G$57)*$W$2*$AD$2+'Demand Base Matrix'!G$58*$W$2*$AD$2*$AE$2+'Demand Base Matrix'!G$60+'Demand Base Matrix'!G$61*$AF$2),IF($C11="Explore",('Demand Base Matrix'!G$82*$AC$2*$AD$2*$AE$2*$AF$2+'Demand Base Matrix'!G$83*$W$2*$AC$2*$AD$2*$AE$2*$AF$2+'Demand Base Matrix'!G$84))))) -> 50 | AK11: =IF($C11="Validate",(('Demand Base Matrix'!H$2+'Demand Base Matrix'!H$6)*$AC$2*$AD$2*$AE$2+('Demand Base Matrix'!H$3+'Demand Base Matrix'!H$4)*$W$2*$AD$2+'Demand Base Matrix'!H$5*$W$2*$AD$2*$AE$2+'Demand Base Matrix'!H$7+'Demand Base Matrix'!H$8*$AF$2),IF($C11="Integrate",(('Demand Base Matrix'!H$28+'Demand Base Matrix'!H$32)*$AC$2*$AD$2*$AE$2+('Demand Base Matrix'!H$29+'Demand Base Matrix'!H$30)*$W$2*$AD$2+'Demand Base Matrix'!H$31*$W$2*$AD$2*$AE$2+'Demand Base Matrix'!H$33+'Demand Base Matrix'!H$34*$AF$2),IF($C11="Bond",(('Demand Base Matrix'!H$55+'Demand Base Matrix'!H$59)*$AC$2*$AD$2*$AE$2+('Demand Base Matrix'!H$56+'Demand Base Matrix'!H$57)*$W$2*$AD$2+'Demand Base Matrix'!H$58*$W$2*$AD$2*$AE$2+'Demand Base Matrix'!H$60+'Demand Base Matrix'!H$61*$AF$2),IF($C11="Explore",('Demand Base Matrix'!H$82*$AC$2*$AD$2*$AE$2*$AF$2+'Demand Base Matrix'!H$83*$W$2*$AC$2*$AD$2*$AE$2*$AF$2+'Demand Base Matrix'!H$84))))) -> 28 | AL11: =IF($C11="Validate",(('Demand Base Matrix'!I$2+'Demand Base Matrix'!I$6)*$AC$2*$AD$2*$AE$2+('Demand Base Matrix'!I$3+'Demand Base Matrix'!I$4)*$W$2*$AD$2+'Demand Base Matrix'!I$5*$W$2*$AD$2*$AE$2+'Demand Base Matrix'!I$7+'Demand Base Matrix'!I$8*$AF$2),IF($C11="Integrate",(('Demand Base Matrix'!I$28+'Demand Base Matrix'!I$32)*$AC$2*$AD$2*$AE$2+('Demand Base Matrix'!I$29+'Demand Base Matrix'!I$30)*$W$2*$AD$2+'Demand Base Matrix'!I$31*$W$2*$AD$2*$AE$2+'Demand Base Matrix'!I$33+'Demand Base Matrix'!I$34*$AF$2),IF($C11="Bond",(('Demand Base Matrix'!I$55+'Demand Base Matrix'!I$59)*$AC$2*$AD$2*$AE$2+('Demand Base Matrix'!I$56+'Demand Base Matrix'!I$57)*$W$2*$AD$2+'Demand Base Matrix'!I$58*$W$2*$AD$2*$AE$2+'Demand Base Matrix'!I$60+'Demand Base Matrix'!I$61*$AF$2),IF($C11="Explore",('Demand Base Matrix'!I$82*$AC$2*$AD$2*$AE$2*$AF$2+'Demand Base Matrix'!I$83*$W$2*$AC$2*$AD$2*$AE$2*$AF$2+'Demand Base Matrix'!I$84))))) -> 8 | AM11: =IF($C11="Validate",(('Demand Base Matrix'!J$2+'Demand Base Matrix'!J$6)*$AC$2*$AD$2*$AE$2+('Demand Base Matrix'!J$3+'Demand Base Matrix'!J$4)*$W$2*$AD$2+'Demand Base Matrix'!J$5*$W$2*$AD$2*$AE$2+'Demand Base Matrix'!J$7+'Demand Base Matrix'!J$8*$AF$2),IF($C11="Integrate",(('Demand Base Matrix'!J$28+'Demand Base Matrix'!J$32)*$AC$2*$AD$2*$AE$2+('Demand Base Matrix'!J$29+'Demand Base Matrix'!J$30)*$W$2*$AD$2+'Demand Base Matrix'!J$31*$W$2*$AD$2*$AE$2+'Demand Base Matrix'!J$33+'Demand Base Matrix'!J$34*$AF$2),IF($C11="Bond",(('Demand Base Matrix'!J$55+'Demand Base Matrix'!J$59)*$AC$2*$AD$2*$AE$2+('Demand Base Matrix'!J$56+'Demand Base Matrix'!J$57)*$W$2*$AD$2+'Demand Base Matrix'!J$58*$W$2*$AD$2*$AE$2+'Demand Base Matrix'!J$60+'Demand Base Matrix'!J$61*$AF$2),IF($C11="Explore",('Demand Base Matrix'!J$82*$AC$2*$AD$2*$AE$2*$AF$2+'Demand Base Matrix'!J$83*$W$2*$AC$2*$AD$2*$AE$2*$AF$2+'Demand Base Matrix'!J$84))))) -> 8
A12: [2026 SaaS Y2] BrightRidge Public Power | B12: BrightRidge Public Power | C12: Bond | D12: Stefanie Naden | E12: Mukul Gupta | F12: Aryan Kumar | I12: =IFERROR(INDEX('Customer 360'!F:F,MATCH(B12,'Customer 360'!A:A,0)),"-") -> D | J12: 1916 | L12: 46275 | M12: 46275 | N12: 2026 | O12: 46023 | P12: IVMS | Q12: =O12 -> 46023 | R12: =IFERROR(IF(M12<>"",M12,IF(L12<>"",L12,INDEX('CSM RDD'!B:B,MATCH(B12,'CSM RDD'!A:A,0)))),"-") -> 46275 | S12: =IFERROR(EOMONTH(Q12,-1)+1,"") -> 46023 | T12: =IFERROR(EOMONTH(R12,-1)+1,"") -> 46266 | U12: =J12+K12 -> 1916 | V12: =IF(C12<>"Validate",DATE(2026,3,1),O12) -> 46082 | W12: =IF(U12=0,1,IF(U12<='Demand Base Matrix'!$K$3,'Demand Base Matrix'!$L$3,IF(U12<='Demand Base Matrix'!$K$4,'Demand Base Matrix'!$L$4,IF(U12<='Demand Base Matrix'!$K$5,'Demand Base Matrix'!$L$5,IF(U12<='Demand Base Matrix'!$K$6,'Demand Base Matrix'!$L$6,IF(U12<='Demand Base Matrix'!$K$7,'Demand Base Matrix'!$L$7)))))) -> 1 | X12: =DATE(YEAR(R12),MONTH(R12),1) -> 46266 | Y12: =IF(K12>0,"Tx","Dx") -> Dx | Z12: Low | AA12: Medium | AB12: Low | AC12: =IFERROR(INDEX('Demand Base Matrix'!AM:AM,MATCH(Y12,'Demand Base Matrix'!AL:AL,0)),"-") -> 1 | AD12: =IFERROR(INDEX('Demand Base Matrix'!AO:AO,MATCH(Z12,'Demand Base Matrix'!AN:AN,0)),1) -> 1 | AE12: =IFERROR(INDEX('Demand Base Matrix'!AQ:AQ,MATCH(AA12,'Demand Base Matrix'!AP:AP,0)),1) -> 1.5 | AF12: =IFERROR(INDEX('Demand Base Matrix'!AS:AS,MATCH(AB12,'Demand Base Matrix'!AR:AR,0)),1) -> 1 | AG12: =IF($C12="Validate",(('Demand Base Matrix'!D$2+'Demand Base Matrix'!D$6)*$AC$2*$AD$2*$AE$2+('Demand Base Matrix'!D$3+'Demand Base Matrix'!D$4)*$W$2*$AD$2+'Demand Base Matrix'!D$5*$W$2*$AD$2*$AE$2+'Demand Base Matrix'!D$7+'Demand Base Matrix'!D$8*$AF$2),IF($C12="Integrate",(('Demand Base Matrix'!D$28+'Demand Base Matrix'!D$32)*$AC$2*$AD$2*$AE$2+('Demand Base Matrix'!D$29+'Demand Base Matrix'!D$30)*$W$2*$AD$2+'Demand Base Matrix'!D$31*$W$2*$AD$2*$AE$2+'Demand Base Matrix'!D$33+'Demand Base Matrix'!D$34*$AF$2),IF($C12="Bond",(('Demand Base Matrix'!D$55+'Demand Base Matrix'!D$59)*$AC$2*$AD$2*$AE$2+('Demand Base Matrix'!D$56+'Demand Base Matrix'!D$57)*$W$2*$AD$2+'Demand Base Matrix'!D$58*$W$2*$AD$2*$AE$2+'Demand Base Matrix'!D$60+'Demand Base Matrix'!D$61*$AF$2),IF($C12="Explore",('Demand Base Matrix'!D$82*$AC$2*$AD$2*$AE$2*$AF$2+'Demand Base Matrix'!D$83*$W$2*$AC$2*$AD$2*$AE$2*$AF$2+'Demand Base Matrix'!D$84))))) -> 10 | AH12: =IF($C12="Validate",(('Demand Base Matrix'!E$2+'Demand Base Matrix'!E$6)*$AC$2*$AD$2*$AE$2+('Demand Base Matrix'!E$3+'Demand Base Matrix'!E$4)*$W$2*$AD$2+'Demand Base Matrix'!E$5*$W$2*$AD$2*$AE$2+'Demand Base Matrix'!E$7+'Demand Base Matrix'!E$8*$AF$2),IF($C12="Integrate",(('Demand Base Matrix'!E$28+'Demand Base Matrix'!E$32)*$AC$2*$AD$2*$AE$2+('Demand Base Matrix'!E$29+'Demand Base Matrix'!E$30)*$W$2*$AD$2+'Demand Base Matrix'!E$31*$W$2*$AD$2*$AE$2+'Demand Base Matrix'!E$33+'Demand Base Matrix'!E$34*$AF$2),IF($C12="Bond",(('Demand Base Matrix'!E$55+'Demand Base Matrix'!E$59)*$AC$2*$AD$2*$AE$2+('Demand Base Matrix'!E$56+'Demand Base Matrix'!E$57)*$W$2*$AD$2+'Demand Base Matrix'!E$58*$W$2*$AD$2*$AE$2+'Demand Base Matrix'!E$60+'Demand Base Matrix'!E$61*$AF$2),IF($C12="Explore",('Demand Base Matrix'!E$82*$AC$2*$AD$2*$AE$2*$AF$2+'Demand Base Matrix'!E$83*$W$2*$AC$2*$AD$2*$AE$2*$AF$2+'Demand Base Matrix'!E$84))))) -> 10 | AI12: =IF($C12="Validate",(('Demand Base Matrix'!F$2+'Demand Base Matrix'!F$6)*$AC$2*$AD$2*$AE$2+('Demand Base Matrix'!F$3+'Demand Base Matrix'!F$4)*$W$2*$AD$2+'Demand Base Matrix'!F$5*$W$2*$AD$2*$AE$2+'Demand Base Matrix'!F$7+'Demand Base Matrix'!F$8*$AF$2),IF($C12="Integrate",(('Demand Base Matrix'!F$28+'Demand Base Matrix'!F$32)*$AC$2*$AD$2*$AE$2+('Demand Base Matrix'!F$29+'Demand Base Matrix'!F$30)*$W$2*$AD$2+'Demand Base Matrix'!F$31*$W$2*$AD$2*$AE$2+'Demand Base Matrix'!F$33+'Demand Base Matrix'!F$34*$AF$2),IF($C12="Bond",(('Demand Base Matrix'!F$55+'Demand Base Matrix'!F$59)*$AC$2*$AD$2*$AE$2+('Demand Base Matrix'!F$56+'Demand Base Matrix'!F$57)*$W$2*$AD$2+'Demand Base Matrix'!F$58*$W$2*$AD$2*$AE$2+'Demand Base Matrix'!F$60+'Demand Base Matrix'!F$61*$AF$2),IF($C12="Explore",('Demand Base Matrix'!F$82*$AC$2*$AD$2*$AE$2*$AF$2+'Demand Base Matrix'!F$83*$W$2*$AC$2*$AD$2*$AE$2*$AF$2+'Demand Base Matrix'!F$84))))) -> 10 | AJ12: =IF($C12="Validate",(('Demand Base Matrix'!G$2+'Demand Base Matrix'!G$6)*$AC$2*$AD$2*$AE$2+('Demand Base Matrix'!G$3+'Demand Base Matrix'!G$4)*$W$2*$AD$2+'Demand Base Matrix'!G$5*$W$2*$AD$2*$AE$2+'Demand Base Matrix'!G$7+'Demand Base Matrix'!G$8*$AF$2),IF($C12="Integrate",(('Demand Base Matrix'!G$28+'Demand Base Matrix'!G$32)*$AC$2*$AD$2*$AE$2+('Demand Base Matrix'!G$29+'Demand Base Matrix'!G$30)*$W$2*$AD$2+'Demand Base Matrix'!G$31*$W$2*$AD$2*$AE$2+'Demand Base Matrix'!G$33+'Demand Base Matrix'!G$34*$AF$2),IF($C12="Bond",(('Demand Base Matrix'!G$55+'Demand Base Matrix'!G$59)*$AC$2*$AD$2*$AE$2+('Demand Base Matrix'!G$56+'Demand Base Matrix'!G$57)*$W$2*$AD$2+'Demand Base Matrix'!G$58*$W$2*$AD$2*$AE$2+'Demand Base Matrix'!G$60+'Demand Base Matrix'!G$61*$AF$2),IF($C12="Explore",('Demand Base Matrix'!G$82*$AC$2*$AD$2*$AE$2*$AF$2+'Demand Base Matrix'!G$83*$W$2*$AC$2*$AD$2*$AE$2*$AF$2+'Demand Base Matrix'!G$84))))) -> 50 | AK12: =IF($C12="Validate",(('Demand Base Matrix'!H$2+'Demand Base Matrix'!H$6)*$AC$2*$AD$2*$AE$2+('Demand Base Matrix'!H$3+'Demand Base Matrix'!H$4)*$W$2*$AD$2+'Demand Base Matrix'!H$5*$W$2*$AD$2*$AE$2+'Demand Base Matrix'!H$7+'Demand Base Matrix'!H$8*$AF$2),IF($C12="Integrate",(('Demand Base Matrix'!H$28+'Demand Base Matrix'!H$32)*$AC$2*$AD$2*$AE$2+('Demand Base Matrix'!H$29+'Demand Base Matrix'!H$30)*$W$2*$AD$2+'Demand Base Matrix'!H$31*$W$2*$AD$2*$AE$2+'Demand Base Matrix'!H$33+'Demand Base Matrix'!H$34*$AF$2),IF($C12="Bond",(('Demand Base Matrix'!H$55+'Demand Base Matrix'!H$59)*$AC$2*$AD$2*$AE$2+('Demand Base Matrix'!H$56+'Demand Base Matrix'!H$57)*$W$2*$AD$2+'Demand Base Matrix'!H$58*$W$2*$AD$2*$AE$2+'Demand Base Matrix'!H$60+'Demand Base Matrix'!H$61*$AF$2),IF($C12="Explore",('Demand Base Matrix'!H$82*$AC$2*$AD$2*$AE$2*$AF$2+'Demand Base Matrix'!H$83*$W$2*$AC$2*$AD$2*$AE$2*$AF$2+'Demand Base Matrix'!H$84))))) -> 28 | AL12: =IF($C12="Validate",(('Demand Base Matrix'!I$2+'Demand Base Matrix'!I$6)*$AC$2*$AD$2*$AE$2+('Demand Base Matrix'!I$3+'Demand Base Matrix'!I$4)*$W$2*$AD$2+'Demand Base Matrix'!I$5*$W$2*$AD$2*$AE$2+'Demand Base Matrix'!I$7+'Demand Base Matrix'!I$8*$AF$2),IF($C12="Integrate",(('Demand Base Matrix'!I$28+'Demand Base Matrix'!I$32)*$AC$2*$AD$2*$AE$2+('Demand Base Matrix'!I$29+'Demand Base Matrix'!I$30)*$W$2*$AD$2+'Demand Base Matrix'!I$31*$W$2*$AD$2*$AE$2+'Demand Base Matrix'!I$33+'Demand Base Matrix'!I$34*$AF$2),IF($C12="Bond",(('Demand Base Matrix'!I$55+'Demand Base Matrix'!I$59)*$AC$2*$AD$2*$AE$2+('Demand Base Matrix'!I$56+'Demand Base Matrix'!I$57)*$W$2*$AD$2+'Demand Base Matrix'!I$58*$W$2*$AD$2*$AE$2+'Demand Base Matrix'!I$60+'Demand Base Matrix'!I$61*$AF$2),IF($C12="Explore",('Demand Base Matrix'!I$82*$AC$2*$AD$2*$AE$2*$AF$2+'Demand Base Matrix'!I$83*$W$2*$AC$2*$AD$2*$AE$2*$AF$2+'Demand Base Matrix'!I$84))))) -> 8 | AM12: =IF($C12="Validate",(('Demand Base Matrix'!J$2+'Demand Base Matrix'!J$6)*$AC$2*$AD$2*$AE$2+('Demand Base Matrix'!J$3+'Demand Base Matrix'!J$4)*$W$2*$AD$2+'Demand Base Matrix'!J$5*$W$2*$AD$2*$AE$2+'Demand Base Matrix'!J$7+'Demand Base Matrix'!J$8*$AF$2),IF($C12="Integrate",(('Demand Base Matrix'!J$28+'Demand Base Matrix'!J$32)*$AC$2*$AD$2*$AE$2+('Demand Base Matrix'!J$29+'Demand Base Matrix'!J$30)*$W$2*$AD$2+'Demand Base Matrix'!J$31*$W$2*$AD$2*$AE$2+'Demand Base Matrix'!J$33+'Demand Base Matrix'!J$34*$AF$2),IF($C12="Bond",(('Demand Base Matrix'!J$55+'Demand Base Matrix'!J$59)*$AC$2*$AD$2*$AE$2+('Demand Base Matrix'!J$56+'Demand Base Matrix'!J$57)*$W$2*$AD$2+'Demand Base Matrix'!J$58*$W$2*$AD$2*$AE$2+'Demand Base Matrix'!J$60+'Demand Base Matrix'!J$61*$AF$2),IF($C12="Explore",('Demand Base Matrix'!J$82*$AC$2*$AD$2*$AE$2*$AF$2+'Demand Base Matrix'!J$83*$W$2*$AC$2*$AD$2*$AE$2*$AF$2+'Demand Base Matrix'!J$84))))) -> 8
A13: [2026 SaaS Y2] Central Virginia Electric | B13: Central Virginia Electric Cooperative | C13: Bond | D13: Jacob Calzavara | E13: Shravani Eleswarapu | F13: Sarthak Goyal | I13: =IFERROR(INDEX('Customer 360'!F:F,MATCH(B13,'Customer 360'!A:A,0)),"-") -> C | J13: 3003 | L13: 46233 | M13: 46233 | N13: 2026 | O13: 46023 | P13: IVMS | Q13: =O13 -> 46023 | R13: =IFERROR(IF(M13<>"",M13,IF(L13<>"",L13,INDEX('CSM RDD'!B:B,MATCH(B13,'CSM RDD'!A:A,0)))),"-") -> 46233 | S13: =IFERROR(EOMONTH(Q13,-1)+1,"") -> 46023 | T13: =IFERROR(EOMONTH(R13,-1)+1,"") -> 46204 | U13: =J13+K13 -> 3003 | V13: =IF(C13<>"Validate",DATE(2026,3,1),O13) -> 46082 | W13: =IF(U13=0,1,IF(U13<='Demand Base Matrix'!$K$3,'Demand Base Matrix'!$L$3,IF(U13<='Demand Base Matrix'!$K$4,'Demand Base Matrix'!$L$4,IF(U13<='Demand Base Matrix'!$K$5,'Demand Base Matrix'!$L$5,IF(U13<='Demand Base Matrix'!$K$6,'Demand Base Matrix'!$L$6,IF(U13<='Demand Base Matrix'!$K$7,'Demand Base Matrix'!$L$7)))))) -> 1 | X13: =DATE(YEAR(R13),MONTH(R13),1) -> 46204 | Y13: =IF(K13>0,"Tx","Dx") -> Dx | Z13: Low | AA13: Low | AB13: Low | AC13: =IFERROR(INDEX('Demand Base Matrix'!AM:AM,MATCH(Y13,'Demand Base Matrix'!AL:AL,0)),"-") -> 1 | AD13: =IFERROR(INDEX('Demand Base Matrix'!AO:AO,MATCH(Z13,'Demand Base Matrix'!AN:AN,0)),1) -> 1 | AE13: =IFERROR(INDEX('Demand Base Matrix'!AQ:AQ,MATCH(AA13,'Demand Base Matrix'!AP:AP,0)),1) -> 1 | AF13: =IFERROR(INDEX('Demand Base Matrix'!AS:AS,MATCH(AB13,'Demand Base Matrix'!AR:AR,0)),1) -> 1 | AG13: =IF($C13="Validate",(('Demand Base Matrix'!D$2+'Demand Base Matrix'!D$6)*$AC$2*$AD$2*$AE$2+('Demand Base Matrix'!D$3+'Demand Base Matrix'!D$4)*$W$2*$AD$2+'Demand Base Matrix'!D$5*$W$2*$AD$2*$AE$2+'Demand Base Matrix'!D$7+'Demand Base Matrix'!D$8*$AF$2),IF($C13="Integrate",(('Demand Base Matrix'!D$28+'Demand Base Matrix'!D$32)*$AC$2*$AD$2*$AE$2+('Demand Base Matrix'!D$29+'Demand Base Matrix'!D$30)*$W$2*$AD$2+'Demand Base Matrix'!D$31*$W$2*$AD$2*$AE$2+'Demand Base Matrix'!D$33+'Demand Base Matrix'!D$34*$AF$2),IF($C13="Bond",(('Demand Base Matrix'!D$55+'Demand Base Matrix'!D$59)*$AC$2*$AD$2*$AE$2+('Demand Base Matrix'!D$56+'Demand Base Matrix'!D$57)*$W$2*$AD$2+'Demand Base Matrix'!D$58*$W$2*$AD$2*$AE$2+'Demand Base Matrix'!D$60+'Demand Base Matrix'!D$61*$AF$2),IF($C13="Explore",('Demand Base Matrix'!D$82*$AC$2*$AD$2*$AE$2*$AF$2+'Demand Base Matrix'!D$83*$W$2*$AC$2*$AD$2*$AE$2*$AF$2+'Demand Base Matrix'!D$84))))) -> 10 | AH13: =IF($C13="Validate",(('Demand Base Matrix'!E$2+'Demand Base Matrix'!E$6)*$AC$2*$AD$2*$AE$2+('Demand Base Matrix'!E$3+'Demand Base Matrix'!E$4)*$W$2*$AD$2+'Demand Base Matrix'!E$5*$W$2*$AD$2*$AE$2+'Demand Base Matrix'!E$7+'Demand Base Matrix'!E$8*$AF$2),IF($C13="Integrate",(('Demand Base Matrix'!E$28+'Demand Base Matrix'!E$32)*$AC$2*$AD$2*$AE$2+('Demand Base Matrix'!E$29+'Demand Base Matrix'!E$30)*$W$2*$AD$2+'Demand Base Matrix'!E$31*$W$2*$AD$2*$AE$2+'Demand Base Matrix'!E$33+'Demand Base Matrix'!E$34*$AF$2),IF($C13="Bond",(('Demand Base Matrix'!E$55+'Demand Base Matrix'!E$59)*$AC$2*$AD$2*$AE$2+('Demand Base Matrix'!E$56+'Demand Base Matrix'!E$57)*$W$2*$AD$2+'Demand Base Matrix'!E$58*$W$2*$AD$2*$AE$2+'Demand Base Matrix'!E$60+'Demand Base Matrix'!E$61*$AF$2),IF($C13="Explore",('Demand Base Matrix'!E$82*$AC$2*$AD$2*$AE$2*$AF$2+'Demand Base Matrix'!E$83*$W$2*$AC$2*$AD$2*$AE$2*$AF$2+'Demand Base Matrix'!E$84))))) -> 10 | AI13: =IF($C13="Validate",(('Demand Base Matrix'!F$2+'Demand Base Matrix'!F$6)*$AC$2*$AD$2*$AE$2+('Demand Base Matrix'!F$3+'Demand Base Matrix'!F$4)*$W$2*$AD$2+'Demand Base Matrix'!F$5*$W$2*$AD$2*$AE$2+'Demand Base Matrix'!F$7+'Demand Base Matrix'!F$8*$AF$2),IF($C13="Integrate",(('Demand Base Matrix'!F$28+'Demand Base Matrix'!F$32)*$AC$2*$AD$2*$AE$2+('Demand Base Matrix'!F$29+'Demand Base Matrix'!F$30)*$W$2*$AD$2+'Demand Base Matrix'!F$31*$W$2*$AD$2*$AE$2+'Demand Base Matrix'!F$33+'Demand Base Matrix'!F$34*$AF$2),IF($C13="Bond",(('Demand Base Matrix'!F$55+'Demand Base Matrix'!F$59)*$AC$2*$AD$2*$AE$2+('Demand Base Matrix'!F$56+'Demand Base Matrix'!F$57)*$W$2*$AD$2+'Demand Base Matrix'!F$58*$W$2*$AD$2*$AE$2+'Demand Base Matrix'!F$60+'Demand Base Matrix'!F$61*$AF$2),IF($C13="Explore",('Demand Base Matrix'!F$82*$AC$2*$AD$2*$AE$2*$AF$2+'Demand Base Matrix'!F$83*$W$2*$AC$2*$AD$2*$AE$2*$AF$2+'Demand Base Matrix'!F$84))))) -> 10 | AJ13: =IF($C13="Validate",(('Demand Base Matrix'!G$2+'Demand Base Matrix'!G$6)*$AC$2*$AD$2*$AE$2+('Demand Base Matrix'!G$3+'Demand Base Matrix'!G$4)*$W$2*$AD$2+'Demand Base Matrix'!G$5*$W$2*$AD$2*$AE$2+'Demand Base Matrix'!G$7+'Demand Base Matrix'!G$8*$AF$2),IF($C13="Integrate",(('Demand Base Matrix'!G$28+'Demand Base Matrix'!G$32)*$AC$2*$AD$2*$AE$2+('Demand Base Matrix'!G$29+'Demand Base Matrix'!G$30)*$W$2*$AD$2+'Demand Base Matrix'!G$31*$W$2*$AD$2*$AE$2+'Demand Base Matrix'!G$33+'Demand Base Matrix'!G$34*$AF$2),IF($C13="Bond",(('Demand Base Matrix'!G$55+'Demand Base Matrix'!G$59)*$AC$2*$AD$2*$AE$2+('Demand Base Matrix'!G$56+'Demand Base Matrix'!G$57)*$W$2*$AD$2+'Demand Base Matrix'!G$58*$W$2*$AD$2*$AE$2+'Demand Base Matrix'!G$60+'Demand Base Matrix'!G$61*$AF$2),IF($C13="Explore",('Demand Base Matrix'!G$82*$AC$2*$AD$2*$AE$2*$AF$2+'Demand Base Matrix'!G$83*$W$2*$AC$2*$AD$2*$AE$2*$AF$2+'Demand Base Matrix'!G$84))))) -> 50 | AK13: =IF($C13="Validate",(('Demand Base Matrix'!H$2+'Demand Base Matrix'!H$6)*$AC$2*$AD$2*$AE$2+('Demand Base Matrix'!H$3+'Demand Base Matrix'!H$4)*$W$2*$AD$2+'Demand Base Matrix'!H$5*$W$2*$AD$2*$AE$2+'Demand Base Matrix'!H$7+'Demand Base Matrix'!H$8*$AF$2),IF($C13="Integrate",(('Demand Base Matrix'!H$28+'Demand Base Matrix'!H$32)*$AC$2*$AD$2*$AE$2+('Demand Base Matrix'!H$29+'Demand Base Matrix'!H$30)*$W$2*$AD$2+'Demand Base Matrix'!H$31*$W$2*$AD$2*$AE$2+'Demand Base Matrix'!H$33+'Demand Base Matrix'!H$34*$AF$2),IF($C13="Bond",(('Demand Base Matrix'!H$55+'Demand Base Matrix'!H$59)*$AC$2*$AD$2*$AE$2+('Demand Base Matrix'!H$56+'Demand Base Matrix'!H$57)*$W$2*$AD$2+'Demand Base Matrix'!H$58*$W$2*$AD$2*$AE$2+'Demand Base Matrix'!H$60+'Demand Base Matrix'!H$61*$AF$2),IF($C13="Explore",('Demand Base Matrix'!H$82*$AC$2*$AD$2*$AE$2*$AF$2+'Demand Base Matrix'!H$83*$W$2*$AC$2*$AD$2*$AE$2*$AF$2+'Demand Base Matrix'!H$84))))) -> 28 | AL13: =IF($C13="Validate",(('Demand Base Matrix'!I$2+'Demand Base Matrix'!I$6)*$AC$2*$AD$2*$AE$2+('Demand Base Matrix'!I$3+'Demand Base Matrix'!I$4)*$W$2*$AD$2+'Demand Base Matrix'!I$5*$W$2*$AD$2*$AE$2+'Demand Base Matrix'!I$7+'Demand Base Matrix'!I$8*$AF$2),IF($C13="Integrate",(('Demand Base Matrix'!I$28+'Demand Base Matrix'!I$32)*$AC$2*$AD$2*$AE$2+('Demand Base Matrix'!I$29+'Demand Base Matrix'!I$30)*$W$2*$AD$2+'Demand Base Matrix'!I$31*$W$2*$AD$2*$AE$2+'Demand Base Matrix'!I$33+'Demand Base Matrix'!I$34*$AF$2),IF($C13="Bond",(('Demand Base Matrix'!I$55+'Demand Base Matrix'!I$59)*$AC$2*$AD$2*$AE$2+('Demand Base Matrix'!I$56+'Demand Base Matrix'!I$57)*$W$2*$AD$2+'Demand Base Matrix'!I$58*$W$2*$AD$2*$AE$2+'Demand Base Matrix'!I$60+'Demand Base Matrix'!I$61*$AF$2),IF($C13="Explore",('Demand Base Matrix'!I$82*$AC$2*$AD$2*$AE$2*$AF$2+'Demand Base Matrix'!I$83*$W$2*$AC$2*$AD$2*$AE$2*$AF$2+'Demand Base Matrix'!I$84))))) -> 8 | AM13: =IF($C13="Validate",(('Demand Base Matrix'!J$2+'Demand Base Matrix'!J$6)*$AC$2*$AD$2*$AE$2+('Demand Base Matrix'!J$3+'Demand Base Matrix'!J$4)*$W$2*$AD$2+'Demand Base Matrix'!J$5*$W$2*$AD$2*$AE$2+'Demand Base Matrix'!J$7+'Demand Base Matrix'!J$8*$AF$2),IF($C13="Integrate",(('Demand Base Matrix'!J$28+'Demand Base Matrix'!J$32)*$AC$2*$AD$2*$AE$2+('Demand Base Matrix'!J$29+'Demand Base Matrix'!J$30)*$W$2*$AD$2+'Demand Base Matrix'!J$31*$W$2*$AD$2*$AE$2+'Demand Base Matrix'!J$33+'Demand Base Matrix'!J$34*$AF$2),IF($C13="Bond",(('Demand Base Matrix'!J$55+'Demand Base Matrix'!J$59)*$AC$2*$AD$2*$AE$2+('Demand Base Matrix'!J$56+'Demand Base Matrix'!J$57)*$W$2*$AD$2+'Demand Base Matrix'!J$58*$W$2*$AD$2*$AE$2+'Demand Base Matrix'!J$60+'Demand Base Matrix'!J$61*$AF$2),IF($C13="Explore",('Demand Base Matrix'!J$82*$AC$2*$AD$2*$AE$2*$AF$2+'Demand Base Matrix'!J$83*$W$2*$AC$2*$AD$2*$AE$2*$AF$2+'Demand Base Matrix'!J$84))))) -> 8
A14: [2026 SaaS Y2] City of Denton | B14: City of Denton | C14: Validate | D14: Emily Turner | E14: Kuljeet Keshav | F14: Aryan Kumar | I14: =IFERROR(INDEX('Customer 360'!F:F,MATCH(B14,'Customer 360'!A:A,0)),"-") -> C | J14: 369 | K14: 47 | L14: 46280 | M14: 46280 | N14: 2026 | O14: 45901 | P14: IVMS | Q14: =O14 -> 45901 | R14: =IFERROR(IF(M14<>"",M14,IF(L14<>"",L14,INDEX('CSM RDD'!B:B,MATCH(B14,'CSM RDD'!A:A,0)))),"-") -> 46280 | S14: =IFERROR(EOMONTH(Q14,-1)+1,"") -> 45901 | T14: =IFERROR(EOMONTH(R14,-1)+1,"") -> 46266 | U14: =J14+K14 -> 416 | V14: =IF(C14<>"Validate",DATE(2026,3,1),O14) -> 45901 | W14: =IF(U14=0,1,IF(U14<='Demand Base Matrix'!$K$3,'Demand Base Matrix'!$L$3,IF(U14<='Demand Base Matrix'!$K$4,'Demand Base Matrix'!$L$4,IF(U14<='Demand Base Matrix'!$K$5,'Demand Base Matrix'!$L$5,IF(U14<='Demand Base Matrix'!$K$6,'Demand Base Matrix'!$L$6,IF(U14<='Demand Base Matrix'!$K$7,'Demand Base Matrix'!$L$7)))))) -> 0.75 | X14: =DATE(YEAR(R14),MONTH(R14),1) -> 46266 | Y14: =IF(K14>0,"Tx","Dx") -> Tx | Z14: Low | AA14: Medium | AB14: Low | AC14: =IFERROR(INDEX('Demand Base Matrix'!AM:AM,MATCH(Y14,'Demand Base Matrix'!AL:AL,0)),"-") -> 1.5 | AD14: =IFERROR(INDEX('Demand Base Matrix'!AO:AO,MATCH(Z14,'Demand Base Matrix'!AN:AN,0)),1) -> 1 | AE14: =IFERROR(INDEX('Demand Base Matrix'!AQ:AQ,MATCH(AA14,'Demand Base Matrix'!AP:AP,0)),1) -> 1.5 | AF14: =IFERROR(INDEX('Demand Base Matrix'!AS:AS,MATCH(AB14,'Demand Base Matrix'!AR:AR,0)),1) -> 1 | AG14: =IF($C14="Validate",(('Demand Base Matrix'!D$2+'Demand Base Matrix'!D$6)*$AC$2*$AD$2*$AE$2+('Demand Base Matrix'!D$3+'Demand Base Matrix'!D$4)*$W$2*$AD$2+'Demand Base Matrix'!D$5*$W$2*$AD$2*$AE$2+'Demand Base Matrix'!D$7+'Demand Base Matrix'!D$8*$AF$2),IF($C14="Integrate",(('Demand Base Matrix'!D$28+'Demand Base Matrix'!D$32)*$AC$2*$AD$2*$AE$2+('Demand Base Matrix'!D$29+'Demand Base Matrix'!D$30)*$W$2*$AD$2+'Demand Base Matrix'!D$31*$W$2*$AD$2*$AE$2+'Demand Base Matrix'!D$33+'Demand Base Matrix'!D$34*$AF$2),IF($C14="Bond",(('Demand Base Matrix'!D$55+'Demand Base Matrix'!D$59)*$AC$2*$AD$2*$AE$2+('Demand Base Matrix'!D$56+'Demand Base Matrix'!D$57)*$W$2*$AD$2+'Demand Base Matrix'!D$58*$W$2*$AD$2*$AE$2+'Demand Base Matrix'!D$60+'Demand Base Matrix'!D$61*$AF$2),IF($C14="Explore",('Demand Base Matrix'!D$82*$AC$2*$AD$2*$AE$2*$AF$2+'Demand Base Matrix'!D$83*$W$2*$AC$2*$AD$2*$AE$2*$AF$2+'Demand Base Matrix'!D$84))))) -> 15 | AH14: =IF($C14="Validate",(('Demand Base Matrix'!E$2+'Demand Base Matrix'!E$6)*$AC$2*$AD$2*$AE$2+('Demand Base Matrix'!E$3+'Demand Base Matrix'!E$4)*$W$2*$AD$2+'Demand Base Matrix'!E$5*$W$2*$AD$2*$AE$2+'Demand Base Matrix'!E$7+'Demand Base Matrix'!E$8*$AF$2),IF($C14="Integrate",(('Demand Base Matrix'!E$28+'Demand Base Matrix'!E$32)*$AC$2*$AD$2*$AE$2+('Demand Base Matrix'!E$29+'Demand Base Matrix'!E$30)*$W$2*$AD$2+'Demand Base Matrix'!E$31*$W$2*$AD$2*$AE$2+'Demand Base Matrix'!E$33+'Demand Base Matrix'!E$34*$AF$2),IF($C14="Bond",(('Demand Base Matrix'!E$55+'Demand Base Matrix'!E$59)*$AC$2*$AD$2*$AE$2+('Demand Base Matrix'!E$56+'Demand Base Matrix'!E$57)*$W$2*$AD$2+'Demand Base Matrix'!E$58*$W$2*$AD$2*$AE$2+'Demand Base Matrix'!E$60+'Demand Base Matrix'!E$61*$AF$2),IF($C14="Explore",('Demand Base Matrix'!E$82*$AC$2*$AD$2*$AE$2*$AF$2+'Demand Base Matrix'!E$83*$W$2*$AC$2*$AD$2*$AE$2*$AF$2+'Demand Base Matrix'!E$84))))) -> 15 | AI14: =IF($C14="Validate",(('Demand Base Matrix'!F$2+'Demand Base Matrix'!F$6)*$AC$2*$AD$2*$AE$2+('Demand Base Matrix'!F$3+'Demand Base Matrix'!F$4)*$W$2*$AD$2+'Demand Base Matrix'!F$5*$W$2*$AD$2*$AE$2+'Demand Base Matrix'!F$7+'Demand Base Matrix'!F$8*$AF$2),IF($C14="Integrate",(('Demand Base Matrix'!F$28+'Demand Base Matrix'!F$32)*$AC$2*$AD$2*$AE$2+('Demand Base Matrix'!F$29+'Demand Base Matrix'!F$30)*$W$2*$AD$2+'Demand Base Matrix'!F$31*$W$2*$AD$2*$AE$2+'Demand Base Matrix'!F$33+'Demand Base Matrix'!F$34*$AF$2),IF($C14="Bond",(('Demand Base Matrix'!F$55+'Demand Base Matrix'!F$59)*$AC$2*$AD$2*$AE$2+('Demand Base Matrix'!F$56+'Demand Base Matrix'!F$57)*$W$2*$AD$2+'Demand Base Matrix'!F$58*$W$2*$AD$2*$AE$2+'Demand Base Matrix'!F$60+'Demand Base Matrix'!F$61*$AF$2),IF($C14="Explore",('Demand Base Matrix'!F$82*$AC$2*$AD$2*$AE$2*$AF$2+'Demand Base Matrix'!F$83*$W$2*$AC$2*$AD$2*$AE$2*$AF$2+'Demand Base Matrix'!F$84))))) -> 7 | AJ14: =IF($C14="Validate",(('Demand Base Matrix'!G$2+'Demand Base Matrix'!G$6)*$AC$2*$AD$2*$AE$2+('Demand Base Matrix'!G$3+'Demand Base Matrix'!G$4)*$W$2*$AD$2+'Demand Base Matrix'!G$5*$W$2*$AD$2*$AE$2+'Demand Base Matrix'!G$7+'Demand Base Matrix'!G$8*$AF$2),IF($C14="Integrate",(('Demand Base Matrix'!G$28+'Demand Base Matrix'!G$32)*$AC$2*$AD$2*$AE$2+('Demand Base Matrix'!G$29+'Demand Base Matrix'!G$30)*$W$2*$AD$2+'Demand Base Matrix'!G$31*$W$2*$AD$2*$AE$2+'Demand Base Matrix'!G$33+'Demand Base Matrix'!G$34*$AF$2),IF($C14="Bond",(('Demand Base Matrix'!G$55+'Demand Base Matrix'!G$59)*$AC$2*$AD$2*$AE$2+('Demand Base Matrix'!G$56+'Demand Base Matrix'!G$57)*$W$2*$AD$2+'Demand Base Matrix'!G$58*$W$2*$AD$2*$AE$2+'Demand Base Matrix'!G$60+'Demand Base Matrix'!G$61*$AF$2),IF($C14="Explore",('Demand Base Matrix'!G$82*$AC$2*$AD$2*$AE$2*$AF$2+'Demand Base Matrix'!G$83*$W$2*$AC$2*$AD$2*$AE$2*$AF$2+'Demand Base Matrix'!G$84))))) -> 40 | AK14: =IF($C14="Validate",(('Demand Base Matrix'!H$2+'Demand Base Matrix'!H$6)*$AC$2*$AD$2*$AE$2+('Demand Base Matrix'!H$3+'Demand Base Matrix'!H$4)*$W$2*$AD$2+'Demand Base Matrix'!H$5*$W$2*$AD$2*$AE$2+'Demand Base Matrix'!H$7+'Demand Base Matrix'!H$8*$AF$2),IF($C14="Integrate",(('Demand Base Matrix'!H$28+'Demand Base Matrix'!H$32)*$AC$2*$AD$2*$AE$2+('Demand Base Matrix'!H$29+'Demand Base Matrix'!H$30)*$W$2*$AD$2+'Demand Base Matrix'!H$31*$W$2*$AD$2*$AE$2+'Demand Base Matrix'!H$33+'Demand Base Matrix'!H$34*$AF$2),IF($C14="Bond",(('Demand Base Matrix'!H$55+'Demand Base Matrix'!H$59)*$AC$2*$AD$2*$AE$2+('Demand Base Matrix'!H$56+'Demand Base Matrix'!H$57)*$W$2*$AD$2+'Demand Base Matrix'!H$58*$W$2*$AD$2*$AE$2+'Demand Base Matrix'!H$60+'Demand Base Matrix'!H$61*$AF$2),IF($C14="Explore",('Demand Base Matrix'!H$82*$AC$2*$AD$2*$AE$2*$AF$2+'Demand Base Matrix'!H$83*$W$2*$AC$2*$AD$2*$AE$2*$AF$2+'Demand Base Matrix'!H$84))))) -> 60 | AL14: =IF($C14="Validate",(('Demand Base Matrix'!I$2+'Demand Base Matrix'!I$6)*$AC$2*$AD$2*$AE$2+('Demand Base Matrix'!I$3+'Demand Base Matrix'!I$4)*$W$2*$AD$2+'Demand Base Matrix'!I$5*$W$2*$AD$2*$AE$2+'Demand Base Matrix'!I$7+'Demand Base Matrix'!I$8*$AF$2),IF($C14="Integrate",(('Demand Base Matrix'!I$28+'Demand Base Matrix'!I$32)*$AC$2*$AD$2*$AE$2+('Demand Base Matrix'!I$29+'Demand Base Matrix'!I$30)*$W$2*$AD$2+'Demand Base Matrix'!I$31*$W$2*$AD$2*$AE$2+'Demand Base Matrix'!I$33+'Demand Base Matrix'!I$34*$AF$2),IF($C14="Bond",(('Demand Base Matrix'!I$55+'Demand Base Matrix'!I$59)*$AC$2*$AD$2*$AE$2+('Demand Base Matrix'!I$56+'Demand Base Matrix'!I$57)*$W$2*$AD$2+'Demand Base Matrix'!I$58*$W$2*$AD$2*$AE$2+'Demand Base Matrix'!I$60+'Demand Base Matrix'!I$61*$AF$2),IF($C14="Explore",('Demand Base Matrix'!I$82*$AC$2*$AD$2*$AE$2*$AF$2+'Demand Base Matrix'!I$83*$W$2*$AC$2*$AD$2*$AE$2*$AF$2+'Demand Base Matrix'!I$84))))) -> 10 | AM14: =IF($C14="Validate",(('Demand Base Matrix'!J$2+'Demand Base Matrix'!J$6)*$AC$2*$AD$2*$AE$2+('Demand Base Matrix'!J$3+'Demand Base Matrix'!J$4)*$W$2*$AD$2+'Demand Base Matrix'!J$5*$W$2*$AD$2*$AE$2+'Demand Base Matrix'!J$7+'Demand Base Matrix'!J$8*$AF$2),IF($C14="Integrate",(('Demand Base Matrix'!J$28+'Demand Base Matrix'!J$32)*$AC$2*$AD$2*$AE$2+('Demand Base Matrix'!J$29+'Demand Base Matrix'!J$30)*$W$2*$AD$2+'Demand Base Matrix'!J$31*$W$2*$AD$2*$AE$2+'Demand Base Matrix'!J$33+'Demand Base Matrix'!J$34*$AF$2),IF($C14="Bond",(('Demand Base Matrix'!J$55+'Demand Base Matrix'!J$59)*$AC$2*$AD$2*$AE$2+('Demand Base Matrix'!J$56+'Demand Base Matrix'!J$57)*$W$2*$AD$2+'Demand Base Matrix'!J$58*$W$2*$AD$2*$AE$2+'Demand Base Matrix'!J$60+'Demand Base Matrix'!J$61*$AF$2),IF($C14="Explore",('Demand Base Matrix'!J$82*$AC$2*$AD$2*$AE$2*$AF$2+'Demand Base Matrix'!J$83*$W$2*$AC$2*$AD$2*$AE$2*$AF$2+'Demand Base Matrix'!J$84))))) -> 4
A15: [2026 SaaS Y3] City of East Point | B15: City of East Point | C15: Bond | D15: Savannah Peery | E15: Mukul Mathur | F15: Divyanshi | I15: =IFERROR(INDEX('Customer 360'!F:F,MATCH(B15,'Customer 360'!A:A,0)),"-") -> D | J15: 200 | L15: 46251 | M15: 46251 | N15: 2026 | O15: 46023 | P15: IVMS | Q15: =O15 -> 46023 | R15: =IFERROR(IF(M15<>"",M15,IF(L15<>"",L15,INDEX('CSM RDD'!B:B,MATCH(B15,'CSM RDD'!A:A,0)))),"-") -> 46251 | S15: =IFERROR(EOMONTH(Q15,-1)+1,"") -> 46023 | T15: =IFERROR(EOMONTH(R15,-1)+1,"") -> 46235 | U15: =J15+K15 -> 200 | V15: =IF(C15<>"Validate",DATE(2026,3,1),O15) -> 46082 | W15: =IF(U15=0,1,IF(U15<='Demand Base Matrix'!$K$3,'Demand Base Matrix'!$L$3,IF(U15<='Demand Base Matrix'!$K$4,'Demand Base Matrix'!$L$4,IF(U15<='Demand Base Matrix'!$K$5,'Demand Base Matrix'!$L$5,IF(U15<='Demand Base Matrix'!$K$6,'Demand Base Matrix'!$L$6,IF(U15<='Demand Base Matrix'!$K$7,'Demand Base Matrix'!$L$7)))))) -> 0.75 | X15: =DATE(YEAR(R15),MONTH(R15),1) -> 46235 | Y15: =IF(K15>0,"Tx","Dx") -> Dx | Z15: Low | AA15: Low | AB15: Low | AC15: =IFERROR(INDEX('Demand Base Matrix'!AM:AM,MATCH(Y15,'Demand Base Matrix'!AL:AL,0)),"-") -> 1 | AD15: =IFERROR(INDEX('Demand Base Matrix'!AO:AO,MATCH(Z15,'Demand Base Matrix'!AN:AN,0)),1) -> 1 | AE15: =IFERROR(INDEX('Demand Base Matrix'!AQ:AQ,MATCH(AA15,'Demand Base Matrix'!AP:AP,0)),1) -> 1 | AF15: =IFERROR(INDEX('Demand Base Matrix'!AS:AS,MATCH(AB15,'Demand Base Matrix'!AR:AR,0)),1) -> 1 | AG15: =IF($C15="Validate",(('Demand Base Matrix'!D$2+'Demand Base Matrix'!D$6)*$AC$2*$AD$2*$AE$2+('Demand Base Matrix'!D$3+'Demand Base Matrix'!D$4)*$W$2*$AD$2+'Demand Base Matrix'!D$5*$W$2*$AD$2*$AE$2+'Demand Base Matrix'!D$7+'Demand Base Matrix'!D$8*$AF$2),IF($C15="Integrate",(('Demand Base Matrix'!D$28+'Demand Base Matrix'!D$32)*$AC$2*$AD$2*$AE$2+('Demand Base Matrix'!D$29+'Demand Base Matrix'!D$30)*$W$2*$AD$2+'Demand Base Matrix'!D$31*$W$2*$AD$2*$AE$2+'Demand Base Matrix'!D$33+'Demand Base Matrix'!D$34*$AF$2),IF($C15="Bond",(('Demand Base Matrix'!D$55+'Demand Base Matrix'!D$59)*$AC$2*$AD$2*$AE$2+('Demand Base Matrix'!D$56+'Demand Base Matrix'!D$57)*$W$2*$AD$2+'Demand Base Matrix'!D$58*$W$2*$AD$2*$AE$2+'Demand Base Matrix'!D$60+'Demand Base Matrix'!D$61*$AF$2),IF($C15="Explore",('Demand Base Matrix'!D$82*$AC$2*$AD$2*$AE$2*$AF$2+'Demand Base Matrix'!D$83*$W$2*$AC$2*$AD$2*$AE$2*$AF$2+'Demand Base Matrix'!D$84))))) -> 10 | AH15: =IF($C15="Validate",(('Demand Base Matrix'!E$2+'Demand Base Matrix'!E$6)*$AC$2*$AD$2*$AE$2+('Demand Base Matrix'!E$3+'Demand Base Matrix'!E$4)*$W$2*$AD$2+'Demand Base Matrix'!E$5*$W$2*$AD$2*$AE$2+'Demand Base Matrix'!E$7+'Demand Base Matrix'!E$8*$AF$2),IF($C15="Integrate",(('Demand Base Matrix'!E$28+'Demand Base Matrix'!E$32)*$AC$2*$AD$2*$AE$2+('Demand Base Matrix'!E$29+'Demand Base Matrix'!E$30)*$W$2*$AD$2+'Demand Base Matrix'!E$31*$W$2*$AD$2*$AE$2+'Demand Base Matrix'!E$33+'Demand Base Matrix'!E$34*$AF$2),IF($C15="Bond",(('Demand Base Matrix'!E$55+'Demand Base Matrix'!E$59)*$AC$2*$AD$2*$AE$2+('Demand Base Matrix'!E$56+'Demand Base Matrix'!E$57)*$W$2*$AD$2+'Demand Base Matrix'!E$58*$W$2*$AD$2*$AE$2+'Demand Base Matrix'!E$60+'Demand Base Matrix'!E$61*$AF$2),IF($C15="Explore",('Demand Base Matrix'!E$82*$AC$2*$AD$2*$AE$2*$AF$2+'Demand Base Matrix'!E$83*$W$2*$AC$2*$AD$2*$AE$2*$AF$2+'Demand Base Matrix'!E$84))))) -> 10 | AI15: =IF($C15="Validate",(('Demand Base Matrix'!F$2+'Demand Base Matrix'!F$6)*$AC$2*$AD$2*$AE$2+('Demand Base Matrix'!F$3+'Demand Base Matrix'!F$4)*$W$2*$AD$2+'Demand Base Matrix'!F$5*$W$2*$AD$2*$AE$2+'Demand Base Matrix'!F$7+'Demand Base Matrix'!F$8*$AF$2),IF($C15="Integrate",(('Demand Base Matrix'!F$28+'Demand Base Matrix'!F$32)*$AC$2*$AD$2*$AE$2+('Demand Base Matrix'!F$29+'Demand Base Matrix'!F$30)*$W$2*$AD$2+'Demand Base Matrix'!F$31*$W$2*$AD$2*$AE$2+'Demand Base Matrix'!F$33+'Demand Base Matrix'!F$34*$AF$2),IF($C15="Bond",(('Demand Base Matrix'!F$55+'Demand Base Matrix'!F$59)*$AC$2*$AD$2*$AE$2+('Demand Base Matrix'!F$56+'Demand Base Matrix'!F$57)*$W$2*$AD$2+'Demand Base Matrix'!F$58*$W$2*$AD$2*$AE$2+'Demand Base Matrix'!F$60+'Demand Base Matrix'!F$61*$AF$2),IF($C15="Explore",('Demand Base Matrix'!F$82*$AC$2*$AD$2*$AE$2*$AF$2+'Demand Base Matrix'!F$83*$W$2*$AC$2*$AD$2*$AE$2*$AF$2+'Demand Base Matrix'!F$84))))) -> 10 | AJ15: =IF($C15="Validate",(('Demand Base Matrix'!G$2+'Demand Base Matrix'!G$6)*$AC$2*$AD$2*$AE$2+('Demand Base Matrix'!G$3+'Demand Base Matrix'!G$4)*$W$2*$AD$2+'Demand Base Matrix'!G$5*$W$2*$AD$2*$AE$2+'Demand Base Matrix'!G$7+'Demand Base Matrix'!G$8*$AF$2),IF($C15="Integrate",(('Demand Base Matrix'!G$28+'Demand Base Matrix'!G$32)*$AC$2*$AD$2*$AE$2+('Demand Base Matrix'!G$29+'Demand Base Matrix'!G$30)*$W$2*$AD$2+'Demand Base Matrix'!G$31*$W$2*$AD$2*$AE$2+'Demand Base Matrix'!G$33+'Demand Base Matrix'!G$34*$AF$2),IF($C15="Bond",(('Demand Base Matrix'!G$55+'Demand Base Matrix'!G$59)*$AC$2*$AD$2*$AE$2+('Demand Base Matrix'!G$56+'Demand Base Matrix'!G$57)*$W$2*$AD$2+'Demand Base Matrix'!G$58*$W$2*$AD$2*$AE$2+'Demand Base Matrix'!G$60+'Demand Base Matrix'!G$61*$AF$2),IF($C15="Explore",('Demand Base Matrix'!G$82*$AC$2*$AD$2*$AE$2*$AF$2+'Demand Base Matrix'!G$83*$W$2*$AC$2*$AD$2*$AE$2*$AF$2+'Demand Base Matrix'!G$84))))) -> 50 | AK15: =IF($C15="Validate",(('Demand Base Matrix'!H$2+'Demand Base Matrix'!H$6)*$AC$2*$AD$2*$AE$2+('Demand Base Matrix'!H$3+'Demand Base Matrix'!H$4)*$W$2*$AD$2+'Demand Base Matrix'!H$5*$W$2*$AD$2*$AE$2+'Demand Base Matrix'!H$7+'Demand Base Matrix'!H$8*$AF$2),IF($C15="Integrate",(('Demand Base Matrix'!H$28+'Demand Base Matrix'!H$32)*$AC$2*$AD$2*$AE$2+('Demand Base Matrix'!H$29+'Demand Base Matrix'!H$30)*$W$2*$AD$2+'Demand Base Matrix'!H$31*$W$2*$AD$2*$AE$2+'Demand Base Matrix'!H$33+'Demand Base Matrix'!H$34*$AF$2),IF($C15="Bond",(('Demand Base Matrix'!H$55+'Demand Base Matrix'!H$59)*$AC$2*$AD$2*$AE$2+('Demand Base Matrix'!H$56+'Demand Base Matrix'!H$57)*$W$2*$AD$2+'Demand Base Matrix'!H$58*$W$2*$AD$2*$AE$2+'Demand Base Matrix'!H$60+'Demand Base Matrix'!H$61*$AF$2),IF($C15="Explore",('Demand Base Matrix'!H$82*$AC$2*$AD$2*$AE$2*$AF$2+'Demand Base Matrix'!H$83*$W$2*$AC$2*$AD$2*$AE$2*$AF$2+'Demand Base Matrix'!H$84))))) -> 28 | AL15: =IF($C15="Validate",(('Demand Base Matrix'!I$2+'Demand Base Matrix'!I$6)*$AC$2*$AD$2*$AE$2+('Demand Base Matrix'!I$3+'Demand Base Matrix'!I$4)*$W$2*$AD$2+'Demand Base Matrix'!I$5*$W$2*$AD$2*$AE$2+'Demand Base Matrix'!I$7+'Demand Base Matrix'!I$8*$AF$2),IF($C15="Integrate",(('Demand Base Matrix'!I$28+'Demand Base Matrix'!I$32)*$AC$2*$AD$2*$AE$2+('Demand Base Matrix'!I$29+'Demand Base Matrix'!I$30)*$W$2*$AD$2+'Demand Base Matrix'!I$31*$W$2*$AD$2*$AE$2+'Demand Base Matrix'!I$33+'Demand Base Matrix'!I$34*$AF$2),IF($C15="Bond",(('Demand Base Matrix'!I$55+'Demand Base Matrix'!I$59)*$AC$2*$AD$2*$AE$2+('Demand Base Matrix'!I$56+'Demand Base Matrix'!I$57)*$W$2*$AD$2+'Demand Base Matrix'!I$58*$W$2*$AD$2*$AE$2+'Demand Base Matrix'!I$60+'Demand Base Matrix'!I$61*$AF$2),IF($C15="Explore",('Demand Base Matrix'!I$82*$AC$2*$AD$2*$AE$2*$AF$2+'Demand Base Matrix'!I$83*$W$2*$AC$2*$AD$2*$AE$2*$AF$2+'Demand Base Matrix'!I$84))))) -> 8 | AM15: =IF($C15="Validate",(('Demand Base Matrix'!J$2+'Demand Base Matrix'!J$6)*$AC$2*$AD$2*$AE$2+('Demand Base Matrix'!J$3+'Demand Base Matrix'!J$4)*$W$2*$AD$2+'Demand Base Matrix'!J$5*$W$2*$AD$2*$AE$2+'Demand Base Matrix'!J$7+'Demand Base Matrix'!J$8*$AF$2),IF($C15="Integrate",(('Demand Base Matrix'!J$28+'Demand Base Matrix'!J$32)*$AC$2*$AD$2*$AE$2+('Demand Base Matrix'!J$29+'Demand Base Matrix'!J$30)*$W$2*$AD$2+'Demand Base Matrix'!J$31*$W$2*$AD$2*$AE$2+'Demand Base Matrix'!J$33+'Demand Base Matrix'!J$34*$AF$2),IF($C15="Bond",(('Demand Base Matrix'!J$55+'Demand Base Matrix'!J$59)*$AC$2*$AD$2*$AE$2+('Demand Base Matrix'!J$56+'Demand Base Matrix'!J$57)*$W$2*$AD$2+'Demand Base Matrix'!J$58*$W$2*$AD$2*$AE$2+'Demand Base Matrix'!J$60+'Demand Base Matrix'!J$61*$AF$2),IF($C15="Explore",('Demand Base Matrix'!J$82*$AC$2*$AD$2*$AE$2*$AF$2+'Demand Base Matrix'!J$83*$W$2*$AC$2*$AD$2*$AE$2*$AF$2+'Demand Base Matrix'!J$84))))) -> 8
A16: [2026 SaaS Y3] City of High Point | B16: City of High Point | C16: Bond | D16: Stefanie Naden | E16: Shashank Sharma | F16: Satyam Kumar | I16: =IFERROR(INDEX('Customer 360'!F:F,MATCH(B16,'Customer 360'!A:A,0)),"-") -> D | J16: 488 | L16: 46176 | M16: 46176 | N16: 2026 | O16: 46023 | P16: IVMS | Q16: =O16 -> 46023 | R16: =IFERROR(IF(M16<>"",M16,IF(L16<>"",L16,INDEX('CSM RDD'!B:B,MATCH(B16,'CSM RDD'!A:A,0)))),"-") -> 46176 | S16: =IFERROR(EOMONTH(Q16,-1)+1,"") -> 46023 | T16: =IFERROR(EOMONTH(R16,-1)+1,"") -> 46174 | U16: =J16+K16 -> 488 | V16: =IF(C16<>"Validate",DATE(2026,3,1),O16) -> 46082 | W16: =IF(U16=0,1,IF(U16<='Demand Base Matrix'!$K$3,'Demand Base Matrix'!$L$3,IF(U16<='Demand Base Matrix'!$K$4,'Demand Base Matrix'!$L$4,IF(U16<='Demand Base Matrix'!$K$5,'Demand Base Matrix'!$L$5,IF(U16<='Demand Base Matrix'!$K$6,'Demand Base Matrix'!$L$6,IF(U16<='Demand Base Matrix'!$K$7,'Demand Base Matrix'!$L$7)))))) -> 0.75 | X16: =DATE(YEAR(R16),MONTH(R16),1) -> 46174 | Y16: =IF(K16>0,"Tx","Dx") -> Dx | Z16: Low | AA16: Low | AB16: Low | AC16: =IFERROR(INDEX('Demand Base Matrix'!AM:AM,MATCH(Y16,'Demand Base Matrix'!AL:AL,0)),"-") -> 1 | AD16: =IFERROR(INDEX('Demand Base Matrix'!AO:AO,MATCH(Z16,'Demand Base Matrix'!AN:AN,0)),1) -> 1 | AE16: =IFERROR(INDEX('Demand Base Matrix'!AQ:AQ,MATCH(AA16,'Demand Base Matrix'!AP:AP,0)),1) -> 1 | AF16: =IFERROR(INDEX('Demand Base Matrix'!AS:AS,MATCH(AB16,'Demand Base Matrix'!AR:AR,0)),1) -> 1 | AG16: =IF($C16="Validate",(('Demand Base Matrix'!D$2+'Demand Base Matrix'!D$6)*$AC$2*$AD$2*$AE$2+('Demand Base Matrix'!D$3+'Demand Base Matrix'!D$4)*$W$2*$AD$2+'Demand Base Matrix'!D$5*$W$2*$AD$2*$AE$2+'Demand Base Matrix'!D$7+'Demand Base Matrix'!D$8*$AF$2),IF($C16="Integrate",(('Demand Base Matrix'!D$28+'Demand Base Matrix'!D$32)*$AC$2*$AD$2*$AE$2+('Demand Base Matrix'!D$29+'Demand Base Matrix'!D$30)*$W$2*$AD$2+'Demand Base Matrix'!D$31*$W$2*$AD$2*$AE$2+'Demand Base Matrix'!D$33+'Demand Base Matrix'!D$34*$AF$2),IF($C16="Bond",(('Demand Base Matrix'!D$55+'Demand Base Matrix'!D$59)*$AC$2*$AD$2*$AE$2+('Demand Base Matrix'!D$56+'Demand Base Matrix'!D$57)*$W$2*$AD$2+'Demand Base Matrix'!D$58*$W$2*$AD$2*$AE$2+'Demand Base Matrix'!D$60+'Demand Base Matrix'!D$61*$AF$2),IF($C16="Explore",('Demand Base Matrix'!D$82*$AC$2*$AD$2*$AE$2*$AF$2+'Demand Base Matrix'!D$83*$W$2*$AC$2*$AD$2*$AE$2*$AF$2+'Demand Base Matrix'!D$84))))) -> 10 | AH16: =IF($C16="Validate",(('Demand Base Matrix'!E$2+'Demand Base Matrix'!E$6)*$AC$2*$AD$2*$AE$2+('Demand Base Matrix'!E$3+'Demand Base Matrix'!E$4)*$W$2*$AD$2+'Demand Base Matrix'!E$5*$W$2*$AD$2*$AE$2+'Demand Base Matrix'!E$7+'Demand Base Matrix'!E$8*$AF$2),IF($C16="Integrate",(('Demand Base Matrix'!E$28+'Demand Base Matrix'!E$32)*$AC$2*$AD$2*$AE$2+('Demand Base Matrix'!E$29+'Demand Base Matrix'!E$30)*$W$2*$AD$2+'Demand Base Matrix'!E$31*$W$2*$AD$2*$AE$2+'Demand Base Matrix'!E$33+'Demand Base Matrix'!E$34*$AF$2),IF($C16="Bond",(('Demand Base Matrix'!E$55+'Demand Base Matrix'!E$59)*$AC$2*$AD$2*$AE$2+('Demand Base Matrix'!E$56+'Demand Base Matrix'!E$57)*$W$2*$AD$2+'Demand Base Matrix'!E$58*$W$2*$AD$2*$AE$2+'Demand Base Matrix'!E$60+'Demand Base Matrix'!E$61*$AF$2),IF($C16="Explore",('Demand Base Matrix'!E$82*$AC$2*$AD$2*$AE$2*$AF$2+'Demand Base Matrix'!E$83*$W$2*$AC$2*$AD$2*$AE$2*$AF$2+'Demand Base Matrix'!E$84))))) -> 10 | AI16: =IF($C16="Validate",(('Demand Base Matrix'!F$2+'Demand Base Matrix'!F$6)*$AC$2*$AD$2*$AE$2+('Demand Base Matrix'!F$3+'Demand Base Matrix'!F$4)*$W$2*$AD$2+'Demand Base Matrix'!F$5*$W$2*$AD$2*$AE$2+'Demand Base Matrix'!F$7+'Demand Base Matrix'!F$8*$AF$2),IF($C16="Integrate",(('Demand Base Matrix'!F$28+'Demand Base Matrix'!F$32)*$AC$2*$AD$2*$AE$2+('Demand Base Matrix'!F$29+'Demand Base Matrix'!F$30)*$W$2*$AD$2+'Demand Base Matrix'!F$31*$W$2*$AD$2*$AE$2+'Demand Base Matrix'!F$33+'Demand Base Matrix'!F$34*$AF$2),IF($C16="Bond",(('Demand Base Matrix'!F$55+'Demand Base Matrix'!F$59)*$AC$2*$AD$2*$AE$2+('Demand Base Matrix'!F$56+'Demand Base Matrix'!F$57)*$W$2*$AD$2+'Demand Base Matrix'!F$58*$W$2*$AD$2*$AE$2+'Demand Base Matrix'!F$60+'Demand Base Matrix'!F$61*$AF$2),IF($C16="Explore",('Demand Base Matrix'!F$82*$AC$2*$AD$2*$AE$2*$AF$2+'Demand Base Matrix'!F$83*$W$2*$AC$2*$AD$2*$AE$2*$AF$2+'Demand Base Matrix'!F$84))))) -> 10 | AJ16: =IF($C16="Validate",(('Demand Base Matrix'!G$2+'Demand Base Matrix'!G$6)*$AC$2*$AD$2*$AE$2+('Demand Base Matrix'!G$3+'Demand Base Matrix'!G$4)*$W$2*$AD$2+'Demand Base Matrix'!G$5*$W$2*$AD$2*$AE$2+'Demand Base Matrix'!G$7+'Demand Base Matrix'!G$8*$AF$2),IF($C16="Integrate",(('Demand Base Matrix'!G$28+'Demand Base Matrix'!G$32)*$AC$2*$AD$2*$AE$2+('Demand Base Matrix'!G$29+'Demand Base Matrix'!G$30)*$W$2*$AD$2+'Demand Base Matrix'!G$31*$W$2*$AD$2*$AE$2+'Demand Base Matrix'!G$33+'Demand Base Matrix'!G$34*$AF$2),IF($C16="Bond",(('Demand Base Matrix'!G$55+'Demand Base Matrix'!G$59)*$AC$2*$AD$2*$AE$2+('Demand Base Matrix'!G$56+'Demand Base Matrix'!G$57)*$W$2*$AD$2+'Demand Base Matrix'!G$58*$W$2*$AD$2*$AE$2+'Demand Base Matrix'!G$60+'Demand Base Matrix'!G$61*$AF$2),IF($C16="Explore",('Demand Base Matrix'!G$82*$AC$2*$AD$2*$AE$2*$AF$2+'Demand Base Matrix'!G$83*$W$2*$AC$2*$AD$2*$AE$2*$AF$2+'Demand Base Matrix'!G$84))))) -> 50 | AK16: =IF($C16="Validate",(('Demand Base Matrix'!H$2+'Demand Base Matrix'!H$6)*$AC$2*$AD$2*$AE$2+('Demand Base Matrix'!H$3+'Demand Base Matrix'!H$4)*$W$2*$AD$2+'Demand Base Matrix'!H$5*$W$2*$AD$2*$AE$2+'Demand Base Matrix'!H$7+'Demand Base Matrix'!H$8*$AF$2),IF($C16="Integrate",(('Demand Base Matrix'!H$28+'Demand Base Matrix'!H$32)*$AC$2*$AD$2*$AE$2+('Demand Base Matrix'!H$29+'Demand Base Matrix'!H$30)*$W$2*$AD$2+'Demand Base Matrix'!H$31*$W$2*$AD$2*$AE$2+'Demand Base Matrix'!H$33+'Demand Base Matrix'!H$34*$AF$2),IF($C16="Bond",(('Demand Base Matrix'!H$55+'Demand Base Matrix'!H$59)*$AC$2*$AD$2*$AE$2+('Demand Base Matrix'!H$56+'Demand Base Matrix'!H$57)*$W$2*$AD$2+'Demand Base Matrix'!H$58*$W$2*$AD$2*$AE$2+'Demand Base Matrix'!H$60+'Demand Base Matrix'!H$61*$AF$2),IF($C16="Explore",('Demand Base Matrix'!H$82*$AC$2*$AD$2*$AE$2*$AF$2+'Demand Base Matrix'!H$83*$W$2*$AC$2*$AD$2*$AE$2*$AF$2+'Demand Base Matrix'!H$84))))) -> 28 | AL16: =IF($C16="Validate",(('Demand Base Matrix'!I$2+'Demand Base Matrix'!I$6)*$AC$2*$AD$2*$AE$2+('Demand Base Matrix'!I$3+'Demand Base Matrix'!I$4)*$W$2*$AD$2+'Demand Base Matrix'!I$5*$W$2*$AD$2*$AE$2+'Demand Base Matrix'!I$7+'Demand Base Matrix'!I$8*$AF$2),IF($C16="Integrate",(('Demand Base Matrix'!I$28+'Demand Base Matrix'!I$32)*$AC$2*$AD$2*$AE$2+('Demand Base Matrix'!I$29+'Demand Base Matrix'!I$30)*$W$2*$AD$2+'Demand Base Matrix'!I$31*$W$2*$AD$2*$AE$2+'Demand Base Matrix'!I$33+'Demand Base Matrix'!I$34*$AF$2),IF($C16="Bond",(('Demand Base Matrix'!I$55+'Demand Base Matrix'!I$59)*$AC$2*$AD$2*$AE$2+('Demand Base Matrix'!I$56+'Demand Base Matrix'!I$57)*$W$2*$AD$2+'Demand Base Matrix'!I$58*$W$2*$AD$2*$AE$2+'Demand Base Matrix'!I$60+'Demand Base Matrix'!I$61*$AF$2),IF($C16="Explore",('Demand Base Matrix'!I$82*$AC$2*$AD$2*$AE$2*$AF$2+'Demand Base Matrix'!I$83*$W$2*$AC$2*$AD$2*$AE$2*$AF$2+'Demand Base Matrix'!I$84))))) -> 8 | AM16: =IF($C16="Validate",(('Demand Base Matrix'!J$2+'Demand Base Matrix'!J$6)*$AC$2*$AD$2*$AE$2+('Demand Base Matrix'!J$3+'Demand Base Matrix'!J$4)*$W$2*$AD$2+'Demand Base Matrix'!J$5*$W$2*$AD$2*$AE$2+'Demand Base Matrix'!J$7+'Demand Base Matrix'!J$8*$AF$2),IF($C16="Integrate",(('Demand Base Matrix'!J$28+'Demand Base Matrix'!J$32)*$AC$2*$AD$2*$AE$2+('Demand Base Matrix'!J$29+'Demand Base Matrix'!J$30)*$W$2*$AD$2+'Demand Base Matrix'!J$31*$W$2*$AD$2*$AE$2+'Demand Base Matrix'!J$33+'Demand Base Matrix'!J$34*$AF$2),IF($C16="Bond",(('Demand Base Matrix'!J$55+'Demand Base Matrix'!J$59)*$AC$2*$AD$2*$AE$2+('Demand Base Matrix'!J$56+'Demand Base Matrix'!J$57)*$W$2*$AD$2+'Demand Base Matrix'!J$58*$W$2*$AD$2*$AE$2+'Demand Base Matrix'!J$60+'Demand Base Matrix'!J$61*$AF$2),IF($C16="Explore",('Demand Base Matrix'!J$82*$AC$2*$AD$2*$AE$2*$AF$2+'Demand Base Matrix'!J$83*$W$2*$AC$2*$AD$2*$AE$2*$AF$2+'Demand Base Matrix'!J$84))))) -> 8
A17: [2026 SaaS Y1] City of Lake Worth Beach | B17: City of Lake Worth Beach | C17: Validate | D17: Emily Turner | E17: Mukul Gupta | F17: Divyanshi | I17: =IFERROR(INDEX('Customer 360'!F:F,MATCH(B17,'Customer 360'!A:A,0)),"-") -> C | M17: 46311 | N17: 2026 | O17: 46082 | P17: IVMS | Q17: =O17 -> 46082 | R17: =IFERROR(IF(M17<>"",M17,IF(L17<>"",L17,INDEX('CSM RDD'!B:B,MATCH(B17,'CSM RDD'!A:A,0)))),"-") -> 46311 | S17: =IFERROR(EOMONTH(Q17,-1)+1,"") -> 46082 | T17: =IFERROR(EOMONTH(R17,-1)+1,"") -> 46296 | U17: =J17+K17 -> 0 | V17: =IF(C17<>"Validate",DATE(2026,3,1),O17) -> 46082 | W17: =IF(U17=0,1,IF(U17<='Demand Base Matrix'!$K$3,'Demand Base Matrix'!$L$3,IF(U17<='Demand Base Matrix'!$K$4,'Demand Base Matrix'!$L$4,IF(U17<='Demand Base Matrix'!$K$5,'Demand Base Matrix'!$L$5,IF(U17<='Demand Base Matrix'!$K$6,'Demand Base Matrix'!$L$6,IF(U17<='Demand Base Matrix'!$K$7,'Demand Base Matrix'!$L$7)))))) -> 1 | X17: =DATE(YEAR(R17),MONTH(R17),1) -> 46296 | Y17: =IF(K17>0,"Tx","Dx") -> Dx | Z17: 0 | AA17: 0 | AB17: 0 | AC17: =IFERROR(INDEX('Demand Base Matrix'!AM:AM,MATCH(Y17,'Demand Base Matrix'!AL:AL,0)),"-") -> 1 | AD17: =IFERROR(INDEX('Demand Base Matrix'!AO:AO,MATCH(Z17,'Demand Base Matrix'!AN:AN,0)),1) -> 1 | AE17: =IFERROR(INDEX('Demand Base Matrix'!AQ:AQ,MATCH(AA17,'Demand Base Matrix'!AP:AP,0)),1) -> 1 | AF17: =IFERROR(INDEX('Demand Base Matrix'!AS:AS,MATCH(AB17,'Demand Base Matrix'!AR:AR,0)),1) -> 1 | AG17: =IF($C17="Validate",(('Demand Base Matrix'!D$2+'Demand Base Matrix'!D$6)*$AC$2*$AD$2*$AE$2+('Demand Base Matrix'!D$3+'Demand Base Matrix'!D$4)*$W$2*$AD$2+'Demand Base Matrix'!D$5*$W$2*$AD$2*$AE$2+'Demand Base Matrix'!D$7+'Demand Base Matrix'!D$8*$AF$2),IF($C17="Integrate",(('Demand Base Matrix'!D$28+'Demand Base Matrix'!D$32)*$AC$2*$AD$2*$AE$2+('Demand Base Matrix'!D$29+'Demand Base Matrix'!D$30)*$W$2*$AD$2+'Demand Base Matrix'!D$31*$W$2*$AD$2*$AE$2+'Demand Base Matrix'!D$33+'Demand Base Matrix'!D$34*$AF$2),IF($C17="Bond",(('Demand Base Matrix'!D$55+'Demand Base Matrix'!D$59)*$AC$2*$AD$2*$AE$2+('Demand Base Matrix'!D$56+'Demand Base Matrix'!D$57)*$W$2*$AD$2+'Demand Base Matrix'!D$58*$W$2*$AD$2*$AE$2+'Demand Base Matrix'!D$60+'Demand Base Matrix'!D$61*$AF$2),IF($C17="Explore",('Demand Base Matrix'!D$82*$AC$2*$AD$2*$AE$2*$AF$2+'Demand Base Matrix'!D$83*$W$2*$AC$2*$AD$2*$AE$2*$AF$2+'Demand Base Matrix'!D$84))))) -> 15 | AH17: =IF($C17="Validate",(('Demand Base Matrix'!E$2+'Demand Base Matrix'!E$6)*$AC$2*$AD$2*$AE$2+('Demand Base Matrix'!E$3+'Demand Base Matrix'!E$4)*$W$2*$AD$2+'Demand Base Matrix'!E$5*$W$2*$AD$2*$AE$2+'Demand Base Matrix'!E$7+'Demand Base Matrix'!E$8*$AF$2),IF($C17="Integrate",(('Demand Base Matrix'!E$28+'Demand Base Matrix'!E$32)*$AC$2*$AD$2*$AE$2+('Demand Base Matrix'!E$29+'Demand Base Matrix'!E$30)*$W$2*$AD$2+'Demand Base Matrix'!E$31*$W$2*$AD$2*$AE$2+'Demand Base Matrix'!E$33+'Demand Base Matrix'!E$34*$AF$2),IF($C17="Bond",(('Demand Base Matrix'!E$55+'Demand Base Matrix'!E$59)*$AC$2*$AD$2*$AE$2+('Demand Base Matrix'!E$56+'Demand Base Matrix'!E$57)*$W$2*$AD$2+'Demand Base Matrix'!E$58*$W$2*$AD$2*$AE$2+'Demand Base Matrix'!E$60+'Demand Base Matrix'!E$61*$AF$2),IF($C17="Explore",('Demand Base Matrix'!E$82*$AC$2*$AD$2*$AE$2*$AF$2+'Demand Base Matrix'!E$83*$W$2*$AC$2*$AD$2*$AE$2*$AF$2+'Demand Base Matrix'!E$84))))) -> 15 | AI17: =IF($C17="Validate",(('Demand Base Matrix'!F$2+'Demand Base Matrix'!F$6)*$AC$2*$AD$2*$AE$2+('Demand Base Matrix'!F$3+'Demand Base Matrix'!F$4)*$W$2*$AD$2+'Demand Base Matrix'!F$5*$W$2*$AD$2*$AE$2+'Demand Base Matrix'!F$7+'Demand Base Matrix'!F$8*$AF$2),IF($C17="Integrate",(('Demand Base Matrix'!F$28+'Demand Base Matrix'!F$32)*$AC$2*$AD$2*$AE$2+('Demand Base Matrix'!F$29+'Demand Base Matrix'!F$30)*$W$2*$AD$2+'Demand Base Matrix'!F$31*$W$2*$AD$2*$AE$2+'Demand Base Matrix'!F$33+'Demand Base Matrix'!F$34*$AF$2),IF($C17="Bond",(('Demand Base Matrix'!F$55+'Demand Base Matrix'!F$59)*$AC$2*$AD$2*$AE$2+('Demand Base Matrix'!F$56+'Demand Base Matrix'!F$57)*$W$2*$AD$2+'Demand Base Matrix'!F$58*$W$2*$AD$2*$AE$2+'Demand Base Matrix'!F$60+'Demand Base Matrix'!F$61*$AF$2),IF($C17="Explore",('Demand Base Matrix'!F$82*$AC$2*$AD$2*$AE$2*$AF$2+'Demand Base Matrix'!F$83*$W$2*$AC$2*$AD$2*$AE$2*$AF$2+'Demand Base Matrix'!F$84))))) -> 7 | AJ17: =IF($C17="Validate",(('Demand Base Matrix'!G$2+'Demand Base Matrix'!G$6)*$AC$2*$AD$2*$AE$2+('Demand Base Matrix'!G$3+'Demand Base Matrix'!G$4)*$W$2*$AD$2+'Demand Base Matrix'!G$5*$W$2*$AD$2*$AE$2+'Demand Base Matrix'!G$7+'Demand Base Matrix'!G$8*$AF$2),IF($C17="Integrate",(('Demand Base Matrix'!G$28+'Demand Base Matrix'!G$32)*$AC$2*$AD$2*$AE$2+('Demand Base Matrix'!G$29+'Demand Base Matrix'!G$30)*$W$2*$AD$2+'Demand Base Matrix'!G$31*$W$2*$AD$2*$AE$2+'Demand Base Matrix'!G$33+'Demand Base Matrix'!G$34*$AF$2),IF($C17="Bond",(('Demand Base Matrix'!G$55+'Demand Base Matrix'!G$59)*$AC$2*$AD$2*$AE$2+('Demand Base Matrix'!G$56+'Demand Base Matrix'!G$57)*$W$2*$AD$2+'Demand Base Matrix'!G$58*$W$2*$AD$2*$AE$2+'Demand Base Matrix'!G$60+'Demand Base Matrix'!G$61*$AF$2),IF($C17="Explore",('Demand Base Matrix'!G$82*$AC$2*$AD$2*$AE$2*$AF$2+'Demand Base Matrix'!G$83*$W$2*$AC$2*$AD$2*$AE$2*$AF$2+'Demand Base Matrix'!G$84))))) -> 40 | AK17: =IF($C17="Validate",(('Demand Base Matrix'!H$2+'Demand Base Matrix'!H$6)*$AC$2*$AD$2*$AE$2+('Demand Base Matrix'!H$3+'Demand Base Matrix'!H$4)*$W$2*$AD$2+'Demand Base Matrix'!H$5*$W$2*$AD$2*$AE$2+'Demand Base Matrix'!H$7+'Demand Base Matrix'!H$8*$AF$2),IF($C17="Integrate",(('Demand Base Matrix'!H$28+'Demand Base Matrix'!H$32)*$AC$2*$AD$2*$AE$2+('Demand Base Matrix'!H$29+'Demand Base Matrix'!H$30)*$W$2*$AD$2+'Demand Base Matrix'!H$31*$W$2*$AD$2*$AE$2+'Demand Base Matrix'!H$33+'Demand Base Matrix'!H$34*$AF$2),IF($C17="Bond",(('Demand Base Matrix'!H$55+'Demand Base Matrix'!H$59)*$AC$2*$AD$2*$AE$2+('Demand Base Matrix'!H$56+'Demand Base Matrix'!H$57)*$W$2*$AD$2+'Demand Base Matrix'!H$58*$W$2*$AD$2*$AE$2+'Demand Base Matrix'!H$60+'Demand Base Matrix'!H$61*$AF$2),IF($C17="Explore",('Demand Base Matrix'!H$82*$AC$2*$AD$2*$AE$2*$AF$2+'Demand Base Matrix'!H$83*$W$2*$AC$2*$AD$2*$AE$2*$AF$2+'Demand Base Matrix'!H$84))))) -> 60 | AL17: =IF($C17="Validate",(('Demand Base Matrix'!I$2+'Demand Base Matrix'!I$6)*$AC$2*$AD$2*$AE$2+('Demand Base Matrix'!I$3+'Demand Base Matrix'!I$4)*$W$2*$AD$2+'Demand Base Matrix'!I$5*$W$2*$AD$2*$AE$2+'Demand Base Matrix'!I$7+'Demand Base Matrix'!I$8*$AF$2),IF($C17="Integrate",(('Demand Base Matrix'!I$28+'Demand Base Matrix'!I$32)*$AC$2*$AD$2*$AE$2+('Demand Base Matrix'!I$29+'Demand Base Matrix'!I$30)*$W$2*$AD$2+'Demand Base Matrix'!I$31*$W$2*$AD$2*$AE$2+'Demand Base Matrix'!I$33+'Demand Base Matrix'!I$34*$AF$2),IF($C17="Bond",(('Demand Base Matrix'!I$55+'Demand Base Matrix'!I$59)*$AC$2*$AD$2*$AE$2+('Demand Base Matrix'!I$56+'Demand Base Matrix'!I$57)*$W$2*$AD$2+'Demand Base Matrix'!I$58*$W$2*$AD$2*$AE$2+'Demand Base Matrix'!I$60+'Demand Base Matrix'!I$61*$AF$2),IF($C17="Explore",('Demand Base Matrix'!I$82*$AC$2*$AD$2*$AE$2*$AF$2+'Demand Base Matrix'!I$83*$W$2*$AC$2*$AD$2*$AE$2*$AF$2+'Demand Base Matrix'!I$84))))) -> 10 | AM17: =IF($C17="Validate",(('Demand Base Matrix'!J$2+'Demand Base Matrix'!J$6)*$AC$2*$AD$2*$AE$2+('Demand Base Matrix'!J$3+'Demand Base Matrix'!J$4)*$W$2*$AD$2+'Demand Base Matrix'!J$5*$W$2*$AD$2*$AE$2+'Demand Base Matrix'!J$7+'Demand Base Matrix'!J$8*$AF$2),IF($C17="Integrate",(('Demand Base Matrix'!J$28+'Demand Base Matrix'!J$32)*$AC$2*$AD$2*$AE$2+('Demand Base Matrix'!J$29+'Demand Base Matrix'!J$30)*$W$2*$AD$2+'Demand Base Matrix'!J$31*$W$2*$AD$2*$AE$2+'Demand Base Matrix'!J$33+'Demand Base Matrix'!J$34*$AF$2),IF($C17="Bond",(('Demand Base Matrix'!J$55+'Demand Base Matrix'!J$59)*$AC$2*$AD$2*$AE$2+('Demand Base Matrix'!J$56+'Demand Base Matrix'!J$57)*$W$2*$AD$2+'Demand Base Matrix'!J$58*$W$2*$AD$2*$AE$2+'Demand Base Matrix'!J$60+'Demand Base Matrix'!J$61*$AF$2),IF($C17="Explore",('Demand Base Matrix'!J$82*$AC$2*$AD$2*$AE$2*$AF$2+'Demand Base Matrix'!J$83*$W$2*$AC$2*$AD$2*$AE$2*$AF$2+'Demand Base Matrix'!J$84))))) -> 4
A18: [2026 SaaS Y2] City of Oak Ridge | B18: City of Oak Ridge | C18: Bond | D18: Stefanie Naden | E18: Shashank Sharma | F18: Satyam Kumar | I18: =IFERROR(INDEX('Customer 360'!F:F,MATCH(B18,'Customer 360'!A:A,0)),"-") -> D | J18: 260 | L18: 46259 | M18: 46259 | N18: 2026 | O18: 46023 | P18: IVMS | Q18: =O18 -> 46023 | R18: =IFERROR(IF(M18<>"",M18,IF(L18<>"",L18,INDEX('CSM RDD'!B:B,MATCH(B18,'CSM RDD'!A:A,0)))),"-") -> 46259 | S18: =IFERROR(EOMONTH(Q18,-1)+1,"") -> 46023 | T18: =IFERROR(EOMONTH(R18,-1)+1,"") -> 46235 | U18: =J18+K18 -> 260 | V18: =IF(C18<>"Validate",DATE(2026,3,1),O18) -> 46082 | W18: =IF(U18=0,1,IF(U18<='Demand Base Matrix'!$K$3,'Demand Base Matrix'!$L$3,IF(U18<='Demand Base Matrix'!$K$4,'Demand Base Matrix'!$L$4,IF(U18<='Demand Base Matrix'!$K$5,'Demand Base Matrix'!$L$5,IF(U18<='Demand Base Matrix'!$K$6,'Demand Base Matrix'!$L$6,IF(U18<='Demand Base Matrix'!$K$7,'Demand Base Matrix'!$L$7)))))) -> 0.75 | X18: =DATE(YEAR(R18),MONTH(R18),1) -> 46235 | Y18: =IF(K18>0,"Tx","Dx") -> Dx | Z18: Low | AA18: Low | AB18: Low | AC18: =IFERROR(INDEX('Demand Base Matrix'!AM:AM,MATCH(Y18,'Demand Base Matrix'!AL:AL,0)),"-") -> 1 | AD18: =IFERROR(INDEX('Demand Base Matrix'!AO:AO,MATCH(Z18,'Demand Base Matrix'!AN:AN,0)),1) -> 1 | AE18: =IFERROR(INDEX('Demand Base Matrix'!AQ:AQ,MATCH(AA18,'Demand Base Matrix'!AP:AP,0)),1) -> 1 | AF18: =IFERROR(INDEX('Demand Base Matrix'!AS:AS,MATCH(AB18,'Demand Base Matrix'!AR:AR,0)),1) -> 1 | AG18: =IF($C18="Validate",(('Demand Base Matrix'!D$2+'Demand Base Matrix'!D$6)*$AC$2*$AD$2*$AE$2+('Demand Base Matrix'!D$3+'Demand Base Matrix'!D$4)*$W$2*$AD$2+'Demand Base Matrix'!D$5*$W$2*$AD$2*$AE$2+'Demand Base Matrix'!D$7+'Demand Base Matrix'!D$8*$AF$2),IF($C18="Integrate",(('Demand Base Matrix'!D$28+'Demand Base Matrix'!D$32)*$AC$2*$AD$2*$AE$2+('Demand Base Matrix'!D$29+'Demand Base Matrix'!D$30)*$W$2*$AD$2+'Demand Base Matrix'!D$31*$W$2*$AD$2*$AE$2+'Demand Base Matrix'!D$33+'Demand Base Matrix'!D$34*$AF$2),IF($C18="Bond",(('Demand Base Matrix'!D$55+'Demand Base Matrix'!D$59)*$AC$2*$AD$2*$AE$2+('Demand Base Matrix'!D$56+'Demand Base Matrix'!D$57)*$W$2*$AD$2+'Demand Base Matrix'!D$58*$W$2*$AD$2*$AE$2+'Demand Base Matrix'!D$60+'Demand Base Matrix'!D$61*$AF$2),IF($C18="Explore",('Demand Base Matrix'!D$82*$AC$2*$AD$2*$AE$2*$AF$2+'Demand Base Matrix'!D$83*$W$2*$AC$2*$AD$2*$AE$2*$AF$2+'Demand Base Matrix'!D$84))))) -> 10 | AH18: =IF($C18="Validate",(('Demand Base Matrix'!E$2+'Demand Base Matrix'!E$6)*$AC$2*$AD$2*$AE$2+('Demand Base Matrix'!E$3+'Demand Base Matrix'!E$4)*$W$2*$AD$2+'Demand Base Matrix'!E$5*$W$2*$AD$2*$AE$2+'Demand Base Matrix'!E$7+'Demand Base Matrix'!E$8*$AF$2),IF($C18="Integrate",(('Demand Base Matrix'!E$28+'Demand Base Matrix'!E$32)*$AC$2*$AD$2*$AE$2+('Demand Base Matrix'!E$29+'Demand Base Matrix'!E$30)*$W$2*$AD$2+'Demand Base Matrix'!E$31*$W$2*$AD$2*$AE$2+'Demand Base Matrix'!E$33+'Demand Base Matrix'!E$34*$AF$2),IF($C18="Bond",(('Demand Base Matrix'!E$55+'Demand Base Matrix'!E$59)*$AC$2*$AD$2*$AE$2+('Demand Base Matrix'!E$56+'Demand Base Matrix'!E$57)*$W$2*$AD$2+'Demand Base Matrix'!E$58*$W$2*$AD$2*$AE$2+'Demand Base Matrix'!E$60+'Demand Base Matrix'!E$61*$AF$2),IF($C18="Explore",('Demand Base Matrix'!E$82*$AC$2*$AD$2*$AE$2*$AF$2+'Demand Base Matrix'!E$83*$W$2*$AC$2*$AD$2*$AE$2*$AF$2+'Demand Base Matrix'!E$84))))) -> 10 | AI18: =IF($C18="Validate",(('Demand Base Matrix'!F$2+'Demand Base Matrix'!F$6)*$AC$2*$AD$2*$AE$2+('Demand Base Matrix'!F$3+'Demand Base Matrix'!F$4)*$W$2*$AD$2+'Demand Base Matrix'!F$5*$W$2*$AD$2*$AE$2+'Demand Base Matrix'!F$7+'Demand Base Matrix'!F$8*$AF$2),IF($C18="Integrate",(('Demand Base Matrix'!F$28+'Demand Base Matrix'!F$32)*$AC$2*$AD$2*$AE$2+('Demand Base Matrix'!F$29+'Demand Base Matrix'!F$30)*$W$2*$AD$2+'Demand Base Matrix'!F$31*$W$2*$AD$2*$AE$2+'Demand Base Matrix'!F$33+'Demand Base Matrix'!F$34*$AF$2),IF($C18="Bond",(('Demand Base Matrix'!F$55+'Demand Base Matrix'!F$59)*$AC$2*$AD$2*$AE$2+('Demand Base Matrix'!F$56+'Demand Base Matrix'!F$57)*$W$2*$AD$2+'Demand Base Matrix'!F$58*$W$2*$AD$2*$AE$2+'Demand Base Matrix'!F$60+'Demand Base Matrix'!F$61*$AF$2),IF($C18="Explore",('Demand Base Matrix'!F$82*$AC$2*$AD$2*$AE$2*$AF$2+'Demand Base Matrix'!F$83*$W$2*$AC$2*$AD$2*$AE$2*$AF$2+'Demand Base Matrix'!F$84))))) -> 10 | AJ18: =IF($C18="Validate",(('Demand Base Matrix'!G$2+'Demand Base Matrix'!G$6)*$AC$2*$AD$2*$AE$2+('Demand Base Matrix'!G$3+'Demand Base Matrix'!G$4)*$W$2*$AD$2+'Demand Base Matrix'!G$5*$W$2*$AD$2*$AE$2+'Demand Base Matrix'!G$7+'Demand Base Matrix'!G$8*$AF$2),IF($C18="Integrate",(('Demand Base Matrix'!G$28+'Demand Base Matrix'!G$32)*$AC$2*$AD$2*$AE$2+('Demand Base Matrix'!G$29+'Demand Base Matrix'!G$30)*$W$2*$AD$2+'Demand Base Matrix'!G$31*$W$2*$AD$2*$AE$2+'Demand Base Matrix'!G$33+'Demand Base Matrix'!G$34*$AF$2),IF($C18="Bond",(('Demand Base Matrix'!G$55+'Demand Base Matrix'!G$59)*$AC$2*$AD$2*$AE$2+('Demand Base Matrix'!G$56+'Demand Base Matrix'!G$57)*$W$2*$AD$2+'Demand Base Matrix'!G$58*$W$2*$AD$2*$AE$2+'Demand Base Matrix'!G$60+'Demand Base Matrix'!G$61*$AF$2),IF($C18="Explore",('Demand Base Matrix'!G$82*$AC$2*$AD$2*$AE$2*$AF$2+'Demand Base Matrix'!G$83*$W$2*$AC$2*$AD$2*$AE$2*$AF$2+'Demand Base Matrix'!G$84))))) -> 50 | AK18: =IF($C18="Validate",(('Demand Base Matrix'!H$2+'Demand Base Matrix'!H$6)*$AC$2*$AD$2*$AE$2+('Demand Base Matrix'!H$3+'Demand Base Matrix'!H$4)*$W$2*$AD$2+'Demand Base Matrix'!H$5*$W$2*$AD$2*$AE$2+'Demand Base Matrix'!H$7+'Demand Base Matrix'!H$8*$AF$2),IF($C18="Integrate",(('Demand Base Matrix'!H$28+'Demand Base Matrix'!H$32)*$AC$2*$AD$2*$AE$2+('Demand Base Matrix'!H$29+'Demand Base Matrix'!H$30)*$W$2*$AD$2+'Demand Base Matrix'!H$31*$W$2*$AD$2*$AE$2+'Demand Base Matrix'!H$33+'Demand Base Matrix'!H$34*$AF$2),IF($C18="Bond",(('Demand Base Matrix'!H$55+'Demand Base Matrix'!H$59)*$AC$2*$AD$2*$AE$2+('Demand Base Matrix'!H$56+'Demand Base Matrix'!H$57)*$W$2*$AD$2+'Demand Base Matrix'!H$58*$W$2*$AD$2*$AE$2+'Demand Base Matrix'!H$60+'Demand Base Matrix'!H$61*$AF$2),IF($C18="Explore",('Demand Base Matrix'!H$82*$AC$2*$AD$2*$AE$2*$AF$2+'Demand Base Matrix'!H$83*$W$2*$AC$2*$AD$2*$AE$2*$AF$2+'Demand Base Matrix'!H$84))))) -> 28 | AL18: =IF($C18="Validate",(('Demand Base Matrix'!I$2+'Demand Base Matrix'!I$6)*$AC$2*$AD$2*$AE$2+('Demand Base Matrix'!I$3+'Demand Base Matrix'!I$4)*$W$2*$AD$2+'Demand Base Matrix'!I$5*$W$2*$AD$2*$AE$2+'Demand Base Matrix'!I$7+'Demand Base Matrix'!I$8*$AF$2),IF($C18="Integrate",(('Demand Base Matrix'!I$28+'Demand Base Matrix'!I$32)*$AC$2*$AD$2*$AE$2+('Demand Base Matrix'!I$29+'Demand Base Matrix'!I$30)*$W$2*$AD$2+'Demand Base Matrix'!I$31*$W$2*$AD$2*$AE$2+'Demand Base Matrix'!I$33+'Demand Base Matrix'!I$34*$AF$2),IF($C18="Bond",(('Demand Base Matrix'!I$55+'Demand Base Matrix'!I$59)*$AC$2*$AD$2*$AE$2+('Demand Base Matrix'!I$56+'Demand Base Matrix'!I$57)*$W$2*$AD$2+'Demand Base Matrix'!I$58*$W$2*$AD$2*$AE$2+'Demand Base Matrix'!I$60+'Demand Base Matrix'!I$61*$AF$2),IF($C18="Explore",('Demand Base Matrix'!I$82*$AC$2*$AD$2*$AE$2*$AF$2+'Demand Base Matrix'!I$83*$W$2*$AC$2*$AD$2*$AE$2*$AF$2+'Demand Base Matrix'!I$84))))) -> 8 | AM18: =IF($C18="Validate",(('Demand Base Matrix'!J$2+'Demand Base Matrix'!J$6)*$AC$2*$AD$2*$AE$2+('Demand Base Matrix'!J$3+'Demand Base Matrix'!J$4)*$W$2*$AD$2+'Demand Base Matrix'!J$5*$W$2*$AD$2*$AE$2+'Demand Base Matrix'!J$7+'Demand Base Matrix'!J$8*$AF$2),IF($C18="Integrate",(('Demand Base Matrix'!J$28+'Demand Base Matrix'!J$32)*$AC$2*$AD$2*$AE$2+('Demand Base Matrix'!J$29+'Demand Base Matrix'!J$30)*$W$2*$AD$2+'Demand Base Matrix'!J$31*$W$2*$AD$2*$AE$2+'Demand Base Matrix'!J$33+'Demand Base Matrix'!J$34*$AF$2),IF($C18="Bond",(('Demand Base Matrix'!J$55+'Demand Base Matrix'!J$59)*$AC$2*$AD$2*$AE$2+('Demand Base Matrix'!J$56+'Demand Base Matrix'!J$57)*$W$2*$AD$2+'Demand Base Matrix'!J$58*$W$2*$AD$2*$AE$2+'Demand Base Matrix'!J$60+'Demand Base Matrix'!J$61*$AF$2),IF($C18="Explore",('Demand Base Matrix'!J$82*$AC$2*$AD$2*$AE$2*$AF$2+'Demand Base Matrix'!J$83*$W$2*$AC$2*$AD$2*$AE$2*$AF$2+'Demand Base Matrix'!J$84))))) -> 8
A19: [2026 SaaS Y2] City of Tallahassee, Florida | B19: City of Tallahassee Utilities | C19: Bond | D19: Savannah Peery | E19: Mukul Gupta | F19: Aalimah Showkat | I19: =IFERROR(INDEX('Customer 360'!F:F,MATCH(B19,'Customer 360'!A:A,0)),"-") -> D | J19: 1148 | K19: 283 | L19: 46240 | M19: 46240 | N19: 2026 | O19: 46023 | P19: IVMS | Q19: =O19 -> 46023 | R19: =IFERROR(IF(M19<>"",M19,IF(L19<>"",L19,INDEX('CSM RDD'!B:B,MATCH(B19,'CSM RDD'!A:A,0)))),"-") -> 46240 | S19: =IFERROR(EOMONTH(Q19,-1)+1,"") -> 46023 | T19: =IFERROR(EOMONTH(R19,-1)+1,"") -> 46235 | U19: =J19+K19 -> 1431 | V19: =IF(C19<>"Validate",DATE(2026,3,1),O19) -> 46082 | W19: =IF(U19=0,1,IF(U19<='Demand Base Matrix'!$K$3,'Demand Base Matrix'!$L$3,IF(U19<='Demand Base Matrix'!$K$4,'Demand Base Matrix'!$L$4,IF(U19<='Demand Base Matrix'!$K$5,'Demand Base Matrix'!$L$5,IF(U19<='Demand Base Matrix'!$K$6,'Demand Base Matrix'!$L$6,IF(U19<='Demand Base Matrix'!$K$7,'Demand Base Matrix'!$L$7)))))) -> 1 | X19: =DATE(YEAR(R19),MONTH(R19),1) -> 46235 | Y19: =IF(K19>0,"Tx","Dx") -> Tx | Z19: Low | AA19: Medium | AB19: Low | AC19: =IFERROR(INDEX('Demand Base Matrix'!AM:AM,MATCH(Y19,'Demand Base Matrix'!AL:AL,0)),"-") -> 1.5 | AD19: =IFERROR(INDEX('Demand Base Matrix'!AO:AO,MATCH(Z19,'Demand Base Matrix'!AN:AN,0)),1) -> 1 | AE19: =IFERROR(INDEX('Demand Base Matrix'!AQ:AQ,MATCH(AA19,'Demand Base Matrix'!AP:AP,0)),1) -> 1.5 | AF19: =IFERROR(INDEX('Demand Base Matrix'!AS:AS,MATCH(AB19,'Demand Base Matrix'!AR:AR,0)),1) -> 1 | AG19: =IF($C19="Validate",(('Demand Base Matrix'!D$2+'Demand Base Matrix'!D$6)*$AC$2*$AD$2*$AE$2+('Demand Base Matrix'!D$3+'Demand Base Matrix'!D$4)*$W$2*$AD$2+'Demand Base Matrix'!D$5*$W$2*$AD$2*$AE$2+'Demand Base Matrix'!D$7+'Demand Base Matrix'!D$8*$AF$2),IF($C19="Integrate",(('Demand Base Matrix'!D$28+'Demand Base Matrix'!D$32)*$AC$2*$AD$2*$AE$2+('Demand Base Matrix'!D$29+'Demand Base Matrix'!D$30)*$W$2*$AD$2+'Demand Base Matrix'!D$31*$W$2*$AD$2*$AE$2+'Demand Base Matrix'!D$33+'Demand Base Matrix'!D$34*$AF$2),IF($C19="Bond",(('Demand Base Matrix'!D$55+'Demand Base Matrix'!D$59)*$AC$2*$AD$2*$AE$2+('Demand Base Matrix'!D$56+'Demand Base Matrix'!D$57)*$W$2*$AD$2+'Demand Base Matrix'!D$58*$W$2*$AD$2*$AE$2+'Demand Base Matrix'!D$60+'Demand Base Matrix'!D$61*$AF$2),IF($C19="Explore",('Demand Base Matrix'!D$82*$AC$2*$AD$2*$AE$2*$AF$2+'Demand Base Matrix'!D$83*$W$2*$AC$2*$AD$2*$AE$2*$AF$2+'Demand Base Matrix'!D$84))))) -> 10 | AH19: =IF($C19="Validate",(('Demand Base Matrix'!E$2+'Demand Base Matrix'!E$6)*$AC$2*$AD$2*$AE$2+('Demand Base Matrix'!E$3+'Demand Base Matrix'!E$4)*$W$2*$AD$2+'Demand Base Matrix'!E$5*$W$2*$AD$2*$AE$2+'Demand Base Matrix'!E$7+'Demand Base Matrix'!E$8*$AF$2),IF($C19="Integrate",(('Demand Base Matrix'!E$28+'Demand Base Matrix'!E$32)*$AC$2*$AD$2*$AE$2+('Demand Base Matrix'!E$29+'Demand Base Matrix'!E$30)*$W$2*$AD$2+'Demand Base Matrix'!E$31*$W$2*$AD$2*$AE$2+'Demand Base Matrix'!E$33+'Demand Base Matrix'!E$34*$AF$2),IF($C19="Bond",(('Demand Base Matrix'!E$55+'Demand Base Matrix'!E$59)*$AC$2*$AD$2*$AE$2+('Demand Base Matrix'!E$56+'Demand Base Matrix'!E$57)*$W$2*$AD$2+'Demand Base Matrix'!E$58*$W$2*$AD$2*$AE$2+'Demand Base Matrix'!E$60+'Demand Base Matrix'!E$61*$AF$2),IF($C19="Explore",('Demand Base Matrix'!E$82*$AC$2*$AD$2*$AE$2*$AF$2+'Demand Base Matrix'!E$83*$W$2*$AC$2*$AD$2*$AE$2*$AF$2+'Demand Base Matrix'!E$84))))) -> 10 | AI19: =IF($C19="Validate",(('Demand Base Matrix'!F$2+'Demand Base Matrix'!F$6)*$AC$2*$AD$2*$AE$2+('Demand Base Matrix'!F$3+'Demand Base Matrix'!F$4)*$W$2*$AD$2+'Demand Base Matrix'!F$5*$W$2*$AD$2*$AE$2+'Demand Base Matrix'!F$7+'Demand Base Matrix'!F$8*$AF$2),IF($C19="Integrate",(('Demand Base Matrix'!F$28+'Demand Base Matrix'!F$32)*$AC$2*$AD$2*$AE$2+('Demand Base Matrix'!F$29+'Demand Base Matrix'!F$30)*$W$2*$AD$2+'Demand Base Matrix'!F$31*$W$2*$AD$2*$AE$2+'Demand Base Matrix'!F$33+'Demand Base Matrix'!F$34*$AF$2),IF($C19="Bond",(('Demand Base Matrix'!F$55+'Demand Base Matrix'!F$59)*$AC$2*$AD$2*$AE$2+('Demand Base Matrix'!F$56+'Demand Base Matrix'!F$57)*$W$2*$AD$2+'Demand Base Matrix'!F$58*$W$2*$AD$2*$AE$2+'Demand Base Matrix'!F$60+'Demand Base Matrix'!F$61*$AF$2),IF($C19="Explore",('Demand Base Matrix'!F$82*$AC$2*$AD$2*$AE$2*$AF$2+'Demand Base Matrix'!F$83*$W$2*$AC$2*$AD$2*$AE$2*$AF$2+'Demand Base Matrix'!F$84))))) -> 10 | AJ19: =IF($C19="Validate",(('Demand Base Matrix'!G$2+'Demand Base Matrix'!G$6)*$AC$2*$AD$2*$AE$2+('Demand Base Matrix'!G$3+'Demand Base Matrix'!G$4)*$W$2*$AD$2+'Demand Base Matrix'!G$5*$W$2*$AD$2*$AE$2+'Demand Base Matrix'!G$7+'Demand Base Matrix'!G$8*$AF$2),IF($C19="Integrate",(('Demand Base Matrix'!G$28+'Demand Base Matrix'!G$32)*$AC$2*$AD$2*$AE$2+('Demand Base Matrix'!G$29+'Demand Base Matrix'!G$30)*$W$2*$AD$2+'Demand Base Matrix'!G$31*$W$2*$AD$2*$AE$2+'Demand Base Matrix'!G$33+'Demand Base Matrix'!G$34*$AF$2),IF($C19="Bond",(('Demand Base Matrix'!G$55+'Demand Base Matrix'!G$59)*$AC$2*$AD$2*$AE$2+('Demand Base Matrix'!G$56+'Demand Base Matrix'!G$57)*$W$2*$AD$2+'Demand Base Matrix'!G$58*$W$2*$AD$2*$AE$2+'Demand Base Matrix'!G$60+'Demand Base Matrix'!G$61*$AF$2),IF($C19="Explore",('Demand Base Matrix'!G$82*$AC$2*$AD$2*$AE$2*$AF$2+'Demand Base Matrix'!G$83*$W$2*$AC$2*$AD$2*$AE$2*$AF$2+'Demand Base Matrix'!G$84))))) -> 50 | AK19: =IF($C19="Validate",(('Demand Base Matrix'!H$2+'Demand Base Matrix'!H$6)*$AC$2*$AD$2*$AE$2+('Demand Base Matrix'!H$3+'Demand Base Matrix'!H$4)*$W$2*$AD$2+'Demand Base Matrix'!H$5*$W$2*$AD$2*$AE$2+'Demand Base Matrix'!H$7+'Demand Base Matrix'!H$8*$AF$2),IF($C19="Integrate",(('Demand Base Matrix'!H$28+'Demand Base Matrix'!H$32)*$AC$2*$AD$2*$AE$2+('Demand Base Matrix'!H$29+'Demand Base Matrix'!H$30)*$W$2*$AD$2+'Demand Base Matrix'!H$31*$W$2*$AD$2*$AE$2+'Demand Base Matrix'!H$33+'Demand Base Matrix'!H$34*$AF$2),IF($C19="Bond",(('Demand Base Matrix'!H$55+'Demand Base Matrix'!H$59)*$AC$2*$AD$2*$AE$2+('Demand Base Matrix'!H$56+'Demand Base Matrix'!H$57)*$W$2*$AD$2+'Demand Base Matrix'!H$58*$W$2*$AD$2*$AE$2+'Demand Base Matrix'!H$60+'Demand Base Matrix'!H$61*$AF$2),IF($C19="Explore",('Demand Base Matrix'!H$82*$AC$2*$AD$2*$AE$2*$AF$2+'Demand Base Matrix'!H$83*$W$2*$AC$2*$AD$2*$AE$2*$AF$2+'Demand Base Matrix'!H$84))))) -> 28 | AL19: =IF($C19="Validate",(('Demand Base Matrix'!I$2+'Demand Base Matrix'!I$6)*$AC$2*$AD$2*$AE$2+('Demand Base Matrix'!I$3+'Demand Base Matrix'!I$4)*$W$2*$AD$2+'Demand Base Matrix'!I$5*$W$2*$AD$2*$AE$2+'Demand Base Matrix'!I$7+'Demand Base Matrix'!I$8*$AF$2),IF($C19="Integrate",(('Demand Base Matrix'!I$28+'Demand Base Matrix'!I$32)*$AC$2*$AD$2*$AE$2+('Demand Base Matrix'!I$29+'Demand Base Matrix'!I$30)*$W$2*$AD$2+'Demand Base Matrix'!I$31*$W$2*$AD$2*$AE$2+'Demand Base Matrix'!I$33+'Demand Base Matrix'!I$34*$AF$2),IF($C19="Bond",(('Demand Base Matrix'!I$55+'Demand Base Matrix'!I$59)*$AC$2*$AD$2*$AE$2+('Demand Base Matrix'!I$56+'Demand Base Matrix'!I$57)*$W$2*$AD$2+'Demand Base Matrix'!I$58*$W$2*$AD$2*$AE$2+'Demand Base Matrix'!I$60+'Demand Base Matrix'!I$61*$AF$2),IF($C19="Explore",('Demand Base Matrix'!I$82*$AC$2*$AD$2*$AE$2*$AF$2+'Demand Base Matrix'!I$83*$W$2*$AC$2*$AD$2*$AE$2*$AF$2+'Demand Base Matrix'!I$84))))) -> 8 | AM19: =IF($C19="Validate",(('Demand Base Matrix'!J$2+'Demand Base Matrix'!J$6)*$AC$2*$AD$2*$AE$2+('Demand Base Matrix'!J$3+'Demand Base Matrix'!J$4)*$W$2*$AD$2+'Demand Base Matrix'!J$5*$W$2*$AD$2*$AE$2+'Demand Base Matrix'!J$7+'Demand Base Matrix'!J$8*$AF$2),IF($C19="Integrate",(('Demand Base Matrix'!J$28+'Demand Base Matrix'!J$32)*$AC$2*$AD$2*$AE$2+('Demand Base Matrix'!J$29+'Demand Base Matrix'!J$30)*$W$2*$AD$2+'Demand Base Matrix'!J$31*$W$2*$AD$2*$AE$2+'Demand Base Matrix'!J$33+'Demand Base Matrix'!J$34*$AF$2),IF($C19="Bond",(('Demand Base Matrix'!J$55+'Demand Base Matrix'!J$59)*$AC$2*$AD$2*$AE$2+('Demand Base Matrix'!J$56+'Demand Base Matrix'!J$57)*$W$2*$AD$2+'Demand Base Matrix'!J$58*$W$2*$AD$2*$AE$2+'Demand Base Matrix'!J$60+'Demand Base Matrix'!J$61*$AF$2),IF($C19="Explore",('Demand Base Matrix'!J$82*$AC$2*$AD$2*$AE$2*$AF$2+'Demand Base Matrix'!J$83*$W$2*$AC$2*$AD$2*$AE$2*$AF$2+'Demand Base Matrix'!J$84))))) -> 8
A20: [2026 SaaS Y3] Clearwater Power | B20: Clearwater Power Company | C20: Bond | D20: Grant Lee | E20: Shashank Sharma | F20: Nitish Ranjan | I20: =IFERROR(INDEX('Customer 360'!F:F,MATCH(B20,'Customer 360'!A:A,0)),"-") -> C | J20: 2002 | L20: 46280 | M20: 46280 | N20: 2026 | O20: 46023 | P20: IVMS | Q20: =O20 -> 46023 | R20: =IFERROR(IF(M20<>"",M20,IF(L20<>"",L20,INDEX('CSM RDD'!B:B,MATCH(B20,'CSM RDD'!A:A,0)))),"-") -> 46280 | S20: =IFERROR(EOMONTH(Q20,-1)+1,"") -> 46023 | T20: =IFERROR(EOMONTH(R20,-1)+1,"") -> 46266 | U20: =J20+K20 -> 2002 | V20: =IF(C20<>"Validate",DATE(2026,3,1),O20) -> 46082 | W20: =IF(U20=0,1,IF(U20<='Demand Base Matrix'!$K$3,'Demand Base Matrix'!$L$3,IF(U20<='Demand Base Matrix'!$K$4,'Demand Base Matrix'!$L$4,IF(U20<='Demand Base Matrix'!$K$5,'Demand Base Matrix'!$L$5,IF(U20<='Demand Base Matrix'!$K$6,'Demand Base Matrix'!$L$6,IF(U20<='Demand Base Matrix'!$K$7,'Demand Base Matrix'!$L$7)))))) -> 1 | X20: =DATE(YEAR(R20),MONTH(R20),1) -> 46266 | Y20: =IF(K20>0,"Tx","Dx") -> Dx | Z20: Low | AA20: Low | AB20: Low | AC20: =IFERROR(INDEX('Demand Base Matrix'!AM:AM,MATCH(Y20,'Demand Base Matrix'!AL:AL,0)),"-") -> 1 | AD20: =IFERROR(INDEX('Demand Base Matrix'!AO:AO,MATCH(Z20,'Demand Base Matrix'!AN:AN,0)),1) -> 1 | AE20: =IFERROR(INDEX('Demand Base Matrix'!AQ:AQ,MATCH(AA20,'Demand Base Matrix'!AP:AP,0)),1) -> 1 | AF20: =IFERROR(INDEX('Demand Base Matrix'!AS:AS,MATCH(AB20,'Demand Base Matrix'!AR:AR,0)),1) -> 1 | AG20: =IF($C20="Validate",(('Demand Base Matrix'!D$2+'Demand Base Matrix'!D$6)*$AC$2*$AD$2*$AE$2+('Demand Base Matrix'!D$3+'Demand Base Matrix'!D$4)*$W$2*$AD$2+'Demand Base Matrix'!D$5*$W$2*$AD$2*$AE$2+'Demand Base Matrix'!D$7+'Demand Base Matrix'!D$8*$AF$2),IF($C20="Integrate",(('Demand Base Matrix'!D$28+'Demand Base Matrix'!D$32)*$AC$2*$AD$2*$AE$2+('Demand Base Matrix'!D$29+'Demand Base Matrix'!D$30)*$W$2*$AD$2+'Demand Base Matrix'!D$31*$W$2*$AD$2*$AE$2+'Demand Base Matrix'!D$33+'Demand Base Matrix'!D$34*$AF$2),IF($C20="Bond",(('Demand Base Matrix'!D$55+'Demand Base Matrix'!D$59)*$AC$2*$AD$2*$AE$2+('Demand Base Matrix'!D$56+'Demand Base Matrix'!D$57)*$W$2*$AD$2+'Demand Base Matrix'!D$58*$W$2*$AD$2*$AE$2+'Demand Base Matrix'!D$60+'Demand Base Matrix'!D$61*$AF$2),IF($C20="Explore",('Demand Base Matrix'!D$82*$AC$2*$AD$2*$AE$2*$AF$2+'Demand Base Matrix'!D$83*$W$2*$AC$2*$AD$2*$AE$2*$AF$2+'Demand Base Matrix'!D$84))))) -> 10 | AH20: =IF($C20="Validate",(('Demand Base Matrix'!E$2+'Demand Base Matrix'!E$6)*$AC$2*$AD$2*$AE$2+('Demand Base Matrix'!E$3+'Demand Base Matrix'!E$4)*$W$2*$AD$2+'Demand Base Matrix'!E$5*$W$2*$AD$2*$AE$2+'Demand Base Matrix'!E$7+'Demand Base Matrix'!E$8*$AF$2),IF($C20="Integrate",(('Demand Base Matrix'!E$28+'Demand Base Matrix'!E$32)*$AC$2*$AD$2*$AE$2+('Demand Base Matrix'!E$29+'Demand Base Matrix'!E$30)*$W$2*$AD$2+'Demand Base Matrix'!E$31*$W$2*$AD$2*$AE$2+'Demand Base Matrix'!E$33+'Demand Base Matrix'!E$34*$AF$2),IF($C20="Bond",(('Demand Base Matrix'!E$55+'Demand Base Matrix'!E$59)*$AC$2*$AD$2*$AE$2+('Demand Base Matrix'!E$56+'Demand Base Matrix'!E$57)*$W$2*$AD$2+'Demand Base Matrix'!E$58*$W$2*$AD$2*$AE$2+'Demand Base Matrix'!E$60+'Demand Base Matrix'!E$61*$AF$2),IF($C20="Explore",('Demand Base Matrix'!E$82*$AC$2*$AD$2*$AE$2*$AF$2+'Demand Base Matrix'!E$83*$W$2*$AC$2*$AD$2*$AE$2*$AF$2+'Demand Base Matrix'!E$84))))) -> 10 | AI20: =IF($C20="Validate",(('Demand Base Matrix'!F$2+'Demand Base Matrix'!F$6)*$AC$2*$AD$2*$AE$2+('Demand Base Matrix'!F$3+'Demand Base Matrix'!F$4)*$W$2*$AD$2+'Demand Base Matrix'!F$5*$W$2*$AD$2*$AE$2+'Demand Base Matrix'!F$7+'Demand Base Matrix'!F$8*$AF$2),IF($C20="Integrate",(('Demand Base Matrix'!F$28+'Demand Base Matrix'!F$32)*$AC$2*$AD$2*$AE$2+('Demand Base Matrix'!F$29+'Demand Base Matrix'!F$30)*$W$2*$AD$2+'Demand Base Matrix'!F$31*$W$2*$AD$2*$AE$2+'Demand Base Matrix'!F$33+'Demand Base Matrix'!F$34*$AF$2),IF($C20="Bond",(('Demand Base Matrix'!F$55+'Demand Base Matrix'!F$59)*$AC$2*$AD$2*$AE$2+('Demand Base Matrix'!F$56+'Demand Base Matrix'!F$57)*$W$2*$AD$2+'Demand Base Matrix'!F$58*$W$2*$AD$2*$AE$2+'Demand Base Matrix'!F$60+'Demand Base Matrix'!F$61*$AF$2),IF($C20="Explore",('Demand Base Matrix'!F$82*$AC$2*$AD$2*$AE$2*$AF$2+'Demand Base Matrix'!F$83*$W$2*$AC$2*$AD$2*$AE$2*$AF$2+'Demand Base Matrix'!F$84))))) -> 10 | AJ20: =IF($C20="Validate",(('Demand Base Matrix'!G$2+'Demand Base Matrix'!G$6)*$AC$2*$AD$2*$AE$2+('Demand Base Matrix'!G$3+'Demand Base Matrix'!G$4)*$W$2*$AD$2+'Demand Base Matrix'!G$5*$W$2*$AD$2*$AE$2+'Demand Base Matrix'!G$7+'Demand Base Matrix'!G$8*$AF$2),IF($C20="Integrate",(('Demand Base Matrix'!G$28+'Demand Base Matrix'!G$32)*$AC$2*$AD$2*$AE$2+('Demand Base Matrix'!G$29+'Demand Base Matrix'!G$30)*$W$2*$AD$2+'Demand Base Matrix'!G$31*$W$2*$AD$2*$AE$2+'Demand Base Matrix'!G$33+'Demand Base Matrix'!G$34*$AF$2),IF($C20="Bond",(('Demand Base Matrix'!G$55+'Demand Base Matrix'!G$59)*$AC$2*$AD$2*$AE$2+('Demand Base Matrix'!G$56+'Demand Base Matrix'!G$57)*$W$2*$AD$2+'Demand Base Matrix'!G$58*$W$2*$AD$2*$AE$2+'Demand Base Matrix'!G$60+'Demand Base Matrix'!G$61*$AF$2),IF($C20="Explore",('Demand Base Matrix'!G$82*$AC$2*$AD$2*$AE$2*$AF$2+'Demand Base Matrix'!G$83*$W$2*$AC$2*$AD$2*$AE$2*$AF$2+'Demand Base Matrix'!G$84))))) -> 50 | AK20: =IF($C20="Validate",(('Demand Base Matrix'!H$2+'Demand Base Matrix'!H$6)*$AC$2*$AD$2*$AE$2+('Demand Base Matrix'!H$3+'Demand Base Matrix'!H$4)*$W$2*$AD$2+'Demand Base Matrix'!H$5*$W$2*$AD$2*$AE$2+'Demand Base Matrix'!H$7+'Demand Base Matrix'!H$8*$AF$2),IF($C20="Integrate",(('Demand Base Matrix'!H$28+'Demand Base Matrix'!H$32)*$AC$2*$AD$2*$AE$2+('Demand Base Matrix'!H$29+'Demand Base Matrix'!H$30)*$W$2*$AD$2+'Demand Base Matrix'!H$31*$W$2*$AD$2*$AE$2+'Demand Base Matrix'!H$33+'Demand Base Matrix'!H$34*$AF$2),IF($C20="Bond",(('Demand Base Matrix'!H$55+'Demand Base Matrix'!H$59)*$AC$2*$AD$2*$AE$2+('Demand Base Matrix'!H$56+'Demand Base Matrix'!H$57)*$W$2*$AD$2+'Demand Base Matrix'!H$58*$W$2*$AD$2*$AE$2+'Demand Base Matrix'!H$60+'Demand Base Matrix'!H$61*$AF$2),IF($C20="Explore",('Demand Base Matrix'!H$82*$AC$2*$AD$2*$AE$2*$AF$2+'Demand Base Matrix'!H$83*$W$2*$AC$2*$AD$2*$AE$2*$AF$2+'Demand Base Matrix'!H$84))))) -> 28 | AL20: =IF($C20="Validate",(('Demand Base Matrix'!I$2+'Demand Base Matrix'!I$6)*$AC$2*$AD$2*$AE$2+('Demand Base Matrix'!I$3+'Demand Base Matrix'!I$4)*$W$2*$AD$2+'Demand Base Matrix'!I$5*$W$2*$AD$2*$AE$2+'Demand Base Matrix'!I$7+'Demand Base Matrix'!I$8*$AF$2),IF($C20="Integrate",(('Demand Base Matrix'!I$28+'Demand Base Matrix'!I$32)*$AC$2*$AD$2*$AE$2+('Demand Base Matrix'!I$29+'Demand Base Matrix'!I$30)*$W$2*$AD$2+'Demand Base Matrix'!I$31*$W$2*$AD$2*$AE$2+'Demand Base Matrix'!I$33+'Demand Base Matrix'!I$34*$AF$2),IF($C20="Bond",(('Demand Base Matrix'!I$55+'Demand Base Matrix'!I$59)*$AC$2*$AD$2*$AE$2+('Demand Base Matrix'!I$56+'Demand Base Matrix'!I$57)*$W$2*$AD$2+'Demand Base Matrix'!I$58*$W$2*$AD$2*$AE$2+'Demand Base Matrix'!I$60+'Demand Base Matrix'!I$61*$AF$2),IF($C20="Explore",('Demand Base Matrix'!I$82*$AC$2*$AD$2*$AE$2*$AF$2+'Demand Base Matrix'!I$83*$W$2*$AC$2*$AD$2*$AE$2*$AF$2+'Demand Base Matrix'!I$84))))) -> 8 | AM20: =IF($C20="Validate",(('Demand Base Matrix'!J$2+'Demand Base Matrix'!J$6)*$AC$2*$AD$2*$AE$2+('Demand Base Matrix'!J$3+'Demand Base Matrix'!J$4)*$W$2*$AD$2+'Demand Base Matrix'!J$5*$W$2*$AD$2*$AE$2+'Demand Base Matrix'!J$7+'Demand Base Matrix'!J$8*$AF$2),IF($C20="Integrate",(('Demand Base Matrix'!J$28+'Demand Base Matrix'!J$32)*$AC$2*$AD$2*$AE$2+('Demand Base Matrix'!J$29+'Demand Base Matrix'!J$30)*$W$2*$AD$2+'Demand Base Matrix'!J$31*$W$2*$AD$2*$AE$2+'Demand Base Matrix'!J$33+'Demand Base Matrix'!J$34*$AF$2),IF($C20="Bond",(('Demand Base Matrix'!J$55+'Demand Base Matrix'!J$59)*$AC$2*$AD$2*$AE$2+('Demand Base Matrix'!J$56+'Demand Base Matrix'!J$57)*$W$2*$AD$2+'Demand Base Matrix'!J$58*$W$2*$AD$2*$AE$2+'Demand Base Matrix'!J$60+'Demand Base Matrix'!J$61*$AF$2),IF($C20="Explore",('Demand Base Matrix'!J$82*$AC$2*$AD$2*$AE$2*$AF$2+'Demand Base Matrix'!J$83*$W$2*$AC$2*$AD$2*$AE$2*$AF$2+'Demand Base Matrix'!J$84))))) -> 8
A21: [2026 SaaS Y2] CoMo Electric | B21: Co-Mo Electric Cooperative | C21: Bond | D21: Stefanie Naden | E21: Shashank Sharma | F21: Piyush Kumar Pandey | I21: =IFERROR(INDEX('Customer 360'!F:F,MATCH(B21,'Customer 360'!A:A,0)),"-") -> D | J21: 3580 | L21: 46265 | M21: 46265 | N21: 2026 | O21: 46023 | P21: IVMS | Q21: =O21 -> 46023 | R21: =IFERROR(IF(M21<>"",M21,IF(L21<>"",L21,INDEX('CSM RDD'!B:B,MATCH(B21,'CSM RDD'!A:A,0)))),"-") -> 46265 | S21: =IFERROR(EOMONTH(Q21,-1)+1,"") -> 46023 | T21: =IFERROR(EOMONTH(R21,-1)+1,"") -> 46235 | U21: =J21+K21 -> 3580 | V21: =IF(C21<>"Validate",DATE(2026,3,1),O21) -> 46082 | W21: =IF(U21=0,1,IF(U21<='Demand Base Matrix'!$K$3,'Demand Base Matrix'!$L$3,IF(U21<='Demand Base Matrix'!$K$4,'Demand Base Matrix'!$L$4,IF(U21<='Demand Base Matrix'!$K$5,'Demand Base Matrix'!$L$5,IF(U21<='Demand Base Matrix'!$K$6,'Demand Base Matrix'!$L$6,IF(U21<='Demand Base Matrix'!$K$7,'Demand Base Matrix'!$L$7)))))) -> 1 | X21: =DATE(YEAR(R21),MONTH(R21),1) -> 46235 | Y21: =IF(K21>0,"Tx","Dx") -> Dx | Z21: Low | AA21: Low | AB21: Low | AC21: =IFERROR(INDEX('Demand Base Matrix'!AM:AM,MATCH(Y21,'Demand Base Matrix'!AL:AL,0)),"-") -> 1 | AD21: =IFERROR(INDEX('Demand Base Matrix'!AO:AO,MATCH(Z21,'Demand Base Matrix'!AN:AN,0)),1) -> 1 | AE21: =IFERROR(INDEX('Demand Base Matrix'!AQ:AQ,MATCH(AA21,'Demand Base Matrix'!AP:AP,0)),1) -> 1 | AF21: =IFERROR(INDEX('Demand Base Matrix'!AS:AS,MATCH(AB21,'Demand Base Matrix'!AR:AR,0)),1) -> 1 | AG21: =IF($C21="Validate",(('Demand Base Matrix'!D$2+'Demand Base Matrix'!D$6)*$AC$2*$AD$2*$AE$2+('Demand Base Matrix'!D$3+'Demand Base Matrix'!D$4)*$W$2*$AD$2+'Demand Base Matrix'!D$5*$W$2*$AD$2*$AE$2+'Demand Base Matrix'!D$7+'Demand Base Matrix'!D$8*$AF$2),IF($C21="Integrate",(('Demand Base Matrix'!D$28+'Demand Base Matrix'!D$32)*$AC$2*$AD$2*$AE$2+('Demand Base Matrix'!D$29+'Demand Base Matrix'!D$30)*$W$2*$AD$2+'Demand Base Matrix'!D$31*$W$2*$AD$2*$AE$2+'Demand Base Matrix'!D$33+'Demand Base Matrix'!D$34*$AF$2),IF($C21="Bond",(('Demand Base Matrix'!D$55+'Demand Base Matrix'!D$59)*$AC$2*$AD$2*$AE$2+('Demand Base Matrix'!D$56+'Demand Base Matrix'!D$57)*$W$2*$AD$2+'Demand Base Matrix'!D$58*$W$2*$AD$2*$AE$2+'Demand Base Matrix'!D$60+'Demand Base Matrix'!D$61*$AF$2),IF($C21="Explore",('Demand Base Matrix'!D$82*$AC$2*$AD$2*$AE$2*$AF$2+'Demand Base Matrix'!D$83*$W$2*$AC$2*$AD$2*$AE$2*$AF$2+'Demand Base Matrix'!D$84))))) -> 10 | AH21: =IF($C21="Validate",(('Demand Base Matrix'!E$2+'Demand Base Matrix'!E$6)*$AC$2*$AD$2*$AE$2+('Demand Base Matrix'!E$3+'Demand Base Matrix'!E$4)*$W$2*$AD$2+'Demand Base Matrix'!E$5*$W$2*$AD$2*$AE$2+'Demand Base Matrix'!E$7+'Demand Base Matrix'!E$8*$AF$2),IF($C21="Integrate",(('Demand Base Matrix'!E$28+'Demand Base Matrix'!E$32)*$AC$2*$AD$2*$AE$2+('Demand Base Matrix'!E$29+'Demand Base Matrix'!E$30)*$W$2*$AD$2+'Demand Base Matrix'!E$31*$W$2*$AD$2*$AE$2+'Demand Base Matrix'!E$33+'Demand Base Matrix'!E$34*$AF$2),IF($C21="Bond",(('Demand Base Matrix'!E$55+'Demand Base Matrix'!E$59)*$AC$2*$AD$2*$AE$2+('Demand Base Matrix'!E$56+'Demand Base Matrix'!E$57)*$W$2*$AD$2+'Demand Base Matrix'!E$58*$W$2*$AD$2*$AE$2+'Demand Base Matrix'!E$60+'Demand Base Matrix'!E$61*$AF$2),IF($C21="Explore",('Demand Base Matrix'!E$82*$AC$2*$AD$2*$AE$2*$AF$2+'Demand Base Matrix'!E$83*$W$2*$AC$2*$AD$2*$AE$2*$AF$2+'Demand Base Matrix'!E$84))))) -> 10 | AI21: =IF($C21="Validate",(('Demand Base Matrix'!F$2+'Demand Base Matrix'!F$6)*$AC$2*$AD$2*$AE$2+('Demand Base Matrix'!F$3+'Demand Base Matrix'!F$4)*$W$2*$AD$2+'Demand Base Matrix'!F$5*$W$2*$AD$2*$AE$2+'Demand Base Matrix'!F$7+'Demand Base Matrix'!F$8*$AF$2),IF($C21="Integrate",(('Demand Base Matrix'!F$28+'Demand Base Matrix'!F$32)*$AC$2*$AD$2*$AE$2+('Demand Base Matrix'!F$29+'Demand Base Matrix'!F$30)*$W$2*$AD$2+'Demand Base Matrix'!F$31*$W$2*$AD$2*$AE$2+'Demand Base Matrix'!F$33+'Demand Base Matrix'!F$34*$AF$2),IF($C21="Bond",(('Demand Base Matrix'!F$55+'Demand Base Matrix'!F$59)*$AC$2*$AD$2*$AE$2+('Demand Base Matrix'!F$56+'Demand Base Matrix'!F$57)*$W$2*$AD$2+'Demand Base Matrix'!F$58*$W$2*$AD$2*$AE$2+'Demand Base Matrix'!F$60+'Demand Base Matrix'!F$61*$AF$2),IF($C21="Explore",('Demand Base Matrix'!F$82*$AC$2*$AD$2*$AE$2*$AF$2+'Demand Base Matrix'!F$83*$W$2*$AC$2*$AD$2*$AE$2*$AF$2+'Demand Base Matrix'!F$84))))) -> 10 | AJ21: =IF($C21="Validate",(('Demand Base Matrix'!G$2+'Demand Base Matrix'!G$6)*$AC$2*$AD$2*$AE$2+('Demand Base Matrix'!G$3+'Demand Base Matrix'!G$4)*$W$2*$AD$2+'Demand Base Matrix'!G$5*$W$2*$AD$2*$AE$2+'Demand Base Matrix'!G$7+'Demand Base Matrix'!G$8*$AF$2),IF($C21="Integrate",(('Demand Base Matrix'!G$28+'Demand Base Matrix'!G$32)*$AC$2*$AD$2*$AE$2+('Demand Base Matrix'!G$29+'Demand Base Matrix'!G$30)*$W$2*$AD$2+'Demand Base Matrix'!G$31*$W$2*$AD$2*$AE$2+'Demand Base Matrix'!G$33+'Demand Base Matrix'!G$34*$AF$2),IF($C21="Bond",(('Demand Base Matrix'!G$55+'Demand Base Matrix'!G$59)*$AC$2*$AD$2*$AE$2+('Demand Base Matrix'!G$56+'Demand Base Matrix'!G$57)*$W$2*$AD$2+'Demand Base Matrix'!G$58*$W$2*$AD$2*$AE$2+'Demand Base Matrix'!G$60+'Demand Base Matrix'!G$61*$AF$2),IF($C21="Explore",('Demand Base Matrix'!G$82*$AC$2*$AD$2*$AE$2*$AF$2+'Demand Base Matrix'!G$83*$W$2*$AC$2*$AD$2*$AE$2*$AF$2+'Demand Base Matrix'!G$84))))) -> 50 | AK21: =IF($C21="Validate",(('Demand Base Matrix'!H$2+'Demand Base Matrix'!H$6)*$AC$2*$AD$2*$AE$2+('Demand Base Matrix'!H$3+'Demand Base Matrix'!H$4)*$W$2*$AD$2+'Demand Base Matrix'!H$5*$W$2*$AD$2*$AE$2+'Demand Base Matrix'!H$7+'Demand Base Matrix'!H$8*$AF$2),IF($C21="Integrate",(('Demand Base Matrix'!H$28+'Demand Base Matrix'!H$32)*$AC$2*$AD$2*$AE$2+('Demand Base Matrix'!H$29+'Demand Base Matrix'!H$30)*$W$2*$AD$2+'Demand Base Matrix'!H$31*$W$2*$AD$2*$AE$2+'Demand Base Matrix'!H$33+'Demand Base Matrix'!H$34*$AF$2),IF($C21="Bond",(('Demand Base Matrix'!H$55+'Demand Base Matrix'!H$59)*$AC$2*$AD$2*$AE$2+('Demand Base Matrix'!H$56+'Demand Base Matrix'!H$57)*$W$2*$AD$2+'Demand Base Matrix'!H$58*$W$2*$AD$2*$AE$2+'Demand Base Matrix'!H$60+'Demand Base Matrix'!H$61*$AF$2),IF($C21="Explore",('Demand Base Matrix'!H$82*$AC$2*$AD$2*$AE$2*$AF$2+'Demand Base Matrix'!H$83*$W$2*$AC$2*$AD$2*$AE$2*$AF$2+'Demand Base Matrix'!H$84))))) -> 28 | AL21: =IF($C21="Validate",(('Demand Base Matrix'!I$2+'Demand Base Matrix'!I$6)*$AC$2*$AD$2*$AE$2+('Demand Base Matrix'!I$3+'Demand Base Matrix'!I$4)*$W$2*$AD$2+'Demand Base Matrix'!I$5*$W$2*$AD$2*$AE$2+'Demand Base Matrix'!I$7+'Demand Base Matrix'!I$8*$AF$2),IF($C21="Integrate",(('Demand Base Matrix'!I$28+'Demand Base Matrix'!I$32)*$AC$2*$AD$2*$AE$2+('Demand Base Matrix'!I$29+'Demand Base Matrix'!I$30)*$W$2*$AD$2+'Demand Base Matrix'!I$31*$W$2*$AD$2*$AE$2+'Demand Base Matrix'!I$33+'Demand Base Matrix'!I$34*$AF$2),IF($C21="Bond",(('Demand Base Matrix'!I$55+'Demand Base Matrix'!I$59)*$AC$2*$AD$2*$AE$2+('Demand Base Matrix'!I$56+'Demand Base Matrix'!I$57)*$W$2*$AD$2+'Demand Base Matrix'!I$58*$W$2*$AD$2*$AE$2+'Demand Base Matrix'!I$60+'Demand Base Matrix'!I$61*$AF$2),IF($C21="Explore",('Demand Base Matrix'!I$82*$AC$2*$AD$2*$AE$2*$AF$2+'Demand Base Matrix'!I$83*$W$2*$AC$2*$AD$2*$AE$2*$AF$2+'Demand Base Matrix'!I$84))))) -> 8 | AM21: =IF($C21="Validate",(('Demand Base Matrix'!J$2+'Demand Base Matrix'!J$6)*$AC$2*$AD$2*$AE$2+('Demand Base Matrix'!J$3+'Demand Base Matrix'!J$4)*$W$2*$AD$2+'Demand Base Matrix'!J$5*$W$2*$AD$2*$AE$2+'Demand Base Matrix'!J$7+'Demand Base Matrix'!J$8*$AF$2),IF($C21="Integrate",(('Demand Base Matrix'!J$28+'Demand Base Matrix'!J$32)*$AC$2*$AD$2*$AE$2+('Demand Base Matrix'!J$29+'Demand Base Matrix'!J$30)*$W$2*$AD$2+'Demand Base Matrix'!J$31*$W$2*$AD$2*$AE$2+'Demand Base Matrix'!J$33+'Demand Base Matrix'!J$34*$AF$2),IF($C21="Bond",(('Demand Base Matrix'!J$55+'Demand Base Matrix'!J$59)*$AC$2*$AD$2*$AE$2+('Demand Base Matrix'!J$56+'Demand Base Matrix'!J$57)*$W$2*$AD$2+'Demand Base Matrix'!J$58*$W$2*$AD$2*$AE$2+'Demand Base Matrix'!J$60+'Demand Base Matrix'!J$61*$AF$2),IF($C21="Explore",('Demand Base Matrix'!J$82*$AC$2*$AD$2*$AE$2*$AF$2+'Demand Base Matrix'!J$83*$W$2*$AC$2*$AD$2*$AE$2*$AF$2+'Demand Base Matrix'!J$84))))) -> 8
A22: [2026 SaaS Y1] Continental Divide Electric | B22: Continental Divide Electric Cooperative | C22: Bond | D22: Stefanie Naden | E22: Shashank Sharma | F22: Aakash Agrawal | I22: =IFERROR(INDEX('Customer 360'!F:F,MATCH(B22,'Customer 360'!A:A,0)),"-") -> D | J22: 3200 | L22: 46273 | M22: 46273 | N22: 2026 | O22: 46023 | P22: IVMS | Q22: =O22 -> 46023 | R22: =IFERROR(IF(M22<>"",M22,IF(L22<>"",L22,INDEX('CSM RDD'!B:B,MATCH(B22,'CSM RDD'!A:A,0)))),"-") -> 46273 | S22: =IFERROR(EOMONTH(Q22,-1)+1,"") -> 46023 | T22: =IFERROR(EOMONTH(R22,-1)+1,"") -> 46266 | U22: =J22+K22 -> 3200 | V22: =IF(C22<>"Validate",DATE(2026,3,1),O22) -> 46082 | W22: =IF(U22=0,1,IF(U22<='Demand Base Matrix'!$K$3,'Demand Base Matrix'!$L$3,IF(U22<='Demand Base Matrix'!$K$4,'Demand Base Matrix'!$L$4,IF(U22<='Demand Base Matrix'!$K$5,'Demand Base Matrix'!$L$5,IF(U22<='Demand Base Matrix'!$K$6,'Demand Base Matrix'!$L$6,IF(U22<='Demand Base Matrix'!$K$7,'Demand Base Matrix'!$L$7)))))) -> 1 | X22: =DATE(YEAR(R22),MONTH(R22),1) -> 46266 | Y22: =IF(K22>0,"Tx","Dx") -> Dx | Z22: Low | AA22: Low | AB22: Low | AC22: =IFERROR(INDEX('Demand Base Matrix'!AM:AM,MATCH(Y22,'Demand Base Matrix'!AL:AL,0)),"-") -> 1 | AD22: =IFERROR(INDEX('Demand Base Matrix'!AO:AO,MATCH(Z22,'Demand Base Matrix'!AN:AN,0)),1) -> 1 | AE22: =IFERROR(INDEX('Demand Base Matrix'!AQ:AQ,MATCH(AA22,'Demand Base Matrix'!AP:AP,0)),1) -> 1 | AF22: =IFERROR(INDEX('Demand Base Matrix'!AS:AS,MATCH(AB22,'Demand Base Matrix'!AR:AR,0)),1) -> 1 | AG22: =IF($C22="Validate",(('Demand Base Matrix'!D$2+'Demand Base Matrix'!D$6)*$AC$2*$AD$2*$AE$2+('Demand Base Matrix'!D$3+'Demand Base Matrix'!D$4)*$W$2*$AD$2+'Demand Base Matrix'!D$5*$W$2*$AD$2*$AE$2+'Demand Base Matrix'!D$7+'Demand Base Matrix'!D$8*$AF$2),IF($C22="Integrate",(('Demand Base Matrix'!D$28+'Demand Base Matrix'!D$32)*$AC$2*$AD$2*$AE$2+('Demand Base Matrix'!D$29+'Demand Base Matrix'!D$30)*$W$2*$AD$2+'Demand Base Matrix'!D$31*$W$2*$AD$2*$AE$2+'Demand Base Matrix'!D$33+'Demand Base Matrix'!D$34*$AF$2),IF($C22="Bond",(('Demand Base Matrix'!D$55+'Demand Base Matrix'!D$59)*$AC$2*$AD$2*$AE$2+('Demand Base Matrix'!D$56+'Demand Base Matrix'!D$57)*$W$2*$AD$2+'Demand Base Matrix'!D$58*$W$2*$AD$2*$AE$2+'Demand Base Matrix'!D$60+'Demand Base Matrix'!D$61*$AF$2),IF($C22="Explore",('Demand Base Matrix'!D$82*$AC$2*$AD$2*$AE$2*$AF$2+'Demand Base Matrix'!D$83*$W$2*$AC$2*$AD$2*$AE$2*$AF$2+'Demand Base Matrix'!D$84))))) -> 10 | AH22: =IF($C22="Validate",(('Demand Base Matrix'!E$2+'Demand Base Matrix'!E$6)*$AC$2*$AD$2*$AE$2+('Demand Base Matrix'!E$3+'Demand Base Matrix'!E$4)*$W$2*$AD$2+'Demand Base Matrix'!E$5*$W$2*$AD$2*$AE$2+'Demand Base Matrix'!E$7+'Demand Base Matrix'!E$8*$AF$2),IF($C22="Integrate",(('Demand Base Matrix'!E$28+'Demand Base Matrix'!E$32)*$AC$2*$AD$2*$AE$2+('Demand Base Matrix'!E$29+'Demand Base Matrix'!E$30)*$W$2*$AD$2+'Demand Base Matrix'!E$31*$W$2*$AD$2*$AE$2+'Demand Base Matrix'!E$33+'Demand Base Matrix'!E$34*$AF$2),IF($C22="Bond",(('Demand Base Matrix'!E$55+'Demand Base Matrix'!E$59)*$AC$2*$AD$2*$AE$2+('Demand Base Matrix'!E$56+'Demand Base Matrix'!E$57)*$W$2*$AD$2+'Demand Base Matrix'!E$58*$W$2*$AD$2*$AE$2+'Demand Base Matrix'!E$60+'Demand Base Matrix'!E$61*$AF$2),IF($C22="Explore",('Demand Base Matrix'!E$82*$AC$2*$AD$2*$AE$2*$AF$2+'Demand Base Matrix'!E$83*$W$2*$AC$2*$AD$2*$AE$2*$AF$2+'Demand Base Matrix'!E$84))))) -> 10 | AI22: =IF($C22="Validate",(('Demand Base Matrix'!F$2+'Demand Base Matrix'!F$6)*$AC$2*$AD$2*$AE$2+('Demand Base Matrix'!F$3+'Demand Base Matrix'!F$4)*$W$2*$AD$2+'Demand Base Matrix'!F$5*$W$2*$AD$2*$AE$2+'Demand Base Matrix'!F$7+'Demand Base Matrix'!F$8*$AF$2),IF($C22="Integrate",(('Demand Base Matrix'!F$28+'Demand Base Matrix'!F$32)*$AC$2*$AD$2*$AE$2+('Demand Base Matrix'!F$29+'Demand Base Matrix'!F$30)*$W$2*$AD$2+'Demand Base Matrix'!F$31*$W$2*$AD$2*$AE$2+'Demand Base Matrix'!F$33+'Demand Base Matrix'!F$34*$AF$2),IF($C22="Bond",(('Demand Base Matrix'!F$55+'Demand Base Matrix'!F$59)*$AC$2*$AD$2*$AE$2+('Demand Base Matrix'!F$56+'Demand Base Matrix'!F$57)*$W$2*$AD$2+'Demand Base Matrix'!F$58*$W$2*$AD$2*$AE$2+'Demand Base Matrix'!F$60+'Demand Base Matrix'!F$61*$AF$2),IF($C22="Explore",('Demand Base Matrix'!F$82*$AC$2*$AD$2*$AE$2*$AF$2+'Demand Base Matrix'!F$83*$W$2*$AC$2*$AD$2*$AE$2*$AF$2+'Demand Base Matrix'!F$84))))) -> 10 | AJ22: =IF($C22="Validate",(('Demand Base Matrix'!G$2+'Demand Base Matrix'!G$6)*$AC$2*$AD$2*$AE$2+('Demand Base Matrix'!G$3+'Demand Base Matrix'!G$4)*$W$2*$AD$2+'Demand Base Matrix'!G$5*$W$2*$AD$2*$AE$2+'Demand Base Matrix'!G$7+'Demand Base Matrix'!G$8*$AF$2),IF($C22="Integrate",(('Demand Base Matrix'!G$28+'Demand Base Matrix'!G$32)*$AC$2*$AD$2*$AE$2+('Demand Base Matrix'!G$29+'Demand Base Matrix'!G$30)*$W$2*$AD$2+'Demand Base Matrix'!G$31*$W$2*$AD$2*$AE$2+'Demand Base Matrix'!G$33+'Demand Base Matrix'!G$34*$AF$2),IF($C22="Bond",(('Demand Base Matrix'!G$55+'Demand Base Matrix'!G$59)*$AC$2*$AD$2*$AE$2+('Demand Base Matrix'!G$56+'Demand Base Matrix'!G$57)*$W$2*$AD$2+'Demand Base Matrix'!G$58*$W$2*$AD$2*$AE$2+'Demand Base Matrix'!G$60+'Demand Base Matrix'!G$61*$AF$2),IF($C22="Explore",('Demand Base Matrix'!G$82*$AC$2*$AD$2*$AE$2*$AF$2+'Demand Base Matrix'!G$83*$W$2*$AC$2*$AD$2*$AE$2*$AF$2+'Demand Base Matrix'!G$84))))) -> 50 | AK22: =IF($C22="Validate",(('Demand Base Matrix'!H$2+'Demand Base Matrix'!H$6)*$AC$2*$AD$2*$AE$2+('Demand Base Matrix'!H$3+'Demand Base Matrix'!H$4)*$W$2*$AD$2+'Demand Base Matrix'!H$5*$W$2*$AD$2*$AE$2+'Demand Base Matrix'!H$7+'Demand Base Matrix'!H$8*$AF$2),IF($C22="Integrate",(('Demand Base Matrix'!H$28+'Demand Base Matrix'!H$32)*$AC$2*$AD$2*$AE$2+('Demand Base Matrix'!H$29+'Demand Base Matrix'!H$30)*$W$2*$AD$2+'Demand Base Matrix'!H$31*$W$2*$AD$2*$AE$2+'Demand Base Matrix'!H$33+'Demand Base Matrix'!H$34*$AF$2),IF($C22="Bond",(('Demand Base Matrix'!H$55+'Demand Base Matrix'!H$59)*$AC$2*$AD$2*$AE$2+('Demand Base Matrix'!H$56+'Demand Base Matrix'!H$57)*$W$2*$AD$2+'Demand Base Matrix'!H$58*$W$2*$AD$2*$AE$2+'Demand Base Matrix'!H$60+'Demand Base Matrix'!H$61*$AF$2),IF($C22="Explore",('Demand Base Matrix'!H$82*$AC$2*$AD$2*$AE$2*$AF$2+'Demand Base Matrix'!H$83*$W$2*$AC$2*$AD$2*$AE$2*$AF$2+'Demand Base Matrix'!H$84))))) -> 28 | AL22: =IF($C22="Validate",(('Demand Base Matrix'!I$2+'Demand Base Matrix'!I$6)*$AC$2*$AD$2*$AE$2+('Demand Base Matrix'!I$3+'Demand Base Matrix'!I$4)*$W$2*$AD$2+'Demand Base Matrix'!I$5*$W$2*$AD$2*$AE$2+'Demand Base Matrix'!I$7+'Demand Base Matrix'!I$8*$AF$2),IF($C22="Integrate",(('Demand Base Matrix'!I$28+'Demand Base Matrix'!I$32)*$AC$2*$AD$2*$AE$2+('Demand Base Matrix'!I$29+'Demand Base Matrix'!I$30)*$W$2*$AD$2+'Demand Base Matrix'!I$31*$W$2*$AD$2*$AE$2+'Demand Base Matrix'!I$33+'Demand Base Matrix'!I$34*$AF$2),IF($C22="Bond",(('Demand Base Matrix'!I$55+'Demand Base Matrix'!I$59)*$AC$2*$AD$2*$AE$2+('Demand Base Matrix'!I$56+'Demand Base Matrix'!I$57)*$W$2*$AD$2+'Demand Base Matrix'!I$58*$W$2*$AD$2*$AE$2+'Demand Base Matrix'!I$60+'Demand Base Matrix'!I$61*$AF$2),IF($C22="Explore",('Demand Base Matrix'!I$82*$AC$2*$AD$2*$AE$2*$AF$2+'Demand Base Matrix'!I$83*$W$2*$AC$2*$AD$2*$AE$2*$AF$2+'Demand Base Matrix'!I$84))))) -> 8 | AM22: =IF($C22="Validate",(('Demand Base Matrix'!J$2+'Demand Base Matrix'!J$6)*$AC$2*$AD$2*$AE$2+('Demand Base Matrix'!J$3+'Demand Base Matrix'!J$4)*$W$2*$AD$2+'Demand Base Matrix'!J$5*$W$2*$AD$2*$AE$2+'Demand Base Matrix'!J$7+'Demand Base Matrix'!J$8*$AF$2),IF($C22="Integrate",(('Demand Base Matrix'!J$28+'Demand Base Matrix'!J$32)*$AC$2*$AD$2*$AE$2+('Demand Base Matrix'!J$29+'Demand Base Matrix'!J$30)*$W$2*$AD$2+'Demand Base Matrix'!J$31*$W$2*$AD$2*$AE$2+'Demand Base Matrix'!J$33+'Demand Base Matrix'!J$34*$AF$2),IF($C22="Bond",(('Demand Base Matrix'!J$55+'Demand Base Matrix'!J$59)*$AC$2*$AD$2*$AE$2+('Demand Base Matrix'!J$56+'Demand Base Matrix'!J$57)*$W$2*$AD$2+'Demand Base Matrix'!J$58*$W$2*$AD$2*$AE$2+'Demand Base Matrix'!J$60+'Demand Base Matrix'!J$61*$AF$2),IF($C22="Explore",('Demand Base Matrix'!J$82*$AC$2*$AD$2*$AE$2*$AF$2+'Demand Base Matrix'!J$83*$W$2*$AC$2*$AD$2*$AE$2*$AF$2+'Demand Base Matrix'!J$84))))) -> 8
A23: [2026 SaaS Y2] Dominion Energy | B23: Dominion Energy | C23: Integrate | D23: Isabella Espinel | E23: Mannat Padha | F23: Sarthak Goyal | I23: =IFERROR(INDEX('Customer 360'!F:F,MATCH(B23,'Customer 360'!A:A,0)),"-") -> NA | J23: 5000 | L23: 46307 | M23: 46307 | N23: 2026 | O23: 46023 | P23: IVMS | Q23: =O23 -> 46023 | R23: =IFERROR(IF(M23<>"",M23,IF(L23<>"",L23,INDEX('CSM RDD'!B:B,MATCH(B23,'CSM RDD'!A:A,0)))),"-") -> 46307 | S23: =IFERROR(EOMONTH(Q23,-1)+1,"") -> 46023 | T23: =IFERROR(EOMONTH(R23,-1)+1,"") -> 46296 | U23: =J23+K23 -> 5000 | V23: =IF(C23<>"Validate",DATE(2026,3,1),O23) -> 46082 | W23: =IF(U23=0,1,IF(U23<='Demand Base Matrix'!$K$3,'Demand Base Matrix'!$L$3,IF(U23<='Demand Base Matrix'!$K$4,'Demand Base Matrix'!$L$4,IF(U23<='Demand Base Matrix'!$K$5,'Demand Base Matrix'!$L$5,IF(U23<='Demand Base Matrix'!$K$6,'Demand Base Matrix'!$L$6,IF(U23<='Demand Base Matrix'!$K$7,'Demand Base Matrix'!$L$7)))))) -> 1 | X23: =DATE(YEAR(R23),MONTH(R23),1) -> 46296 | Y23: =IF(K23>0,"Tx","Dx") -> Dx | Z23: Low | AA23: Medium | AB23: Low | AC23: =IFERROR(INDEX('Demand Base Matrix'!AM:AM,MATCH(Y23,'Demand Base Matrix'!AL:AL,0)),"-") -> 1 | AD23: =IFERROR(INDEX('Demand Base Matrix'!AO:AO,MATCH(Z23,'Demand Base Matrix'!AN:AN,0)),1) -> 1 | AE23: =IFERROR(INDEX('Demand Base Matrix'!AQ:AQ,MATCH(AA23,'Demand Base Matrix'!AP:AP,0)),1) -> 1.5 | AF23: =IFERROR(INDEX('Demand Base Matrix'!AS:AS,MATCH(AB23,'Demand Base Matrix'!AR:AR,0)),1) -> 1 | AG23: =IF($C23="Validate",(('Demand Base Matrix'!D$2+'Demand Base Matrix'!D$6)*$AC$2*$AD$2*$AE$2+('Demand Base Matrix'!D$3+'Demand Base Matrix'!D$4)*$W$2*$AD$2+'Demand Base Matrix'!D$5*$W$2*$AD$2*$AE$2+'Demand Base Matrix'!D$7+'Demand Base Matrix'!D$8*$AF$2),IF($C23="Integrate",(('Demand Base Matrix'!D$28+'Demand Base Matrix'!D$32)*$AC$2*$AD$2*$AE$2+('Demand Base Matrix'!D$29+'Demand Base Matrix'!D$30)*$W$2*$AD$2+'Demand Base Matrix'!D$31*$W$2*$AD$2*$AE$2+'Demand Base Matrix'!D$33+'Demand Base Matrix'!D$34*$AF$2),IF($C23="Bond",(('Demand Base Matrix'!D$55+'Demand Base Matrix'!D$59)*$AC$2*$AD$2*$AE$2+('Demand Base Matrix'!D$56+'Demand Base Matrix'!D$57)*$W$2*$AD$2+'Demand Base Matrix'!D$58*$W$2*$AD$2*$AE$2+'Demand Base Matrix'!D$60+'Demand Base Matrix'!D$61*$AF$2),IF($C23="Explore",('Demand Base Matrix'!D$82*$AC$2*$AD$2*$AE$2*$AF$2+'Demand Base Matrix'!D$83*$W$2*$AC$2*$AD$2*$AE$2*$AF$2+'Demand Base Matrix'!D$84))))) -> 10 | AH23: =IF($C23="Validate",(('Demand Base Matrix'!E$2+'Demand Base Matrix'!E$6)*$AC$2*$AD$2*$AE$2+('Demand Base Matrix'!E$3+'Demand Base Matrix'!E$4)*$W$2*$AD$2+'Demand Base Matrix'!E$5*$W$2*$AD$2*$AE$2+'Demand Base Matrix'!E$7+'Demand Base Matrix'!E$8*$AF$2),IF($C23="Integrate",(('Demand Base Matrix'!E$28+'Demand Base Matrix'!E$32)*$AC$2*$AD$2*$AE$2+('Demand Base Matrix'!E$29+'Demand Base Matrix'!E$30)*$W$2*$AD$2+'Demand Base Matrix'!E$31*$W$2*$AD$2*$AE$2+'Demand Base Matrix'!E$33+'Demand Base Matrix'!E$34*$AF$2),IF($C23="Bond",(('Demand Base Matrix'!E$55+'Demand Base Matrix'!E$59)*$AC$2*$AD$2*$AE$2+('Demand Base Matrix'!E$56+'Demand Base Matrix'!E$57)*$W$2*$AD$2+'Demand Base Matrix'!E$58*$W$2*$AD$2*$AE$2+'Demand Base Matrix'!E$60+'Demand Base Matrix'!E$61*$AF$2),IF($C23="Explore",('Demand Base Matrix'!E$82*$AC$2*$AD$2*$AE$2*$AF$2+'Demand Base Matrix'!E$83*$W$2*$AC$2*$AD$2*$AE$2*$AF$2+'Demand Base Matrix'!E$84))))) -> 20 | AI23: =IF($C23="Validate",(('Demand Base Matrix'!F$2+'Demand Base Matrix'!F$6)*$AC$2*$AD$2*$AE$2+('Demand Base Matrix'!F$3+'Demand Base Matrix'!F$4)*$W$2*$AD$2+'Demand Base Matrix'!F$5*$W$2*$AD$2*$AE$2+'Demand Base Matrix'!F$7+'Demand Base Matrix'!F$8*$AF$2),IF($C23="Integrate",(('Demand Base Matrix'!F$28+'Demand Base Matrix'!F$32)*$AC$2*$AD$2*$AE$2+('Demand Base Matrix'!F$29+'Demand Base Matrix'!F$30)*$W$2*$AD$2+'Demand Base Matrix'!F$31*$W$2*$AD$2*$AE$2+'Demand Base Matrix'!F$33+'Demand Base Matrix'!F$34*$AF$2),IF($C23="Bond",(('Demand Base Matrix'!F$55+'Demand Base Matrix'!F$59)*$AC$2*$AD$2*$AE$2+('Demand Base Matrix'!F$56+'Demand Base Matrix'!F$57)*$W$2*$AD$2+'Demand Base Matrix'!F$58*$W$2*$AD$2*$AE$2+'Demand Base Matrix'!F$60+'Demand Base Matrix'!F$61*$AF$2),IF($C23="Explore",('Demand Base Matrix'!F$82*$AC$2*$AD$2*$AE$2*$AF$2+'Demand Base Matrix'!F$83*$W$2*$AC$2*$AD$2*$AE$2*$AF$2+'Demand Base Matrix'!F$84))))) -> 10 | AJ23: =IF($C23="Validate",(('Demand Base Matrix'!G$2+'Demand Base Matrix'!G$6)*$AC$2*$AD$2*$AE$2+('Demand Base Matrix'!G$3+'Demand Base Matrix'!G$4)*$W$2*$AD$2+'Demand Base Matrix'!G$5*$W$2*$AD$2*$AE$2+'Demand Base Matrix'!G$7+'Demand Base Matrix'!G$8*$AF$2),IF($C23="Integrate",(('Demand Base Matrix'!G$28+'Demand Base Matrix'!G$32)*$AC$2*$AD$2*$AE$2+('Demand Base Matrix'!G$29+'Demand Base Matrix'!G$30)*$W$2*$AD$2+'Demand Base Matrix'!G$31*$W$2*$AD$2*$AE$2+'Demand Base Matrix'!G$33+'Demand Base Matrix'!G$34*$AF$2),IF($C23="Bond",(('Demand Base Matrix'!G$55+'Demand Base Matrix'!G$59)*$AC$2*$AD$2*$AE$2+('Demand Base Matrix'!G$56+'Demand Base Matrix'!G$57)*$W$2*$AD$2+'Demand Base Matrix'!G$58*$W$2*$AD$2*$AE$2+'Demand Base Matrix'!G$60+'Demand Base Matrix'!G$61*$AF$2),IF($C23="Explore",('Demand Base Matrix'!G$82*$AC$2*$AD$2*$AE$2*$AF$2+'Demand Base Matrix'!G$83*$W$2*$AC$2*$AD$2*$AE$2*$AF$2+'Demand Base Matrix'!G$84))))) -> 60 | AK23: =IF($C23="Validate",(('Demand Base Matrix'!H$2+'Demand Base Matrix'!H$6)*$AC$2*$AD$2*$AE$2+('Demand Base Matrix'!H$3+'Demand Base Matrix'!H$4)*$W$2*$AD$2+'Demand Base Matrix'!H$5*$W$2*$AD$2*$AE$2+'Demand Base Matrix'!H$7+'Demand Base Matrix'!H$8*$AF$2),IF($C23="Integrate",(('Demand Base Matrix'!H$28+'Demand Base Matrix'!H$32)*$AC$2*$AD$2*$AE$2+('Demand Base Matrix'!H$29+'Demand Base Matrix'!H$30)*$W$2*$AD$2+'Demand Base Matrix'!H$31*$W$2*$AD$2*$AE$2+'Demand Base Matrix'!H$33+'Demand Base Matrix'!H$34*$AF$2),IF($C23="Bond",(('Demand Base Matrix'!H$55+'Demand Base Matrix'!H$59)*$AC$2*$AD$2*$AE$2+('Demand Base Matrix'!H$56+'Demand Base Matrix'!H$57)*$W$2*$AD$2+'Demand Base Matrix'!H$58*$W$2*$AD$2*$AE$2+'Demand Base Matrix'!H$60+'Demand Base Matrix'!H$61*$AF$2),IF($C23="Explore",('Demand Base Matrix'!H$82*$AC$2*$AD$2*$AE$2*$AF$2+'Demand Base Matrix'!H$83*$W$2*$AC$2*$AD$2*$AE$2*$AF$2+'Demand Base Matrix'!H$84))))) -> 28 | AL23: =IF($C23="Validate",(('Demand Base Matrix'!I$2+'Demand Base Matrix'!I$6)*$AC$2*$AD$2*$AE$2+('Demand Base Matrix'!I$3+'Demand Base Matrix'!I$4)*$W$2*$AD$2+'Demand Base Matrix'!I$5*$W$2*$AD$2*$AE$2+'Demand Base Matrix'!I$7+'Demand Base Matrix'!I$8*$AF$2),IF($C23="Integrate",(('Demand Base Matrix'!I$28+'Demand Base Matrix'!I$32)*$AC$2*$AD$2*$AE$2+('Demand Base Matrix'!I$29+'Demand Base Matrix'!I$30)*$W$2*$AD$2+'Demand Base Matrix'!I$31*$W$2*$AD$2*$AE$2+'Demand Base Matrix'!I$33+'Demand Base Matrix'!I$34*$AF$2),IF($C23="Bond",(('Demand Base Matrix'!I$55+'Demand Base Matrix'!I$59)*$AC$2*$AD$2*$AE$2+('Demand Base Matrix'!I$56+'Demand Base Matrix'!I$57)*$W$2*$AD$2+'Demand Base Matrix'!I$58*$W$2*$AD$2*$AE$2+'Demand Base Matrix'!I$60+'Demand Base Matrix'!I$61*$AF$2),IF($C23="Explore",('Demand Base Matrix'!I$82*$AC$2*$AD$2*$AE$2*$AF$2+'Demand Base Matrix'!I$83*$W$2*$AC$2*$AD$2*$AE$2*$AF$2+'Demand Base Matrix'!I$84))))) -> 8 | AM23: =IF($C23="Validate",(('Demand Base Matrix'!J$2+'Demand Base Matrix'!J$6)*$AC$2*$AD$2*$AE$2+('Demand Base Matrix'!J$3+'Demand Base Matrix'!J$4)*$W$2*$AD$2+'Demand Base Matrix'!J$5*$W$2*$AD$2*$AE$2+'Demand Base Matrix'!J$7+'Demand Base Matrix'!J$8*$AF$2),IF($C23="Integrate",(('Demand Base Matrix'!J$28+'Demand Base Matrix'!J$32)*$AC$2*$AD$2*$AE$2+('Demand Base Matrix'!J$29+'Demand Base Matrix'!J$30)*$W$2*$AD$2+'Demand Base Matrix'!J$31*$W$2*$AD$2*$AE$2+'Demand Base Matrix'!J$33+'Demand Base Matrix'!J$34*$AF$2),IF($C23="Bond",(('Demand Base Matrix'!J$55+'Demand Base Matrix'!J$59)*$AC$2*$AD$2*$AE$2+('Demand Base Matrix'!J$56+'Demand Base Matrix'!J$57)*$W$2*$AD$2+'Demand Base Matrix'!J$58*$W$2*$AD$2*$AE$2+'Demand Base Matrix'!J$60+'Demand Base Matrix'!J$61*$AF$2),IF($C23="Explore",('Demand Base Matrix'!J$82*$AC$2*$AD$2*$AE$2*$AF$2+'Demand Base Matrix'!J$83*$W$2*$AC$2*$AD$2*$AE$2*$AF$2+'Demand Base Matrix'!J$84))))) -> 8
